Workbook

Sheet Respuestas de formulario 1
A1: Marca temporal | B1: Apellido | C1: Nombre | D1: e-mail | E1: Fecha de nacimiento | F1: DNI | G1: Teléfono | H1: ¿Cómo nos encontraste? | I1: ¿Cómo te vas a atender? | J1: ¿Cuál es tu obra social? | K1: ¿Realizás actividad física? | L1: ¿Qué actividad física realizás? | M1: ¿Cuántas veces por semana entrenás? | N1: ¿Cómo te vas a atender? | O1: ¿Cuál es tu obra social? | Q1: ¿Realizás activad física? | R1: FUENTE | S1: AÑO | T1: MES
A2: 44865.663 | B2: Llanos | C2: Cristian | D2: Cristian_kobe@hotmail.com | E2: 31427 | F2: 32099118 | G2: 3518046736 | H2: Google | I2: Obra social | J2: APROSS | R2: =IF(H2="","",VLOOKUP(H2,'Hoja 9'!$A$1:$B$255,2,0)) -> GOOGLE | S2: =IF(A2="","",YEAR(A2)) -> 2022 | T2: =IF(A2="","",MONTH(A2)) -> 10
A3: 44866.425 | B3: Leiva | C3: Nilda Carolina | D3: caroagus023@gmail.com | E3: 29208 | F3: 27671982 | G3: 3513844529 | H3: Recomendación | I3: Particular | R3: =IF(H3="","",VLOOKUP(H3,'Hoja 9'!$A$1:$B$255,2,0)) -> BOCA EN BOCA | S3: =IF(A3="","",YEAR(A3)) -> 2022 | T3: =IF(A3="","",MONTH(A3)) -> 11
A4: 44872.859 | B4: Far | C4: Juan Manuel | D4: Manufar87@hotmail.com | E4: 31894 | F4: 33082576 | G4: 3512006711 | H4: Recomendación | I4: Particular | R4: =IF(H4="","",VLOOKUP(H4,'Hoja 9'!$A$1:$B$255,2,0)) -> BOCA EN BOCA | S4: =IF(A4="","",YEAR(A4)) -> 2022 | T4: =IF(A4="","",MONTH(A4)) -> 11
A5: 44879.654 | B5: Urquía | C5: Yohana | D5: yohana.urquia@gmail.com | E5: 31206 | F5: 31647631 | G5: 3516299562 | H5: Recomendación | I5: Particular | R5: =IF(H5="","",VLOOKUP(H5,'Hoja 9'!$A$1:$B$255,2,0)) -> BOCA EN BOCA | S5: =IF(A5="","",YEAR(A5)) -> 2022 | T5: =IF(A5="","",MONTH(A5)) -> 11
A6: 44879.671 | B6: Lopez | C6: Gonzalo Daniel | D6: Zonlopez10@gmail.com | E6: 34623 | F6: 38501250 | G6: 3515186768 | H6: Lo conozco al fabri de defensores | I6: Obra social | J6: APROSS | R6: =IF(H6="","",VLOOKUP(H6,'Hoja 9'!$A$1:$B$255,2,0)) -> BOCA EN BOCA | S6: =IF(A6="","",YEAR(A6)) -> 2022 | T6: =IF(A6="","",MONTH(A6)) -> 11
A7: 44880.471 | B7: Agüero | C7: Juan Manuel | D7: juanmamendiolaza@gmail.com | E7: 31846 | F7: 32787354 | G7: 3516219534 | H7: Google | I7: Particular | R7: =IF(H7="","",VLOOKUP(H7,'Hoja 9'!$A$1:$B$255,2,0)) -> GOOGLE | S7: =IF(A7="","",YEAR(A7)) -> 2022 | T7: =IF(A7="","",MONTH(A7)) -> 11
A8: 44880.5 | B8: Valdez | C8: Rubén | D8: Rubenavaldez930@gmail.com | E8: 34161 | F8: 37733188 | G8: 3513374771 | H8: Voy al gym Manantial | J8: APROSS | R8: =IF(H8="","",VLOOKUP(H8,'Hoja 9'!$A$1:$B$255,2,0)) -> GIMNASIO | S8: =IF(A8="","",YEAR(A8)) -> 2022 | T8: =IF(A8="","",MONTH(A8)) -> 11
A9: 44881.413 | B9: Giménez | C9: Fernando | D9: gimenezfa@gmail.com | E9: 35171 | F9: 30544064 | G9: 3516953672 | H9: Recomendación | I9: Obra social | J9: APROSS | R9: =IF(H9="","",VLOOKUP(H9,'Hoja 9'!$A$1:$B$255,2,0)) -> BOCA EN BOCA | S9: =IF(A9="","",YEAR(A9)) -> 2022 | T9: =IF(A9="","",MONTH(A9)) -> 11
A10: 44881.491 | B10: JOHNSON | C10: GUILLERMO | D10: guillermorjohnson@gmail.com | E10: 26996 | F10: 23683982 | G10: 3515138062 | H10: Recomendación | I10: Obra social | J10: caja Notarial | R10: =IF(H10="","",VLOOKUP(H10,'Hoja 9'!$A$1:$B$255,2,0)) -> BOCA EN BOCA | S10: =IF(A10="","",YEAR(A10)) -> 2022 | T10: =IF(A10="","",MONTH(A10)) -> 11
A11: 44881.688 | B11: Carnevale | C11: Mariela | D11: marielacarnevale533@hotmail.com | E11: 29629 | F11: 23683982 | G11: 3513040216 | H11: Google | I11: Particular | R11: =IF(H11="","",VLOOKUP(H11,'Hoja 9'!$A$1:$B$255,2,0)) -> GOOGLE | S11: =IF(A11="","",YEAR(A11)) -> 2022 | T11: =IF(A11="","",MONTH(A11)) -> 11
A12: 44882.46 | B12: Isa Minuet | C12: Elías | D12: eliasisaa@gmail.com | E12: 36108 | F12: 41019335 | G12: 3517580512 | H12: Voy al gym Manantial | I12: Obra social | J12: SANCOR | R12: =IF(H12="","",VLOOKUP(H12,'Hoja 9'!$A$1:$B$255,2,0)) -> GIMNASIO | S12: =IF(A12="","",YEAR(A12)) -> 2022 | T12: =IF(A12="","",MONTH(A12)) -> 11
A13: 44888.414 | B13: Ghibaudo | C13: Pablo | D13: lic.pabloghibaudo@gmail.com | E13: 29137 | F13: 27267620 | G13: 3515528353 | H13: Google | I13: Obra social | J13: APROSS | R13: =IF(H13="","",VLOOKUP(H13,'Hoja 9'!$A$1:$B$255,2,0)) -> GOOGLE | S13: =IF(A13="","",YEAR(A13)) -> 2022 | T13: =IF(A13="","",MONTH(A13)) -> 11
A14: 44889.821 | B14: Asinari | C14: Emanuel | D14: lic.pabloghibaudo@gmail.com | E14: 34338 | F14: 38001813 | G14: 3516098550 | H14: Soy amigo de la feliz pareja | I14: Particular | R14: =IF(H14="","",VLOOKUP(H14,'Hoja 9'!$A$1:$B$255,2,0)) -> BOCA EN BOCA | S14: =IF(A14="","",YEAR(A14)) -> 2022 | T14: =IF(A14="","",MONTH(A14)) -> 11
A15: 44890.799 | B15: Rivara | C15: Mauro Alejandro | D15: rivaramauro@hotmail.com | E15: 22514 | F15: 14747390 | G15: 3516536874 | H15: Recomendación | I15: Obra social | J15: CPCE | R15: =IF(H15="","",VLOOKUP(H15,'Hoja 9'!$A$1:$B$255,2,0)) -> BOCA EN BOCA | S15: =IF(A15="","",YEAR(A15)) -> 2022 | T15: =IF(A15="","",MONTH(A15)) -> 11
A16: 44891.475 | B16: Andino | C16: Guillermo Regino | D16: puchiandino1@gmail.com | E16: 37207 | F16: 43693789 | G16: 3517014316 | H16: Recomendación | I16: Obra social | J16: DASPU | R16: =IF(H16="","",VLOOKUP(H16,'Hoja 9'!$A$1:$B$255,2,0)) -> BOCA EN BOCA | S16: =IF(A16="","",YEAR(A16)) -> 2022 | T16: =IF(A16="","",MONTH(A16)) -> 11
A17: 44893.471 | B17: MUÑOZ | C17: Emery omar | D17: escribaniamunoz@gmail.com | E17: 28950 | F17: 27303587 | G17: 3513493623 | H17: Voy al gym Manantial | I17: Obra social | J17: CAJA NOTARIAL | R17: =IF(H17="","",VLOOKUP(H17,'Hoja 9'!$A$1:$B$255,2,0)) -> GIMNASIO | S17: =IF(A17="","",YEAR(A17)) -> 2022 | T17: =IF(A17="","",MONTH(A17)) -> 11
A18: 44893.501 | B18: Boasso | C18: Lucas | D18: sosamariapia@hotmail.com | E18: 42410 | F18: 55011829 | G18: 3516280350 | H18: Google | I18: Obra social | J18: APROSS | R18: =IF(H18="","",VLOOKUP(H18,'Hoja 9'!$A$1:$B$255,2,0)) -> GOOGLE | S18: =IF(A18="","",YEAR(A18)) -> 2022 | T18: =IF(A18="","",MONTH(A18)) -> 11
A19: 44895.838 | B19: Druetta | C19: Joaquín | D19: joadruetta@gmail.com | E19: 35936 | F19: 4081605 | G19: 3513861638 | H19: Recomendación | I19: Particular | R19: =IF(H19="","",VLOOKUP(H19,'Hoja 9'!$A$1:$B$255,2,0)) -> BOCA EN BOCA | S19: =IF(A19="","",YEAR(A19)) -> 2022 | T19: =IF(A19="","",MONTH(A19)) -> 11
A20: 44897.848 | B20: Hilbe | C20: Estela | D20: Estelahilbe5@hotmail.com | E20: 19420 | F20: 10756516 | G20: 3513123179 | H20: Recomendación | I20: Obra social | J20: Jerarquico salud | R20: =IF(H20="","",VLOOKUP(H20,'Hoja 9'!$A$1:$B$255,2,0)) -> BOCA EN BOCA | S20: =IF(A20="","",YEAR(A20)) -> 2022 | T20: =IF(A20="","",MONTH(A20)) -> 12
A21: 44901.883 | B21: Conrero | C21: Valentino | D21: vconrero@gmail.com | E21: 37698 | F21: 44694075 | G21: 3515290969 | H21: Google | I21: Obra social | J21: Medifé | R21: =IF(H21="","",VLOOKUP(H21,'Hoja 9'!$A$1:$B$255,2,0)) -> GOOGLE | S21: =IF(A21="","",YEAR(A21)) -> 2022 | T21: =IF(A21="","",MONTH(A21)) -> 12
A22: 44902.416 | B22: Gonzalez | C22: Nicolas | D22: Nicomatigonzalez@hotmail.com | E22: 34786 | F22: 38749170 | G22: 3512558234 | H22: Recomendación | I22: Particular | R22: =IF(H22="","",VLOOKUP(H22,'Hoja 9'!$A$1:$B$255,2,0)) -> BOCA EN BOCA | S22: =IF(A22="","",YEAR(A22)) -> 2022 | T22: =IF(A22="","",MONTH(A22)) -> 12
A23: 44907.7 | B23: Araujo | C23: Dora Susana | D23: sietejuana@gmail.com | E23: 16564 | F23: 4647485 | G23: 3513503636 | H23: Recomendación | I23: Obra social | J23: APROSS | R23: =IF(H23="","",VLOOKUP(H23,'Hoja 9'!$A$1:$B$255,2,0)) -> BOCA EN BOCA | S23: =IF(A23="","",YEAR(A23)) -> 2022 | T23: =IF(A23="","",MONTH(A23)) -> 12
A24: 44908.351 | B24: Boasi | C24: Ivana | D24: ivanaboasi@gmail.com | E24: 30556 | F24: 30469315 | G24: 3513732026 | H24: Voy al gym Manantial | I24: Particular | R24: =IF(H24="","",VLOOKUP(H24,'Hoja 9'!$A$1:$B$255,2,0)) -> GIMNASIO | S24: =IF(A24="","",YEAR(A24)) -> 2022 | T24: =IF(A24="","",MONTH(A24)) -> 12
A25: 44908.902 | B25: Ferreyra | C25: Ariel | D25: ariel.jferreyra@gmail.com | E25: ramos | F25: 24356325 | G25: 3516535435 | H25: Recomendación | I25: Obra social | R25: =IF(H25="","",VLOOKUP(H25,'Hoja 9'!$A$1:$B$255,2,0)) -> BOCA EN BOCA | S25: =IF(A25="","",YEAR(A25)) -> 2022 | T25: =IF(A25="","",MONTH(A25)) -> 12
A26: 44909.906 | B26: Baena | C26: Gustavo Ariel | D26: arielbaena@hotmail.com.ar | E26: 26901 | F26: 23440420 | G26: 3516419517 | H26: Recomendación | I26: Obra social | J26: APROSS | R26: =IF(H26="","",VLOOKUP(H26,'Hoja 9'!$A$1:$B$255,2,0)) -> BOCA EN BOCA | S26: =IF(A26="","",YEAR(A26)) -> 2022 | T26: =IF(A26="","",MONTH(A26)) -> 12
A27: 44911.649 | B27: Lozano | C27: Ezequiel | D27: ezelozano7@gmail.com | E27: 34581 | F27: 38412070 | G27: 3517384848 | H27: Recomendación | I27: Particular | R27: =IF(H27="","",VLOOKUP(H27,'Hoja 9'!$A$1:$B$255,2,0)) -> BOCA EN BOCA | S27: =IF(A27="","",YEAR(A27)) -> 2022 | T27: =IF(A27="","",MONTH(A27)) -> 12
A28: 44918.476 | B28: Lazcano | C28: Stella | E28: 16642 | F28: 5210099 | G28: 3512757694 | H28: Google | I28: Obra social | J28: APROSS | R28: =IF(H28="","",VLOOKUP(H28,'Hoja 9'!$A$1:$B$255,2,0)) -> GOOGLE | S28: =IF(A28="","",YEAR(A28)) -> 2022 | T28: =IF(A28="","",MONTH(A28)) -> 12
A29: 44920.965 | B29: Accornero | C29: Ignacio | D29: nachoaccornero@hotmail.com | E29: 35767 | F29: 40815684 | G29: 665987371 | H29: Recomendación | I29: Particular | R29: =IF(H29="","",VLOOKUP(H29,'Hoja 9'!$A$1:$B$255,2,0)) -> BOCA EN BOCA | S29: =IF(A29="","",YEAR(A29)) -> 2022 | T29: =IF(A29="","",MONTH(A29)) -> 12
A30: 44921.73 | B30: Ortelli | C30: Esther | D30: esther.tarantino@hotmail.com | E30: 16144 | F30: 4789045 | G30: 3515306152 | H30: Google | I30: Obra social | J30: CPCE | R30: =IF(H30="","",VLOOKUP(H30,'Hoja 9'!$A$1:$B$255,2,0)) -> GOOGLE | S30: =IF(A30="","",YEAR(A30)) -> 2022 | T30: =IF(A30="","",MONTH(A30)) -> 12
A31: 44923.411 | B31: Sibona | C31: Karina | D31: karinasibona@hotmail.com | E31: 26650 | F31: 22795191 | G31: 3512588741 | H31: Google | I31: Obra social | J31: CPCE | R31: =IF(H31="","",VLOOKUP(H31,'Hoja 9'!$A$1:$B$255,2,0)) -> GOOGLE | S31: =IF(A31="","",YEAR(A31)) -> 2022 | T31: =IF(A31="","",MONTH(A31)) -> 12
A32: 44923.412 | B32: Pepi | C32: Bettina | D32: karinasibona@hotmail.com | E32: 41264 | F32: 52466966 | G32: 3512588741 | H32: Google | I32: Obra social | J32: CPCE | R32: =IF(H32="","",VLOOKUP(H32,'Hoja 9'!$A$1:$B$255,2,0)) -> GOOGLE | S32: =IF(A32="","",YEAR(A32)) -> 2022 | T32: =IF(A32="","",MONTH(A32)) -> 12
A33: 44924.73 | B33: Cardoni | C33: Gino | D33: gino.baret@gmail.com | E33: 31877 | F33: 33117511 | G33: 3512287296 | H33: Recomendación | I33: Particular | R33: =IF(H33="","",VLOOKUP(H33,'Hoja 9'!$A$1:$B$255,2,0)) -> BOCA EN BOCA | S33: =IF(A33="","",YEAR(A33)) -> 2022 | T33: =IF(A33="","",MONTH(A33)) -> 12
A34: 44924.838 | B34: Gutiérrez | C34: Ángela nora | D34: angelanoragutierrez03@gmail.com | E34: 18600 | F34: 6259516 | G34: 3512484269 | H34: Google | I34: Obra social | J34: APROSS | R34: =IF(H34="","",VLOOKUP(H34,'Hoja 9'!$A$1:$B$255,2,0)) -> GOOGLE | S34: =IF(A34="","",YEAR(A34)) -> 2022 | T34: =IF(A34="","",MONTH(A34)) -> 12
A35: 44926.812 | B35: Heredia Pereyra | C35: Mercedes Andrea | D35: mercedesahp@hotmail.com | E35: 29279 | F35: 27955896 | G35: 3513401354 | H35: Recomendación | I35: Obra social | J35: APROSS | R35: =IF(H35="","",VLOOKUP(H35,'Hoja 9'!$A$1:$B$255,2,0)) -> BOCA EN BOCA | S35: =IF(A35="","",YEAR(A35)) -> 2022 | T35: =IF(A35="","",MONTH(A35)) -> 12
A36: 44928.448 | B36: Perini | C36: Leonardo | D36: Lf04_cba@hotmail.com | E36: 32451 | F36: 34069704 | G36: 3512615886 | H36: Google | I36: Particular | R36: =IF(H36="","",VLOOKUP(H36,'Hoja 9'!$A$1:$B$255,2,0)) -> GOOGLE | S36: =IF(A36="","",YEAR(A36)) -> 2023 | T36: =IF(A36="","",MONTH(A36)) -> 1
A37: 44928.826 | B37: Brun | C37: Luciano | D37: lucianobrun@hotmail.com | E37: 29722 | F37: 28850950 | G37: 3513904324 | H37: Voy al gym Manantial | I37: Particular | R37: =IF(H37="","",VLOOKUP(H37,'Hoja 9'!$A$1:$B$255,2,0)) -> GIMNASIO | S37: =IF(A37="","",YEAR(A37)) -> 2023 | T37: =IF(A37="","",MONTH(A37)) -> 1
A38: 44930.686 | B38: Dolivo | C38: Josefina | D38: dolivojosefina@gmail.com | E38: 33208 | F38: 35564552 | G38: 3525454941 | H38: Recomendación | I38: Obra social | J38: SANCOR | R38: =IF(H38="","",VLOOKUP(H38,'Hoja 9'!$A$1:$B$255,2,0)) -> BOCA EN BOCA | S38: =IF(A38="","",YEAR(A38)) -> 2023 | T38: =IF(A38="","",MONTH(A38)) -> 1
A39: 44930.971 | B39: LASTRA | C39: MELISA | D39: MELISALASTRA@GMAIL.COM | E39: 32449 | F39: 33976093 | G39: 3512441614 | H39: Voy al gym Manantial | I39: Obra social | J39: A.P.M | R39: =IF(H39="","",VLOOKUP(H39,'Hoja 9'!$A$1:$B$255,2,0)) -> GIMNASIO | S39: =IF(A39="","",YEAR(A39)) -> 2023 | T39: =IF(A39="","",MONTH(A39)) -> 1
A40: 44932.671 | B40: Menzi | C40: Antonio | D40: tony.menzi@gmail.com | E40: 35720 | F40: 40686489 | G40: 3512064245 | H40: Cartilla Obra Social | I40: Obra social | J40: PREVENCIÓN | R40: =IF(H40="","",VLOOKUP(H40,'Hoja 9'!$A$1:$B$255,2,0)) -> OBRA SOCIAL | S40: =IF(A40="","",YEAR(A40)) -> 2023 | T40: =IF(A40="","",MONTH(A40)) -> 1
A41: 44935.811 | B41: MARQUEZ | C41: ELENA BEATRIZ | D41: elenabeatrizmarquez@g.mail.com | E41: 20145 | F41: 11745268 | G41: 3512770181 | H41: Recomendación | I41: Obra social | J41: APROSS | R41: =IF(H41="","",VLOOKUP(H41,'Hoja 9'!$A$1:$B$255,2,0)) -> BOCA EN BOCA | S41: =IF(A41="","",YEAR(A41)) -> 2023 | T41: =IF(A41="","",MONTH(A41)) -> 1
A42: 44937.558 | B42: Nievas Acosta | C42: Marcos Daniel | D42: Mnievasacosta@gmail.com | E42: 34033 | F42: 37317203 | G42: 3516558107 | H42: Recomendación | I42: Particular | R42: =IF(H42="","",VLOOKUP(H42,'Hoja 9'!$A$1:$B$255,2,0)) -> BOCA EN BOCA | S42: =IF(A42="","",YEAR(A42)) -> 2023 | T42: =IF(A42="","",MONTH(A42)) -> 1
A43: 44942.87 | B43: Vocos | C43: Lucia | E43: 32574 | F43: 34315567 | G43: 17677271846 | H43: Recomendación | I43: Particular | R43: =IF(H43="","",VLOOKUP(H43,'Hoja 9'!$A$1:$B$255,2,0)) -> BOCA EN BOCA | S43: =IF(A43="","",YEAR(A43)) -> 2023 | T43: =IF(A43="","",MONTH(A43)) -> 1
A44: 44951.763 | B44: Garino | C44: Dario | D44: dariog128@hotmail.com | E44: 32583 | F44: 34247843 | G44: 3515571888 | H44: Recomendación | I44: Particular | R44: =IF(H44="","",VLOOKUP(H44,'Hoja 9'!$A$1:$B$255,2,0)) -> BOCA EN BOCA | S44: =IF(A44="","",YEAR(A44)) -> 2023 | T44: =IF(A44="","",MONTH(A44)) -> 1
A45: 44953.489 | B45: layus | C45: Daniel | D45: dansocias77@gmail.com | E45: 28046 | F45: 26177948 | G45: 3515471689 | H45: Google | I45: Obra social | J45: PREVENCIÓN | R45: =IF(H45="","",VLOOKUP(H45,'Hoja 9'!$A$1:$B$255,2,0)) -> GOOGLE | S45: =IF(A45="","",YEAR(A45)) -> 2023 | T45: =IF(A45="","",MONTH(A45)) -> 1
A46: 44953.495 | B46: Retter | C46: Norma | D46: normaretter@hotmail.com | E46: 18169 | F46: 6132407 | G46: 3513241502 | H46: Recomendación | I46: Obra social | J46: DASPU | R46: =IF(H46="","",VLOOKUP(H46,'Hoja 9'!$A$1:$B$255,2,0)) -> BOCA EN BOCA | S46: =IF(A46="","",YEAR(A46)) -> 2023 | T46: =IF(A46="","",MONTH(A46)) -> 1
A47: 44953.502 | B47: Bracco | C47: Munir | D47: munirbracco@hotmail.com | E47: 27251 | F47: 24088161 | G47: 3515185921 | H47: Recomendación | I47: Obra social | J47: AE San Pedro | R47: =IF(H47="","",VLOOKUP(H47,'Hoja 9'!$A$1:$B$255,2,0)) -> BOCA EN BOCA | S47: =IF(A47="","",YEAR(A47)) -> 2023 | T47: =IF(A47="","",MONTH(A47)) -> 1
A48: 44953.742 | B48: Rodriguez | C48: Reinaldo | D48: Estelahilbe5@hotmail.com | E48: 18352 | F48: 7868456 | G48: 3491464298 | H48: Recomendación | I48: Obra social | J48: Jerarquicos salud | R48: =IF(H48="","",VLOOKUP(H48,'Hoja 9'!$A$1:$B$255,2,0)) -> BOCA EN BOCA | S48: =IF(A48="","",YEAR(A48)) -> 2023 | T48: =IF(A48="","",MONTH(A48)) -> 1
A49: 44956.413 | B49: Vega Machado | C49: Alejandro | D49: alejandro.vega79@gmail.com | E49: 28911 | F49: 27172103 | G49: 3515583969 | H49: Recomendación | I49: Particular | R49: =IF(H49="","",VLOOKUP(H49,'Hoja 9'!$A$1:$B$255,2,0)) -> BOCA EN BOCA | S49: =IF(A49="","",YEAR(A49)) -> 2023 | T49: =IF(A49="","",MONTH(A49)) -> 1
A50: 44957.464 | B50: Vega | C50: Maria belen | E50: 44957 | F50: 31523085 | G50: 3513798148 | H50: Google | I50: Obra social | J50: APROSS | R50: =IF(H50="","",VLOOKUP(H50,'Hoja 9'!$A$1:$B$255,2,0)) -> GOOGLE | S50: =IF(A50="","",YEAR(A50)) -> 2023 | T50: =IF(A50="","",MONTH(A50)) -> 1
A51: 44957.682 | B51: Micheloud | C51: Santiago | D51: caroponce_@hotmail.com | E51: 40598 | F51: 50631375 | G51: 3513287710 | H51: Google | I51: Particular | R51: =IF(H51="","",VLOOKUP(H51,'Hoja 9'!$A$1:$B$255,2,0)) -> GOOGLE | S51: =IF(A51="","",YEAR(A51)) -> 2023 | T51: =IF(A51="","",MONTH(A51)) -> 1
A52: 44957.746 | B52: Palacios | C52: Santiago | D52: santipalacios17@hotmail.com | E52: 36599 | F52: 42697056 | G52: 3516160854 | H52: Google | I52: Particular | R52: =IF(H52="","",VLOOKUP(H52,'Hoja 9'!$A$1:$B$255,2,0)) -> GOOGLE | S52: =IF(A52="","",YEAR(A52)) -> 2023 | T52: =IF(A52="","",MONTH(A52)) -> 1
A53: 44959.758 | B53: Viberti | C53: Carlos | E53: 14333 | F53: 6385089 | G53: 3515385789 | H53: Recomendación | I53: Obra social | J53: APROSS | R53: =IF(H53="","",VLOOKUP(H53,'Hoja 9'!$A$1:$B$255,2,0)) -> BOCA EN BOCA | S53: =IF(A53="","",YEAR(A53)) -> 2023 | T53: =IF(A53="","",MONTH(A53)) -> 2
A54: 44959.82 | B54: Arrieta | C54: Claudio Carlos | D54: ccarrieta@gmail.com | E54: 27145 | F54: 23824551 | G54: 3516137697 | H54: Compañera natación | I54: Obra social | J54: APROSS | R54: =IF(H54="","",VLOOKUP(H54,'Hoja 9'!$A$1:$B$255,2,0)) -> BOCA EN BOCA | S54: =IF(A54="","",YEAR(A54)) -> 2023 | T54: =IF(A54="","",MONTH(A54)) -> 2
A55: 44959.883 | B55: Martinez | C55: Sergio dario | D55: Sergiooomartinezz.@gmail. | E55: 23655 | F55: 17154620 | G55: 3513516889 | H55: Recomendación | I55: Particular | R55: =IF(H55="","",VLOOKUP(H55,'Hoja 9'!$A$1:$B$255,2,0)) -> BOCA EN BOCA | S55: =IF(A55="","",YEAR(A55)) -> 2023 | T55: =IF(A55="","",MONTH(A55)) -> 2
A56: 44960.458 | B56: Ibarra | C56: Marta | D56: draibarrajaramillo@gmail.com | E56: 19122 | F56: 10377891 | G56: 3516505375 | H56: Voy al gym Manantial | I56: Obra social | J56: APROSS | R56: =IF(H56="","",VLOOKUP(H56,'Hoja 9'!$A$1:$B$255,2,0)) -> GIMNASIO | S56: =IF(A56="","",YEAR(A56)) -> 2023 | T56: =IF(A56="","",MONTH(A56)) -> 2
A57: 44960.464 | B57: Avila | C57: Patricia | D57: avilapati@hotmail.com | E57: 21135 | F57: 13597824 | G57: 3512774033 | H57: Recomendación | I57: Obra social | J57: APROSS | R57: =IF(H57="","",VLOOKUP(H57,'Hoja 9'!$A$1:$B$255,2,0)) -> BOCA EN BOCA | S57: =IF(A57="","",YEAR(A57)) -> 2023 | T57: =IF(A57="","",MONTH(A57)) -> 2
A58: 44964.14 | B58: Teran | C58: Emanuel | D58: emanuelterande05@gmail.com | E58: 37330 | F58: 43812470 | G58: 3518137350 | H58: Recomendación | I58: Particular | R58: =IF(H58="","",VLOOKUP(H58,'Hoja 9'!$A$1:$B$255,2,0)) -> BOCA EN BOCA | S58: =IF(A58="","",YEAR(A58)) -> 2023 | T58: =IF(A58="","",MONTH(A58)) -> 2
A59: 44964.713 | B59: Abadie | C59: Raul | D59: raulgabadie@hotmail.com | E59: 27999 | F59: 25281585 | G59: 3516655602 | H59: Google | I59: Particular | R59: =IF(H59="","",VLOOKUP(H59,'Hoja 9'!$A$1:$B$255,2,0)) -> GOOGLE | S59: =IF(A59="","",YEAR(A59)) -> 2023 | T59: =IF(A59="","",MONTH(A59)) -> 2
A60: 44964.886 | B60: Ceballos | C60: José | D60: Jose.maria.ceballos94@gmail.com | E60: 34699 | F60: 38645431 | G60: 3517590683 | H60: Recomendación | I60: Obra social | J60: PREVENCIÓN | R60: =IF(H60="","",VLOOKUP(H60,'Hoja 9'!$A$1:$B$255,2,0)) -> BOCA EN BOCA | S60: =IF(A60="","",YEAR(A60)) -> 2023 | T60: =IF(A60="","",MONTH(A60)) -> 2
A61: 44967.533 | B61: Raffin | C61: Vilma Rosa | D61: vraffin002@gmail.com | E61: 25111 | F61: 20454528 | G61: 3515389887 | H61: Propaganda en noticias | I61: Particular | R61: =IF(H61="","",VLOOKUP(H61,'Hoja 9'!$A$1:$B$255,2,0)) -> GOOGLE | S61: =IF(A61="","",YEAR(A61)) -> 2023 | T61: =IF(A61="","",MONTH(A61)) -> 2
A62: 44970.443 | B62: ICIKSON | C62: Tomas | D62: tomasicikson@gmail.com | E62: 35040 | F62: 40520046 | G62: 3516113790 | H62: Voy al gym Manantial | I62: Particular | R62: =IF(H62="","",VLOOKUP(H62,'Hoja 9'!$A$1:$B$255,2,0)) -> GIMNASIO | S62: =IF(A62="","",YEAR(A62)) -> 2023 | T62: =IF(A62="","",MONTH(A62)) -> 2
A63: 44970.649 | B63: Rios giache | C63: Luciano lucas | D63: Lucianolucasrg98@gmail.com | E63: 35949 | F63: 41279824 | G63: 3512893805 | H63: Cartilla Obra Social | I63: Particular | R63: =IF(H63="","",VLOOKUP(H63,'Hoja 9'!$A$1:$B$255,2,0)) -> OBRA SOCIAL | S63: =IF(A63="","",YEAR(A63)) -> 2023 | T63: =IF(A63="","",MONTH(A63)) -> 2
A64: 44970.799 | B64: Ruiz | C64: Luis | D64: Lruizgalizi@gmail.com | E64: 33653 | F64: 36147980 | G64: 3518142452 | H64: Recomendación | I64: Particular | R64: =IF(H64="","",VLOOKUP(H64,'Hoja 9'!$A$1:$B$255,2,0)) -> BOCA EN BOCA | S64: =IF(A64="","",YEAR(A64)) -> 2023 | T64: =IF(A64="","",MONTH(A64)) -> 2
A65: 44971.425 | B65: Martinez | C65: Joaquin Adolfo | E65: 19629 | F65: 10903673 | G65: 3516566224 | H65: Google | I65: Obra social | J65: APROSS | R65: =IF(H65="","",VLOOKUP(H65,'Hoja 9'!$A$1:$B$255,2,0)) -> GOOGLE | S65: =IF(A65="","",YEAR(A65)) -> 2023 | T65: =IF(A65="","",MONTH(A65)) -> 2
A66: 44971.496 | B66: Inbrechts | C66: Lisett | D66: inbrechts@gmail.com | E66: 31725 | F66: 95826217 | G66: 3513475295 | H66: Google | I66: Particular | R66: =IF(H66="","",VLOOKUP(H66,'Hoja 9'!$A$1:$B$255,2,0)) -> GOOGLE | S66: =IF(A66="","",YEAR(A66)) -> 2023 | T66: =IF(A66="","",MONTH(A66)) -> 2
A67: 44971.499 | B67: Gutiérrez | C67: Ledis | D67: inbrechts@gmail.com | E67: 23350 | F67: 39153938 | G67: 3513475295 | H67: Google | I67: Particular | R67: =IF(H67="","",VLOOKUP(H67,'Hoja 9'!$A$1:$B$255,2,0)) -> GOOGLE | S67: =IF(A67="","",YEAR(A67)) -> 2023 | T67: =IF(A67="","",MONTH(A67)) -> 2
A68: 44972.484 | B68: Galarce | C68: Carlos | D68: Cag1@hotmail.com.ar | E68: 28696 | F68: 26672639 | G68: 3513642210 | H68: Google | I68: Particular | R68: =IF(H68="","",VLOOKUP(H68,'Hoja 9'!$A$1:$B$255,2,0)) -> GOOGLE | S68: =IF(A68="","",YEAR(A68)) -> 2023 | T68: =IF(A68="","",MONTH(A68)) -> 2
A69: 44972.782 | B69: Aisa | C69: Ruben | D69: rubenelderaisa@hotmail.com | E69: 21530 | F69: 12671913 | G69: 3515415895 | H69: Voy al gym Manantial | I69: Particular | R69: =IF(H69="","",VLOOKUP(H69,'Hoja 9'!$A$1:$B$255,2,0)) -> GIMNASIO | S69: =IF(A69="","",YEAR(A69)) -> 2023 | T69: =IF(A69="","",MONTH(A69)) -> 2
A70: 44972.796 | B70: Reyna | C70: Lucas | D70: lucasereyna@gmail.com | E70: 31862 | F70: 32925170 | G70: 3515131485 | H70: Recomendación | I70: Particular | R70: =IF(H70="","",VLOOKUP(H70,'Hoja 9'!$A$1:$B$255,2,0)) -> BOCA EN BOCA | S70: =IF(A70="","",YEAR(A70)) -> 2023 | T70: =IF(A70="","",MONTH(A70)) -> 2
A71: 44974.513 | B71: Quiligotti | C71: Pablo | D71: pabloquiligotti@gmail.com | E71: 30214 | F71: 29706314 | G71: 3516870843 | H71: Recomendación | I71: Obra social | J71: Federada Salud | R71: =IF(H71="","",VLOOKUP(H71,'Hoja 9'!$A$1:$B$255,2,0)) -> BOCA EN BOCA | S71: =IF(A71="","",YEAR(A71)) -> 2023 | T71: =IF(A71="","",MONTH(A71)) -> 2
A72: 44978.723 | B72: Armando | C72: Marcos | D72: marcos.armando1@gmail.com | E72: 32509 | F72: 34130395 | G72: 3513887184 | H72: Google | I72: Particular | R72: =IF(H72="","",VLOOKUP(H72,'Hoja 9'!$A$1:$B$255,2,0)) -> GOOGLE | S72: =IF(A72="","",YEAR(A72)) -> 2023 | T72: =IF(A72="","",MONTH(A72)) -> 2
A73: 44978.802 | B73: Heredia | C73: Andres | D73: andresheredia911@gmail.com | E73: 35500 | F73: 40248804 | G73: 3515331363 | H73: Voy al gym Manantial | I73: Obra social | J73: DASPU | R73: =IF(H73="","",VLOOKUP(H73,'Hoja 9'!$A$1:$B$255,2,0)) -> GIMNASIO | S73: =IF(A73="","",YEAR(A73)) -> 2023 | T73: =IF(A73="","",MONTH(A73)) -> 2
A74: 44979.692 | B74: Sebastián | C74: Octavio | D74: octaviosebastiann@gmail.com | E74: 34072 | F74: 37476306 | G74: 3517060825 | H74: Instagram | I74: Particular | R74: =IF(H74="","",VLOOKUP(H74,'Hoja 9'!$A$1:$B$255,2,0)) -> META | S74: =IF(A74="","",YEAR(A74)) -> 2023 | T74: =IF(A74="","",MONTH(A74)) -> 2
A75: 44979.801 | B75: Fernández | C75: Marcos Gabriel | D75: markosgabriel_1206@hotmail.com | E75: 28653 | F75: 26484703 | G75: 3516324625 | H75: Voy al gym Manantial | I75: Obra social | J75: Apromed | R75: =IF(H75="","",VLOOKUP(H75,'Hoja 9'!$A$1:$B$255,2,0)) -> GIMNASIO | S75: =IF(A75="","",YEAR(A75)) -> 2023 | T75: =IF(A75="","",MONTH(A75)) -> 2
A76: 44985.698 | B76: Cantonati | C76: María Belén | D76: Belcantonati@hotmail.com | E76: 31031 | F76: 31187943 | G76: 3516330590 | H76: Recomendación | I76: Particular | R76: =IF(H76="","",VLOOKUP(H76,'Hoja 9'!$A$1:$B$255,2,0)) -> BOCA EN BOCA | S76: =IF(A76="","",YEAR(A76)) -> 2023 | T76: =IF(A76="","",MONTH(A76)) -> 2
A77: 44986.359 | B77: Druetta | C77: Camila | D77: camidrue@gmail.com | E77: 36796 | F77: 42892997 | G77: 3512024838 | H77: Recomendación | I77: Particular | R77: =IF(H77="","",VLOOKUP(H77,'Hoja 9'!$A$1:$B$255,2,0)) -> BOCA EN BOCA | S77: =IF(A77="","",YEAR(A77)) -> 2023 | T77: =IF(A77="","",MONTH(A77)) -> 3
A78: 44986.474 | B78: CASTRO | C78: Mirta Cristina | D78: micricas@hotmail.com | E78: 26826 | F78: 23198663 | G78: 3516520221 | H78: Recomendación | I78: Obra social | J78: DASPU | R78: =IF(H78="","",VLOOKUP(H78,'Hoja 9'!$A$1:$B$255,2,0)) -> BOCA EN BOCA | S78: =IF(A78="","",YEAR(A78)) -> 2023 | T78: =IF(A78="","",MONTH(A78)) -> 3
A79: 44986.644 | B79: Semeraro | C79: Nora | D79: norasemeraro@gmail.com | E79: 21195 | F79: 12270859 | G79: 3516608455 | H79: Voy al gym Manantial | I79: Obra social | J79: OSSEG | R79: =IF(H79="","",VLOOKUP(H79,'Hoja 9'!$A$1:$B$255,2,0)) -> GIMNASIO | S79: =IF(A79="","",YEAR(A79)) -> 2023 | T79: =IF(A79="","",MONTH(A79)) -> 3
A80: 44986.803 | B80: Sueldo | C80: Belkis Anabella | D80: basueldo@gmail.com | E80: 31671 | F80: 32518805 | G80: 3512466755 | H80: Google | I80: Particular | R80: =IF(H80="","",VLOOKUP(H80,'Hoja 9'!$A$1:$B$255,2,0)) -> GOOGLE | S80: =IF(A80="","",YEAR(A80)) -> 2023 | T80: =IF(A80="","",MONTH(A80)) -> 3
A81: 44987.389 | B81: Ponce | C81: Federico | D81: federico.jponce@gmail.com | E81: 34895 | F81: 39072489 | G81: 3517502384 | H81: Recomendación | I81: Obra social | J81: APROSS | R81: =IF(H81="","",VLOOKUP(H81,'Hoja 9'!$A$1:$B$255,2,0)) -> BOCA EN BOCA | S81: =IF(A81="","",YEAR(A81)) -> 2023 | T81: =IF(A81="","",MONTH(A81)) -> 3
A82: 44987.457 | B82: Baigorri | C82: Joel | D82: Baigorri.joel@gmail.com | E82: 31593 | F82: 32372182 | G82: 3513471220 | H82: Google | I82: Particular | R82: =IF(H82="","",VLOOKUP(H82,'Hoja 9'!$A$1:$B$255,2,0)) -> GOOGLE | S82: =IF(A82="","",YEAR(A82)) -> 2023 | T82: =IF(A82="","",MONTH(A82)) -> 3
A83: 44988.747 | B83: Grion | C83: Alejandro | D83: alejandrogrion@gmail.com | E83: 25928 | F83: 21967210 | G83: 3512388424 | H83: Google | I83: Particular | R83: =IF(H83="","",VLOOKUP(H83,'Hoja 9'!$A$1:$B$255,2,0)) -> GOOGLE | S83: =IF(A83="","",YEAR(A83)) -> 2023 | T83: =IF(A83="","",MONTH(A83)) -> 3
A84: 44991.51 | B84: Biani | C84: Jeremias | D84: diegoivanbiani79@gmail.com | E84: 39526 | F84: 48124818 | G84: 3513357046 | H84: Google | I84: Particular | R84: =IF(H84="","",VLOOKUP(H84,'Hoja 9'!$A$1:$B$255,2,0)) -> GOOGLE | S84: =IF(A84="","",YEAR(A84)) -> 2023 | T84: =IF(A84="","",MONTH(A84)) -> 3
A85: 44991.863 | B85: Castro | C85: Facundo | D85: castrofacundo265@gmail.com | E85: 36204 | F85: 40506846 | G85: 3542461695 | H85: Recomendación | I85: Obra social | J85: APROSS | R85: =IF(H85="","",VLOOKUP(H85,'Hoja 9'!$A$1:$B$255,2,0)) -> BOCA EN BOCA | S85: =IF(A85="","",YEAR(A85)) -> 2023 | T85: =IF(A85="","",MONTH(A85)) -> 3
A86: 44992.498 | B86: DUARTE POLANCO | C86: AXEL MATIAS | D86: amatiasduarte@gmail.com | E86: 32925 | F86: 35054004 | G86: 3513792102 | H86: Google | I86: Obra social | J86: SANCOR | R86: =IF(H86="","",VLOOKUP(H86,'Hoja 9'!$A$1:$B$255,2,0)) -> GOOGLE | S86: =IF(A86="","",YEAR(A86)) -> 2023 | T86: =IF(A86="","",MONTH(A86)) -> 3
A87: 44992.869 | B87: Bordino | C87: Alvaro | D87: Alvarobordino1995@gmail.com | E87: 34460 | F87: 38183134 | G87: 3515337720 | H87: Google | I87: Particular | R87: =IF(H87="","",VLOOKUP(H87,'Hoja 9'!$A$1:$B$255,2,0)) -> GOOGLE | S87: =IF(A87="","",YEAR(A87)) -> 2023 | T87: =IF(A87="","",MONTH(A87)) -> 3
A88: 44993.774 | B88: Freno | C88: Pablo Manuel | D88: pablomanuelfreno@gmail.com | E88: 21433 | F88: 12613243 | G88: 3515435327 | H88: Recomendación | I88: Obra social | J88: Medife | R88: =IF(H88="","",VLOOKUP(H88,'Hoja 9'!$A$1:$B$255,2,0)) -> BOCA EN BOCA | S88: =IF(A88="","",YEAR(A88)) -> 2023 | T88: =IF(A88="","",MONTH(A88)) -> 3
A89: 44998.423 | B89: Gadea | C89: Erik paul | D89: erikgadea@hotmail.com.ar | E89: 35542 | F89: 40203248 | G89: 3522400613 | H89: Recomendación | I89: Obra social | J89: Unimed | R89: =IF(H89="","",VLOOKUP(H89,'Hoja 9'!$A$1:$B$255,2,0)) -> BOCA EN BOCA | S89: =IF(A89="","",YEAR(A89)) -> 2023 | T89: =IF(A89="","",MONTH(A89)) -> 3
A90: 44999.482 | B90: Charif | C90: Asdrubal | D90: Ivoncharif556@gmail.com | E90: 26823 | F90: 23458302 | G90: 3513537495 | H90: Google | I90: Particular | R90: =IF(H90="","",VLOOKUP(H90,'Hoja 9'!$A$1:$B$255,2,0)) -> GOOGLE | S90: =IF(A90="","",YEAR(A90)) -> 2023 | T90: =IF(A90="","",MONTH(A90)) -> 3
A91: 45005.438 | B91: Oña | C91: Ignacio | D91: ignaona@gmail.com | E91: 31219 | F91: 31669854 | G91: 3513746660 | H91: Voy al gym Manantial | I91: Obra social | J91: PREVENCIÓN | R91: =IF(H91="","",VLOOKUP(H91,'Hoja 9'!$A$1:$B$255,2,0)) -> GIMNASIO | S91: =IF(A91="","",YEAR(A91)) -> 2023 | T91: =IF(A91="","",MONTH(A91)) -> 3
A92: 45005.455 | B92: Depaul | C92: Emilia | D92: emiliadepaul.mkt@gmail.com | E92: 36598 | F92: 42383051 | G92: 3517680758 | H92: Cartilla Obra Social | I92: Obra social | J92: PREVENCIÓN | R92: =IF(H92="","",VLOOKUP(H92,'Hoja 9'!$A$1:$B$255,2,0)) -> OBRA SOCIAL | S92: =IF(A92="","",YEAR(A92)) -> 2023 | T92: =IF(A92="","",MONTH(A92)) -> 3
A93: 45005.548 | B93: Menacho | C93: Silvia | D93: silviambaigorri@gmail.com | E93: 24935 | F93: 20346063 | G93: 3513854962 | H93: Recomendación | I93: Particular | R93: =IF(H93="","",VLOOKUP(H93,'Hoja 9'!$A$1:$B$255,2,0)) -> BOCA EN BOCA | S93: =IF(A93="","",YEAR(A93)) -> 2023 | T93: =IF(A93="","",MONTH(A93)) -> 3
A94: 45005.794 | B94: Fernandez Lopez | C94: Jeronimo | D94: jerofernandezlopez@gmail.com | E94: 39119 | F94: 47662640 | G94: 3518069982 | H94: Google | I94: Particular | R94: =IF(H94="","",VLOOKUP(H94,'Hoja 9'!$A$1:$B$255,2,0)) -> GOOGLE | S94: =IF(A94="","",YEAR(A94)) -> 2023 | T94: =IF(A94="","",MONTH(A94)) -> 3
A95: 45006.655 | B95: Sosa | C95: Carlos Alberto | D95: caro-elstein@hotmail.com | E95: 25511 | F95: 21013856 | G95: 3513242191 | H95: Instagram | I95: Obra social | J95: Ositac | R95: =IF(H95="","",VLOOKUP(H95,'Hoja 9'!$A$1:$B$255,2,0)) -> META | S95: =IF(A95="","",YEAR(A95)) -> 2023 | T95: =IF(A95="","",MONTH(A95)) -> 3
A96: 45007.518 | B96: Romano | C96: Camilo Francisco | D96: camilofranciscoromano@gmail.com | E96: 38540 | F96: 46283518 | G96: 3512486914 | H96: Instagram | I96: Obra social | J96: Medife | R96: =IF(H96="","",VLOOKUP(H96,'Hoja 9'!$A$1:$B$255,2,0)) -> META | S96: =IF(A96="","",YEAR(A96)) -> 2023 | T96: =IF(A96="","",MONTH(A96)) -> 3
A97: 45012.671 | B97: España luppo | C97: Emilia | D97: Emilia040905@gmail.com | E97: 38599 | F97: 46505684 | G97: 3516166272 | H97: Voy al gym Manantial | I97: Particular | R97: =IF(H97="","",VLOOKUP(H97,'Hoja 9'!$A$1:$B$255,2,0)) -> GIMNASIO | S97: =IF(A97="","",YEAR(A97)) -> 2023 | T97: =IF(A97="","",MONTH(A97)) -> 3
A98: 45012.676 | B98: Caminoa | C98: Abril | D98: Abril.caminoa16@gmail.com | E98: 36516 | F98: 42208997 | G98: 2235414440 | H98: Recomendación | I98: Particular | R98: =IF(H98="","",VLOOKUP(H98,'Hoja 9'!$A$1:$B$255,2,0)) -> BOCA EN BOCA | S98: =IF(A98="","",YEAR(A98)) -> 2023 | T98: =IF(A98="","",MONTH(A98)) -> 3
A99: 45012.804 | B99: Prieto Marconi | C99: Sofia | D99: sofiprieto070215@gmail.com | E99: 37294 | F99: 43879802 | G99: 3515485039 | H99: Voy al gym Manantial | I99: Particular | R99: =IF(H99="","",VLOOKUP(H99,'Hoja 9'!$A$1:$B$255,2,0)) -> GIMNASIO | S99: =IF(A99="","",YEAR(A99)) -> 2023 | T99: =IF(A99="","",MONTH(A99)) -> 3
A100: 45013.836 | B100: Abaca | C100: Lucas Hernan | D100: lucasabaca@hotmail.como | E100: 29889 | F100: 29136743 | G100: 3517582118 | H100: Voy al gym Manantial | I100: Obra social | J100: Avalian | R100: =IF(H100="","",VLOOKUP(H100,'Hoja 9'!$A$1:$B$255,2,0)) -> GIMNASIO | S100: =IF(A100="","",YEAR(A100)) -> 2023 | T100: =IF(A100="","",MONTH(A100)) -> 3
...

Sheet Contacto
A1: Name | B1: Phone 1 - Value | C1: Estado de contacto | D1: DETALLE_ERROR
A2: {=IF(INGRESOS_API!P2:P3000="","",INGRESOS_API!P2:P3000)} -> Llanos Cristian | B2: {=IF(INGRESOS_API!G2:G3000="","",IF(LEFT(INGRESOS_API!G2:G3000,4)="+549",INGRESOS_API!G2:G3000,IF(LEFT(INGRESOS_API!G2:G3000,3)="+54","+549"&RIGHT(INGRESOS_API!G2:G3000,LEN(INGRESOS_API!G2:G3000)-4),INGRESOS_API!G2:G3000)))} -> +549518046736 | C2: CREADO
A3: Leiva Nilda Carolina | B3: +549513844529 | C3: CREADO
A4: Far Juan Manuel | B4: +549512006711 | C4: CREADO
A5: Urquía Yohana | B5: +549516299562 | C5: CREADO
A6: Lopez Gonzalo Daniel | B6: +549515186768 | C6: CREADO
A7: Agüero Juan Manuel | B7: +549516219534 | C7: CREADO
A8: Valdez Rubén | B8: +549513374771 | C8: CREADO
A9: Giménez Fernando | B9: +549516953672 | C9: CREADO
A10: JOHNSON GUILLERMO | B10: +549515138062 | C10: CREADO
A11: Carnevale Mariela | B11: +549513040216 | C11: CREADO
A12: Isa Minuet Elías | B12: +549517580512 | C12: CREADO
A13: Ghibaudo Pablo | B13: +549515528353 | C13: CREADO
A14: Asinari Emanuel | B14: +549516098550 | C14: CREADO
... A969: Cabanillas Miguel | B969: +549512441054 | C969: CREADO
A970: Cortez Angelica Nene | B970: #VALUE! | C970: YA_EXISTE
A971: Paulino Sofia | B971: #VALUE! | C971: CREADO
A972: Tobares Regina | B972: +549512665822 | C972: CREADO
A973: Davila Pablo | B973: +549513022880 | C973: YA_EXISTE
A974: Moretto Horacio | B974: +549515505817 | C974: CREADO
A975: VIBERTI Carlos | B975: +549514590212 | C975: CREADO
A976: Castro Antonia Matilde | B976: +549513565063 | C976: YA_EXISTE
A977: Merdidian Juan Carlos | B977: +549513146903 | C977: CREADO
A978: Barra González Tomás | B978: +549515329797 | C978: CREADO
A979: Blanco Luis Manuel | B979: +549512008982 | C979: CREADO
A980: Bassano Jorge | B980: +549516817829 | C980: CREADO
A981: Navarro Fabian | B981: +549515135709 | C981: CREADO
A982: Gonzalez Mazzoni Octavio | B982: +549512343290 | C982: CREADO
A983: Romero Sergio | B983: +549513218392 | C983: CREADO
... A1547: Acosta Lucas | B1547: +549364222018 | C1547: INCOMPLETO
C1548: INCOMPLETO
C1549: INCOMPLETO
C1550: INCOMPLETO
C1551: INCOMPLETO
C1552: INCOMPLETO
C1553: INCOMPLETO
C1554: INCOMPLETO
C1555: INCOMPLETO
C1556: INCOMPLETO
C1557: INCOMPLETO
C1558: INCOMPLETO
C1559: INCOMPLETO
... C2000: INCOMPLETO

Sheet INGRESOS_API
A1: submitted_at | B1: apellido | C1: nombre | D1: email | E1: fecha_nacimiento | F1: dni | G1: telefono_e164 | H1: fuente | I1: tipo_atencion | J1: obra_social | K1: actividad_fisica | L1: actividad_detalle | M1: frecuencia_semana | N1: anio | O1: mes
A2: ='Respuestas de formulario 1'!A2 -> 44865.663 | B2: ='Respuestas de formulario 1'!B2 -> Llanos | C2: ='Respuestas de formulario 1'!C2 -> Cristian | D2: ='Respuestas de formulario 1'!D2 -> Cristian_kobe@hotmail.com | E2: ='Respuestas de formulario 1'!E2 -> 31427 | F2: ='Respuestas de formulario 1'!F2 -> 32099118 | G2: =IFERROR(__xludf.DUMMYFUNCTION("IF('Respuestas de formulario 1'!G2="""","""",IF(LEFT(REGEXREPLACE(TO_TEXT('Respuestas de formulario 1'!G2),""[^0-9]"",""""),2)=""54"",""+""&REGEXREPLACE(TO_TEXT('Respuestas de formulario 1'!G2),""[^0-9]"",""""),""+54""&REGEXREPLACE(TO_TEXT('Respuestas de "&"formulario 1'!G2),""[^0-9]"","""")))"),"+543518046736") -> +543518046736 | H2: ='Respuestas de formulario 1'!S2 -> 2022 | I2: =IFERROR(__xludf.DUMMYFUNCTION("IF('Respuestas de formulario 1'!I2="""","""",TO_TEXT('Respuestas de formulario 1'!I2))"),"Obra social") -> Obra social | J2: =IFERROR(__xludf.DUMMYFUNCTION("IF('Respuestas de formulario 1'!J2<>"""",UPPER(TRIM(TO_TEXT('Respuestas de formulario 1'!J2))),IF('Respuestas de formulario 1'!O2<>"""",UPPER(TRIM(TO_TEXT('Respuestas de formulario 1'!O2))),""""))"),"APROSS") -> APROSS | K2: =IFERROR(__xludf.DUMMYFUNCTION("IF('Respuestas de formulario 1'!K2="""","""",TO_TEXT('Respuestas de formulario 1'!K2))"),"") | L2: =IFERROR(__xludf.DUMMYFUNCTION("IF('Respuestas de formulario 1'!L2="""","""",TO_TEXT('Respuestas de formulario 1'!L2))"),"") | M2: =IFERROR(__xludf.DUMMYFUNCTION("IF('Respuestas de formulario 1'!M2="""","""",TO_TEXT('Respuestas de formulario 1'!M2))"),"") | N2: =IF(A2="","",IFERROR(YEAR(A2),"")) -> 2022 | O2: =IF(A2="","",IFERROR(TEXT(A2,"mmmm"),"")) -> octubre | P2: {=IF(F2:F2000="",,B2:B2000&" "&C2:C2000)} -> Llanos Cristian
A3: ='Respuestas de formulario 1'!A3 -> 44866.425 | B3: ='Respuestas de formulario 1'!B3 -> Leiva | C3: ='Respuestas de formulario 1'!C3 -> Nilda Carolina | D3: ='Respuestas de formulario 1'!D3 -> caroagus023@gmail.com | E3: ='Respuestas de formulario 1'!E3 -> 29208 | F3: ='Respuestas de formulario 1'!F3 -> 27671982 | G3: =IFERROR(__xludf.DUMMYFUNCTION("IF('Respuestas de formulario 1'!G3="""","""",IF(LEFT(REGEXREPLACE(TO_TEXT('Respuestas de formulario 1'!G3),""[^0-9]"",""""),2)=""54"",""+""&REGEXREPLACE(TO_TEXT('Respuestas de formulario 1'!G3),""[^0-9]"",""""),""+54""&REGEXREPLACE(TO_TEXT('Respuestas de "&"formulario 1'!G3),""[^0-9]"","""")))"),"+543513844529") -> +543513844529 | H3: ='Respuestas de formulario 1'!S3 -> 2022 | I3: =IFERROR(__xludf.DUMMYFUNCTION("IF('Respuestas de formulario 1'!I3="""","""",TO_TEXT('Respuestas de formulario 1'!I3))"),"Particular") -> Particular | J3: =IFERROR(__xludf.DUMMYFUNCTION("IF('Respuestas de formulario 1'!J3<>"""",UPPER(TRIM(TO_TEXT('Respuestas de formulario 1'!J3))),IF('Respuestas de formulario 1'!O3<>"""",UPPER(TRIM(TO_TEXT('Respuestas de formulario 1'!O3))),""""))"),"") | K3: =IFERROR(__xludf.DUMMYFUNCTION("IF('Respuestas de formulario 1'!K3="""","""",TO_TEXT('Respuestas de formulario 1'!K3))"),"") | L3: =IFERROR(__xludf.DUMMYFUNCTION("IF('Respuestas de formulario 1'!L3="""","""",TO_TEXT('Respuestas de formulario 1'!L3))"),"") | M3: =IFERROR(__xludf.DUMMYFUNCTION("IF('Respuestas de formulario 1'!M3="""","""",TO_TEXT('Respuestas de formulario 1'!M3))"),"") | N3: =IF(A3="","",IFERROR(YEAR(A3),"")) -> 2022 | O3: =IF(A3="","",IFERROR(TEXT(A3,"mmmm"),"")) -> noviembre | P3: Leiva Nilda Carolina
A4: ='Respuestas de formulario 1'!A4 -> 44872.859 | B4: ='Respuestas de formulario 1'!B4 -> Far | C4: ='Respuestas de formulario 1'!C4 -> Juan Manuel | D4: ='Respuestas de formulario 1'!D4 -> Manufar87@hotmail.com | E4: ='Respuestas de formulario 1'!E4 -> 31894 | F4: ='Respuestas de formulario 1'!F4 -> 33082576 | G4: =IFERROR(__xludf.DUMMYFUNCTION("IF('Respuestas de formulario 1'!G4="""","""",IF(LEFT(REGEXREPLACE(TO_TEXT('Respuestas de formulario 1'!G4),""[^0-9]"",""""),2)=""54"",""+""&REGEXREPLACE(TO_TEXT('Respuestas de formulario 1'!G4),""[^0-9]"",""""),""+54""&REGEXREPLACE(TO_TEXT('Respuestas de "&"formulario 1'!G4),""[^0-9]"","""")))"),"+543512006711") -> +543512006711 | H4: ='Respuestas de formulario 1'!S4 -> 2022 | I4: =IFERROR(__xludf.DUMMYFUNCTION("IF('Respuestas de formulario 1'!I4="""","""",TO_TEXT('Respuestas de formulario 1'!I4))"),"Particular") -> Particular | J4: =IFERROR(__xludf.DUMMYFUNCTION("IF('Respuestas de formulario 1'!J4<>"""",UPPER(TRIM(TO_TEXT('Respuestas de formulario 1'!J4))),IF('Respuestas de formulario 1'!O4<>"""",UPPER(TRIM(TO_TEXT('Respuestas de formulario 1'!O4))),""""))"),"") | K4: =IFERROR(__xludf.DUMMYFUNCTION("IF('Respuestas de formulario 1'!K4="""","""",TO_TEXT('Respuestas de formulario 1'!K4))"),"") | L4: =IFERROR(__xludf.DUMMYFUNCTION("IF('Respuestas de formulario 1'!L4="""","""",TO_TEXT('Respuestas de formulario 1'!L4))"),"") | M4: =IFERROR(__xludf.DUMMYFUNCTION("IF('Respuestas de formulario 1'!M4="""","""",TO_TEXT('Respuestas de formulario 1'!M4))"),"") | N4: =IF(A4="","",IFERROR(YEAR(A4),"")) -> 2022 | O4: =IF(A4="","",IFERROR(TEXT(A4,"mmmm"),"")) -> noviembre | P4: Far Juan Manuel
A5: ='Respuestas de formulario 1'!A5 -> 44879.654 | B5: ='Respuestas de formulario 1'!B5 -> Urquía | C5: ='Respuestas de formulario 1'!C5 -> Yohana | D5: ='Respuestas de formulario 1'!D5 -> yohana.urquia@gmail.com | E5: ='Respuestas de formulario 1'!E5 -> 31206 | F5: ='Respuestas de formulario 1'!F5 -> 31647631 | G5: =IFERROR(__xludf.DUMMYFUNCTION("IF('Respuestas de formulario 1'!G5="""","""",IF(LEFT(REGEXREPLACE(TO_TEXT('Respuestas de formulario 1'!G5),""[^0-9]"",""""),2)=""54"",""+""&REGEXREPLACE(TO_TEXT('Respuestas de formulario 1'!G5),""[^0-9]"",""""),""+54""&REGEXREPLACE(TO_TEXT('Respuestas de "&"formulario 1'!G5),""[^0-9]"","""")))"),"+543516299562") -> +543516299562 | H5: ='Respuestas de formulario 1'!S5 -> 2022 | I5: =IFERROR(__xludf.DUMMYFUNCTION("IF('Respuestas de formulario 1'!I5="""","""",TO_TEXT('Respuestas de formulario 1'!I5))"),"Particular") -> Particular | J5: =IFERROR(__xludf.DUMMYFUNCTION("IF('Respuestas de formulario 1'!J5<>"""",UPPER(TRIM(TO_TEXT('Respuestas de formulario 1'!J5))),IF('Respuestas de formulario 1'!O5<>"""",UPPER(TRIM(TO_TEXT('Respuestas de formulario 1'!O5))),""""))"),"") | K5: =IFERROR(__xludf.DUMMYFUNCTION("IF('Respuestas de formulario 1'!K5="""","""",TO_TEXT('Respuestas de formulario 1'!K5))"),"") | L5: =IFERROR(__xludf.DUMMYFUNCTION("IF('Respuestas de formulario 1'!L5="""","""",TO_TEXT('Respuestas de formulario 1'!L5))"),"") | M5: =IFERROR(__xludf.DUMMYFUNCTION("IF('Respuestas de formulario 1'!M5="""","""",TO_TEXT('Respuestas de formulario 1'!M5))"),"") | N5: =IF(A5="","",IFERROR(YEAR(A5),"")) -> 2022 | O5: =IF(A5="","",IFERROR(TEXT(A5,"mmmm"),"")) -> noviembre | P5: Urquía Yohana
A6: ='Respuestas de formulario 1'!A6 -> 44879.671 | B6: ='Respuestas de formulario 1'!B6 -> Lopez | C6: ='Respuestas de formulario 1'!C6 -> Gonzalo Daniel | D6: ='Respuestas de formulario 1'!D6 -> Zonlopez10@gmail.com | E6: ='Respuestas de formulario 1'!E6 -> 34623 | F6: ='Respuestas de formulario 1'!F6 -> 38501250 | G6: =IFERROR(__xludf.DUMMYFUNCTION("IF('Respuestas de formulario 1'!G6="""","""",IF(LEFT(REGEXREPLACE(TO_TEXT('Respuestas de formulario 1'!G6),""[^0-9]"",""""),2)=""54"",""+""&REGEXREPLACE(TO_TEXT('Respuestas de formulario 1'!G6),""[^0-9]"",""""),""+54""&REGEXREPLACE(TO_TEXT('Respuestas de "&"formulario 1'!G6),""[^0-9]"","""")))"),"+543515186768") -> +543515186768 | H6: ='Respuestas de formulario 1'!S6 -> 2022 | I6: =IFERROR(__xludf.DUMMYFUNCTION("IF('Respuestas de formulario 1'!I6="""","""",TO_TEXT('Respuestas de formulario 1'!I6))"),"Obra social") -> Obra social | J6: =IFERROR(__xludf.DUMMYFUNCTION("IF('Respuestas de formulario 1'!J6<>"""",UPPER(TRIM(TO_TEXT('Respuestas de formulario 1'!J6))),IF('Respuestas de formulario 1'!O6<>"""",UPPER(TRIM(TO_TEXT('Respuestas de formulario 1'!O6))),""""))"),"APROSS") -> APROSS | K6: =IFERROR(__xludf.DUMMYFUNCTION("IF('Respuestas de formulario 1'!K6="""","""",TO_TEXT('Respuestas de formulario 1'!K6))"),"") | L6: =IFERROR(__xludf.DUMMYFUNCTION("IF('Respuestas de formulario 1'!L6="""","""",TO_TEXT('Respuestas de formulario 1'!L6))"),"") | M6: =IFERROR(__xludf.DUMMYFUNCTION("IF('Respuestas de formulario 1'!M6="""","""",TO_TEXT('Respuestas de formulario 1'!M6))"),"") | N6: =IF(A6="","",IFERROR(YEAR(A6),"")) -> 2022 | O6: =IF(A6="","",IFERROR(TEXT(A6,"mmmm"),"")) -> noviembre | P6: Lopez Gonzalo Daniel
A7: ='Respuestas de formulario 1'!A7 -> 44880.471 | B7: ='Respuestas de formulario 1'!B7 -> Agüero | C7: ='Respuestas de formulario 1'!C7 -> Juan Manuel | D7: ='Respuestas de formulario 1'!D7 -> juanmamendiolaza@gmail.com | E7: ='Respuestas de formulario 1'!E7 -> 31846 | F7: ='Respuestas de formulario 1'!F7 -> 32787354 | G7: =IFERROR(__xludf.DUMMYFUNCTION("IF('Respuestas de formulario 1'!G7="""","""",IF(LEFT(REGEXREPLACE(TO_TEXT('Respuestas de formulario 1'!G7),""[^0-9]"",""""),2)=""54"",""+""&REGEXREPLACE(TO_TEXT('Respuestas de formulario 1'!G7),""[^0-9]"",""""),""+54""&REGEXREPLACE(TO_TEXT('Respuestas de "&"formulario 1'!G7),""[^0-9]"","""")))"),"+543516219534") -> +543516219534 | H7: ='Respuestas de formulario 1'!S7 -> 2022 | I7: =IFERROR(__xludf.DUMMYFUNCTION("IF('Respuestas de formulario 1'!I7="""","""",TO_TEXT('Respuestas de formulario 1'!I7))"),"Particular") -> Particular | J7: =IFERROR(__xludf.DUMMYFUNCTION("IF('Respuestas de formulario 1'!J7<>"""",UPPER(TRIM(TO_TEXT('Respuestas de formulario 1'!J7))),IF('Respuestas de formulario 1'!O7<>"""",UPPER(TRIM(TO_TEXT('Respuestas de formulario 1'!O7))),""""))"),"") | K7: =IFERROR(__xludf.DUMMYFUNCTION("IF('Respuestas de formulario 1'!K7="""","""",TO_TEXT('Respuestas de formulario 1'!K7))"),"") | L7: =IFERROR(__xludf.DUMMYFUNCTION("IF('Respuestas de formulario 1'!L7="""","""",TO_TEXT('Respuestas de formulario 1'!L7))"),"") | M7: =IFERROR(__xludf.DUMMYFUNCTION("IF('Respuestas de formulario 1'!M7="""","""",TO_TEXT('Respuestas de formulario 1'!M7))"),"") | N7: =IF(A7="","",IFERROR(YEAR(A7),"")) -> 2022 | O7: =IF(A7="","",IFERROR(TEXT(A7,"mmmm"),"")) -> noviembre | P7: Agüero Juan Manuel
A8: ='Respuestas de formulario 1'!A8 -> 44880.5 | B8: ='Respuestas de formulario 1'!B8 -> Valdez | C8: ='Respuestas de formulario 1'!C8 -> Rubén | D8: ='Respuestas de formulario 1'!D8 -> Rubenavaldez930@gmail.com | E8: ='Respuestas de formulario 1'!E8 -> 34161 | F8: ='Respuestas de formulario 1'!F8 -> 37733188 | G8: =IFERROR(__xludf.DUMMYFUNCTION("IF('Respuestas de formulario 1'!G8="""","""",IF(LEFT(REGEXREPLACE(TO_TEXT('Respuestas de formulario 1'!G8),""[^0-9]"",""""),2)=""54"",""+""&REGEXREPLACE(TO_TEXT('Respuestas de formulario 1'!G8),""[^0-9]"",""""),""+54""&REGEXREPLACE(TO_TEXT('Respuestas de "&"formulario 1'!G8),""[^0-9]"","""")))"),"+543513374771") -> +543513374771 | H8: ='Respuestas de formulario 1'!S8 -> 2022 | I8: =IFERROR(__xludf.DUMMYFUNCTION("IF('Respuestas de formulario 1'!I8="""","""",TO_TEXT('Respuestas de formulario 1'!I8))"),"") | J8: =IFERROR(__xludf.DUMMYFUNCTION("IF('Respuestas de formulario 1'!J8<>"""",UPPER(TRIM(TO_TEXT('Respuestas de formulario 1'!J8))),IF('Respuestas de formulario 1'!O8<>"""",UPPER(TRIM(TO_TEXT('Respuestas de formulario 1'!O8))),""""))"),"APROSS") -> APROSS | K8: =IFERROR(__xludf.DUMMYFUNCTION("IF('Respuestas de formulario 1'!K8="""","""",TO_TEXT('Respuestas de formulario 1'!K8))"),"") | L8: =IFERROR(__xludf.DUMMYFUNCTION("IF('Respuestas de formulario 1'!L8="""","""",TO_TEXT('Respuestas de formulario 1'!L8))"),"") | M8: =IFERROR(__xludf.DUMMYFUNCTION("IF('Respuestas de formulario 1'!M8="""","""",TO_TEXT('Respuestas de formulario 1'!M8))"),"") | N8: =IF(A8="","",IFERROR(YEAR(A8),"")) -> 2022 | O8: =IF(A8="","",IFERROR(TEXT(A8,"mmmm"),"")) -> noviembre | P8: Valdez Rubén
A9: ='Respuestas de formulario 1'!A9 -> 44881.413 | B9: ='Respuestas de formulario 1'!B9 -> Giménez | C9: ='Respuestas de formulario 1'!C9 -> Fernando | D9: ='Respuestas de formulario 1'!D9 -> gimenezfa@gmail.com | E9: ='Respuestas de formulario 1'!E9 -> 35171 | F9: ='Respuestas de formulario 1'!F9 -> 30544064 | G9: =IFERROR(__xludf.DUMMYFUNCTION("IF('Respuestas de formulario 1'!G9="""","""",IF(LEFT(REGEXREPLACE(TO_TEXT('Respuestas de formulario 1'!G9),""[^0-9]"",""""),2)=""54"",""+""&REGEXREPLACE(TO_TEXT('Respuestas de formulario 1'!G9),""[^0-9]"",""""),""+54""&REGEXREPLACE(TO_TEXT('Respuestas de "&"formulario 1'!G9),""[^0-9]"","""")))"),"+543516953672") -> +543516953672 | H9: ='Respuestas de formulario 1'!S9 -> 2022 | I9: =IFERROR(__xludf.DUMMYFUNCTION("IF('Respuestas de formulario 1'!I9="""","""",TO_TEXT('Respuestas de formulario 1'!I9))"),"Obra social") -> Obra social | J9: =IFERROR(__xludf.DUMMYFUNCTION("IF('Respuestas de formulario 1'!J9<>"""",UPPER(TRIM(TO_TEXT('Respuestas de formulario 1'!J9))),IF('Respuestas de formulario 1'!O9<>"""",UPPER(TRIM(TO_TEXT('Respuestas de formulario 1'!O9))),""""))"),"APROSS") -> APROSS | K9: =IFERROR(__xludf.DUMMYFUNCTION("IF('Respuestas de formulario 1'!K9="""","""",TO_TEXT('Respuestas de formulario 1'!K9))"),"") | L9: =IFERROR(__xludf.DUMMYFUNCTION("IF('Respuestas de formulario 1'!L9="""","""",TO_TEXT('Respuestas de formulario 1'!L9))"),"") | M9: =IFERROR(__xludf.DUMMYFUNCTION("IF('Respuestas de formulario 1'!M9="""","""",TO_TEXT('Respuestas de formulario 1'!M9))"),"") | N9: =IF(A9="","",IFERROR(YEAR(A9),"")) -> 2022 | O9: =IF(A9="","",IFERROR(TEXT(A9,"mmmm"),"")) -> noviembre | P9: Giménez Fernando
A10: ='Respuestas de formulario 1'!A10 -> 44881.491 | B10: ='Respuestas de formulario 1'!B10 -> JOHNSON | C10: ='Respuestas de formulario 1'!C10 -> GUILLERMO | D10: ='Respuestas de formulario 1'!D10 -> guillermorjohnson@gmail.com | E10: ='Respuestas de formulario 1'!E10 -> 26996 | F10: ='Respuestas de formulario 1'!F10 -> 23683982 | G10: =IFERROR(__xludf.DUMMYFUNCTION("IF('Respuestas de formulario 1'!G10="""","""",IF(LEFT(REGEXREPLACE(TO_TEXT('Respuestas de formulario 1'!G10),""[^0-9]"",""""),2)=""54"",""+""&REGEXREPLACE(TO_TEXT('Respuestas de formulario 1'!G10),""[^0-9]"",""""),""+54""&REGEXREPLACE(TO_TEXT('Respuestas "&"de formulario 1'!G10),""[^0-9]"","""")))"),"+543515138062") -> +543515138062 | H10: ='Respuestas de formulario 1'!S10 -> 2022 | I10: =IFERROR(__xludf.DUMMYFUNCTION("IF('Respuestas de formulario 1'!I10="""","""",TO_TEXT('Respuestas de formulario 1'!I10))"),"Obra social") -> Obra social | J10: =IFERROR(__xludf.DUMMYFUNCTION("IF('Respuestas de formulario 1'!J10<>"""",UPPER(TRIM(TO_TEXT('Respuestas de formulario 1'!J10))),IF('Respuestas de formulario 1'!O10<>"""",UPPER(TRIM(TO_TEXT('Respuestas de formulario 1'!O10))),""""))"),"CAJA NOTARIAL") -> CAJA NOTARIAL | K10: =IFERROR(__xludf.DUMMYFUNCTION("IF('Respuestas de formulario 1'!K10="""","""",TO_TEXT('Respuestas de formulario 1'!K10))"),"") | L10: =IFERROR(__xludf.DUMMYFUNCTION("IF('Respuestas de formulario 1'!L10="""","""",TO_TEXT('Respuestas de formulario 1'!L10))"),"") | M10: =IFERROR(__xludf.DUMMYFUNCTION("IF('Respuestas de formulario 1'!M10="""","""",TO_TEXT('Respuestas de formulario 1'!M10))"),"") | N10: =IF(A10="","",IFERROR(YEAR(A10),"")) -> 2022 | O10: =IF(A10="","",IFERROR(TEXT(A10,"mmmm"),"")) -> noviembre | P10: JOHNSON GUILLERMO
A11: ='Respuestas de formulario 1'!A11 -> 44881.688 | B11: ='Respuestas de formulario 1'!B11 -> Carnevale | C11: ='Respuestas de formulario 1'!C11 -> Mariela | D11: ='Respuestas de formulario 1'!D11 -> marielacarnevale533@hotmail.com | E11: ='Respuestas de formulario 1'!E11 -> 29629 | F11: ='Respuestas de formulario 1'!F11 -> 23683982 | G11: =IFERROR(__xludf.DUMMYFUNCTION("IF('Respuestas de formulario 1'!G11="""","""",IF(LEFT(REGEXREPLACE(TO_TEXT('Respuestas de formulario 1'!G11),""[^0-9]"",""""),2)=""54"",""+""&REGEXREPLACE(TO_TEXT('Respuestas de formulario 1'!G11),""[^0-9]"",""""),""+54""&REGEXREPLACE(TO_TEXT('Respuestas "&"de formulario 1'!G11),""[^0-9]"","""")))"),"+543513040216") -> +543513040216 | H11: ='Respuestas de formulario 1'!S11 -> 2022 | I11: =IFERROR(__xludf.DUMMYFUNCTION("IF('Respuestas de formulario 1'!I11="""","""",TO_TEXT('Respuestas de formulario 1'!I11))"),"Particular") -> Particular | J11: =IFERROR(__xludf.DUMMYFUNCTION("IF('Respuestas de formulario 1'!J11<>"""",UPPER(TRIM(TO_TEXT('Respuestas de formulario 1'!J11))),IF('Respuestas de formulario 1'!O11<>"""",UPPER(TRIM(TO_TEXT('Respuestas de formulario 1'!O11))),""""))"),"") | K11: =IFERROR(__xludf.DUMMYFUNCTION("IF('Respuestas de formulario 1'!K11="""","""",TO_TEXT('Respuestas de formulario 1'!K11))"),"") | L11: =IFERROR(__xludf.DUMMYFUNCTION("IF('Respuestas de formulario 1'!L11="""","""",TO_TEXT('Respuestas de formulario 1'!L11))"),"") | M11: =IFERROR(__xludf.DUMMYFUNCTION("IF('Respuestas de formulario 1'!M11="""","""",TO_TEXT('Respuestas de formulario 1'!M11))"),"") | N11: =IF(A11="","",IFERROR(YEAR(A11),"")) -> 2022 | O11: =IF(A11="","",IFERROR(TEXT(A11,"mmmm"),"")) -> noviembre | P11: Carnevale Mariela
A12: ='Respuestas de formulario 1'!A12 -> 44882.46 | B12: ='Respuestas de formulario 1'!B12 -> Isa Minuet | C12: ='Respuestas de formulario 1'!C12 -> Elías | D12: ='Respuestas de formulario 1'!D12 -> eliasisaa@gmail.com | E12: ='Respuestas de formulario 1'!E12 -> 36108 | F12: ='Respuestas de formulario 1'!F12 -> 41019335 | G12: =IFERROR(__xludf.DUMMYFUNCTION("IF('Respuestas de formulario 1'!G12="""","""",IF(LEFT(REGEXREPLACE(TO_TEXT('Respuestas de formulario 1'!G12),""[^0-9]"",""""),2)=""54"",""+""&REGEXREPLACE(TO_TEXT('Respuestas de formulario 1'!G12),""[^0-9]"",""""),""+54""&REGEXREPLACE(TO_TEXT('Respuestas "&"de formulario 1'!G12),""[^0-9]"","""")))"),"+543517580512") -> +543517580512 | H12: ='Respuestas de formulario 1'!S12 -> 2022 | I12: =IFERROR(__xludf.DUMMYFUNCTION("IF('Respuestas de formulario 1'!I12="""","""",TO_TEXT('Respuestas de formulario 1'!I12))"),"Obra social") -> Obra social | J12: =IFERROR(__xludf.DUMMYFUNCTION("IF('Respuestas de formulario 1'!J12<>"""",UPPER(TRIM(TO_TEXT('Respuestas de formulario 1'!J12))),IF('Respuestas de formulario 1'!O12<>"""",UPPER(TRIM(TO_TEXT('Respuestas de formulario 1'!O12))),""""))"),"SANCOR") -> SANCOR | K12: =IFERROR(__xludf.DUMMYFUNCTION("IF('Respuestas de formulario 1'!K12="""","""",TO_TEXT('Respuestas de formulario 1'!K12))"),"") | L12: =IFERROR(__xludf.DUMMYFUNCTION("IF('Respuestas de formulario 1'!L12="""","""",TO_TEXT('Respuestas de formulario 1'!L12))"),"") | M12: =IFERROR(__xludf.DUMMYFUNCTION("IF('Respuestas de formulario 1'!M12="""","""",TO_TEXT('Respuestas de formulario 1'!M12))"),"") | N12: =IF(A12="","",IFERROR(YEAR(A12),"")) -> 2022 | O12: =IF(A12="","",IFERROR(TEXT(A12,"mmmm"),"")) -> noviembre | P12: Isa Minuet Elías
A13: ='Respuestas de formulario 1'!A13 -> 44888.414 | B13: ='Respuestas de formulario 1'!B13 -> Ghibaudo | C13: ='Respuestas de formulario 1'!C13 -> Pablo | D13: ='Respuestas de formulario 1'!D13 -> lic.pabloghibaudo@gmail.com | E13: ='Respuestas de formulario 1'!E13 -> 29137 | F13: ='Respuestas de formulario 1'!F13 -> 27267620 | G13: =IFERROR(__xludf.DUMMYFUNCTION("IF('Respuestas de formulario 1'!G13="""","""",IF(LEFT(REGEXREPLACE(TO_TEXT('Respuestas de formulario 1'!G13),""[^0-9]"",""""),2)=""54"",""+""&REGEXREPLACE(TO_TEXT('Respuestas de formulario 1'!G13),""[^0-9]"",""""),""+54""&REGEXREPLACE(TO_TEXT('Respuestas "&"de formulario 1'!G13),""[^0-9]"","""")))"),"+543515528353") -> +543515528353 | H13: ='Respuestas de formulario 1'!S13 -> 2022 | I13: =IFERROR(__xludf.DUMMYFUNCTION("IF('Respuestas de formulario 1'!I13="""","""",TO_TEXT('Respuestas de formulario 1'!I13))"),"Obra social") -> Obra social | J13: =IFERROR(__xludf.DUMMYFUNCTION("IF('Respuestas de formulario 1'!J13<>"""",UPPER(TRIM(TO_TEXT('Respuestas de formulario 1'!J13))),IF('Respuestas de formulario 1'!O13<>"""",UPPER(TRIM(TO_TEXT('Respuestas de formulario 1'!O13))),""""))"),"APROSS") -> APROSS | K13: =IFERROR(__xludf.DUMMYFUNCTION("IF('Respuestas de formulario 1'!K13="""","""",TO_TEXT('Respuestas de formulario 1'!K13))"),"") | L13: =IFERROR(__xludf.DUMMYFUNCTION("IF('Respuestas de formulario 1'!L13="""","""",TO_TEXT('Respuestas de formulario 1'!L13))"),"") | M13: =IFERROR(__xludf.DUMMYFUNCTION("IF('Respuestas de formulario 1'!M13="""","""",TO_TEXT('Respuestas de formulario 1'!M13))"),"") | N13: =IF(A13="","",IFERROR(YEAR(A13),"")) -> 2022 | O13: =IF(A13="","",IFERROR(TEXT(A13,"mmmm"),"")) -> noviembre | P13: Ghibaudo Pablo
A14: ='Respuestas de formulario 1'!A14 -> 44889.821 | B14: ='Respuestas de formulario 1'!B14 -> Asinari | C14: ='Respuestas de formulario 1'!C14 -> Emanuel | D14: ='Respuestas de formulario 1'!D14 -> lic.pabloghibaudo@gmail.com | E14: ='Respuestas de formulario 1'!E14 -> 34338 | F14: ='Respuestas de formulario 1'!F14 -> 38001813 | G14: =IFERROR(__xludf.DUMMYFUNCTION("IF('Respuestas de formulario 1'!G14="""","""",IF(LEFT(REGEXREPLACE(TO_TEXT('Respuestas de formulario 1'!G14),""[^0-9]"",""""),2)=""54"",""+""&REGEXREPLACE(TO_TEXT('Respuestas de formulario 1'!G14),""[^0-9]"",""""),""+54""&REGEXREPLACE(TO_TEXT('Respuestas "&"de formulario 1'!G14),""[^0-9]"","""")))"),"+543516098550") -> +543516098550 | H14: ='Respuestas de formulario 1'!S14 -> 2022 | I14: =IFERROR(__xludf.DUMMYFUNCTION("IF('Respuestas de formulario 1'!I14="""","""",TO_TEXT('Respuestas de formulario 1'!I14))"),"Particular") -> Particular | J14: =IFERROR(__xludf.DUMMYFUNCTION("IF('Respuestas de formulario 1'!J14<>"""",UPPER(TRIM(TO_TEXT('Respuestas de formulario 1'!J14))),IF('Respuestas de formulario 1'!O14<>"""",UPPER(TRIM(TO_TEXT('Respuestas de formulario 1'!O14))),""""))"),"") | K14: =IFERROR(__xludf.DUMMYFUNCTION("IF('Respuestas de formulario 1'!K14="""","""",TO_TEXT('Respuestas de formulario 1'!K14))"),"") | L14: =IFERROR(__xludf.DUMMYFUNCTION("IF('Respuestas de formulario 1'!L14="""","""",TO_TEXT('Respuestas de formulario 1'!L14))"),"") | M14: =IFERROR(__xludf.DUMMYFUNCTION("IF('Respuestas de formulario 1'!M14="""","""",TO_TEXT('Respuestas de formulario 1'!M14))"),"") | N14: =IF(A14="","",IFERROR(YEAR(A14),"")) -> 2022 | O14: =IF(A14="","",IFERROR(TEXT(A14,"mmmm"),"")) -> noviembre | P14: Asinari Emanuel
A15: ='Respuestas de formulario 1'!A15 -> 44890.799 | B15: ='Respuestas de formulario 1'!B15 -> Rivara | C15: ='Respuestas de formulario 1'!C15 -> Mauro Alejandro | D15: ='Respuestas de formulario 1'!D15 -> rivaramauro@hotmail.com | E15: ='Respuestas de formulario 1'!E15 -> 22514 | F15: ='Respuestas de formulario 1'!F15 -> 14747390 | G15: =IFERROR(__xludf.DUMMYFUNCTION("IF('Respuestas de formulario 1'!G15="""","""",IF(LEFT(REGEXREPLACE(TO_TEXT('Respuestas de formulario 1'!G15),""[^0-9]"",""""),2)=""54"",""+""&REGEXREPLACE(TO_TEXT('Respuestas de formulario 1'!G15),""[^0-9]"",""""),""+54""&REGEXREPLACE(TO_TEXT('Respuestas "&"de formulario 1'!G15),""[^0-9]"","""")))"),"+543516536874") -> +543516536874 | H15: ='Respuestas de formulario 1'!S15 -> 2022 | I15: =IFERROR(__xludf.DUMMYFUNCTION("IF('Respuestas de formulario 1'!I15="""","""",TO_TEXT('Respuestas de formulario 1'!I15))"),"Obra social") -> Obra social | J15: =IFERROR(__xludf.DUMMYFUNCTION("IF('Respuestas de formulario 1'!J15<>"""",UPPER(TRIM(TO_TEXT('Respuestas de formulario 1'!J15))),IF('Respuestas de formulario 1'!O15<>"""",UPPER(TRIM(TO_TEXT('Respuestas de formulario 1'!O15))),""""))"),"CPCE") -> CPCE | K15: =IFERROR(__xludf.DUMMYFUNCTION("IF('Respuestas de formulario 1'!K15="""","""",TO_TEXT('Respuestas de formulario 1'!K15))"),"") | L15: =IFERROR(__xludf.DUMMYFUNCTION("IF('Respuestas de formulario 1'!L15="""","""",TO_TEXT('Respuestas de formulario 1'!L15))"),"") | M15: =IFERROR(__xludf.DUMMYFUNCTION("IF('Respuestas de formulario 1'!M15="""","""",TO_TEXT('Respuestas de formulario 1'!M15))"),"") | N15: =IF(A15="","",IFERROR(YEAR(A15),"")) -> 2022 | O15: =IF(A15="","",IFERROR(TEXT(A15,"mmmm"),"")) -> noviembre | P15: Rivara Mauro Alejandro
A16: ='Respuestas de formulario 1'!A16 -> 44891.475 | B16: ='Respuestas de formulario 1'!B16 -> Andino | C16: ='Respuestas de formulario 1'!C16 -> Guillermo Regino | D16: ='Respuestas de formulario 1'!D16 -> puchiandino1@gmail.com | E16: ='Respuestas de formulario 1'!E16 -> 37207 | F16: ='Respuestas de formulario 1'!F16 -> 43693789 | G16: =IFERROR(__xludf.DUMMYFUNCTION("IF('Respuestas de formulario 1'!G16="""","""",IF(LEFT(REGEXREPLACE(TO_TEXT('Respuestas de formulario 1'!G16),""[^0-9]"",""""),2)=""54"",""+""&REGEXREPLACE(TO_TEXT('Respuestas de formulario 1'!G16),""[^0-9]"",""""),""+54""&REGEXREPLACE(TO_TEXT('Respuestas "&"de formulario 1'!G16),""[^0-9]"","""")))"),"+543517014316") -> +543517014316 | H16: ='Respuestas de formulario 1'!S16 -> 2022 | I16: =IFERROR(__xludf.DUMMYFUNCTION("IF('Respuestas de formulario 1'!I16="""","""",TO_TEXT('Respuestas de formulario 1'!I16))"),"Obra social") -> Obra social | J16: =IFERROR(__xludf.DUMMYFUNCTION("IF('Respuestas de formulario 1'!J16<>"""",UPPER(TRIM(TO_TEXT('Respuestas de formulario 1'!J16))),IF('Respuestas de formulario 1'!O16<>"""",UPPER(TRIM(TO_TEXT('Respuestas de formulario 1'!O16))),""""))"),"DASPU") -> DASPU | K16: =IFERROR(__xludf.DUMMYFUNCTION("IF('Respuestas de formulario 1'!K16="""","""",TO_TEXT('Respuestas de formulario 1'!K16))"),"") | L16: =IFERROR(__xludf.DUMMYFUNCTION("IF('Respuestas de formulario 1'!L16="""","""",TO_TEXT('Respuestas de formulario 1'!L16))"),"") | M16: =IFERROR(__xludf.DUMMYFUNCTION("IF('Respuestas de formulario 1'!M16="""","""",TO_TEXT('Respuestas de formulario 1'!M16))"),"") | N16: =IF(A16="","",IFERROR(YEAR(A16),"")) -> 2022 | O16: =IF(A16="","",IFERROR(TEXT(A16,"mmmm"),"")) -> noviembre | P16: Andino Guillermo Regino
A17: ='Respuestas de formulario 1'!A17 -> 44893.471 | B17: ='Respuestas de formulario 1'!B17 -> MUÑOZ | C17: ='Respuestas de formulario 1'!C17 -> Emery omar | D17: ='Respuestas de formulario 1'!D17 -> escribaniamunoz@gmail.com | E17: ='Respuestas de formulario 1'!E17 -> 28950 | F17: ='Respuestas de formulario 1'!F17 -> 27303587 | G17: =IFERROR(__xludf.DUMMYFUNCTION("IF('Respuestas de formulario 1'!G17="""","""",IF(LEFT(REGEXREPLACE(TO_TEXT('Respuestas de formulario 1'!G17),""[^0-9]"",""""),2)=""54"",""+""&REGEXREPLACE(TO_TEXT('Respuestas de formulario 1'!G17),""[^0-9]"",""""),""+54""&REGEXREPLACE(TO_TEXT('Respuestas "&"de formulario 1'!G17),""[^0-9]"","""")))"),"+543513493623") -> +543513493623 | H17: ='Respuestas de formulario 1'!S17 -> 2022 | I17: =IFERROR(__xludf.DUMMYFUNCTION("IF('Respuestas de formulario 1'!I17="""","""",TO_TEXT('Respuestas de formulario 1'!I17))"),"Obra social") -> Obra social | J17: =IFERROR(__xludf.DUMMYFUNCTION("IF('Respuestas de formulario 1'!J17<>"""",UPPER(TRIM(TO_TEXT('Respuestas de formulario 1'!J17))),IF('Respuestas de formulario 1'!O17<>"""",UPPER(TRIM(TO_TEXT('Respuestas de formulario 1'!O17))),""""))"),"CAJA NOTARIAL") -> CAJA NOTARIAL | K17: =IFERROR(__xludf.DUMMYFUNCTION("IF('Respuestas de formulario 1'!K17="""","""",TO_TEXT('Respuestas de formulario 1'!K17))"),"") | L17: =IFERROR(__xludf.DUMMYFUNCTION("IF('Respuestas de formulario 1'!L17="""","""",TO_TEXT('Respuestas de formulario 1'!L17))"),"") | M17: =IFERROR(__xludf.DUMMYFUNCTION("IF('Respuestas de formulario 1'!M17="""","""",TO_TEXT('Respuestas de formulario 1'!M17))"),"") | N17: =IF(A17="","",IFERROR(YEAR(A17),"")) -> 2022 | O17: =IF(A17="","",IFERROR(TEXT(A17,"mmmm"),"")) -> noviembre | P17: MUÑOZ Emery omar
A18: ='Respuestas de formulario 1'!A18 -> 44893.501 | B18: ='Respuestas de formulario 1'!B18 -> Boasso | C18: ='Respuestas de formulario 1'!C18 -> Lucas | D18: ='Respuestas de formulario 1'!D18 -> sosamariapia@hotmail.com | E18: ='Respuestas de formulario 1'!E18 -> 42410 | F18: ='Respuestas de formulario 1'!F18 -> 55011829 | G18: =IFERROR(__xludf.DUMMYFUNCTION("IF('Respuestas de formulario 1'!G18="""","""",IF(LEFT(REGEXREPLACE(TO_TEXT('Respuestas de formulario 1'!G18),""[^0-9]"",""""),2)=""54"",""+""&REGEXREPLACE(TO_TEXT('Respuestas de formulario 1'!G18),""[^0-9]"",""""),""+54""&REGEXREPLACE(TO_TEXT('Respuestas "&"de formulario 1'!G18),""[^0-9]"","""")))"),"+543516280350") -> +543516280350 | H18: ='Respuestas de formulario 1'!S18 -> 2022 | I18: =IFERROR(__xludf.DUMMYFUNCTION("IF('Respuestas de formulario 1'!I18="""","""",TO_TEXT('Respuestas de formulario 1'!I18))"),"Obra social") -> Obra social | J18: =IFERROR(__xludf.DUMMYFUNCTION("IF('Respuestas de formulario 1'!J18<>"""",UPPER(TRIM(TO_TEXT('Respuestas de formulario 1'!J18))),IF('Respuestas de formulario 1'!O18<>"""",UPPER(TRIM(TO_TEXT('Respuestas de formulario 1'!O18))),""""))"),"APROSS") -> APROSS | K18: =IFERROR(__xludf.DUMMYFUNCTION("IF('Respuestas de formulario 1'!K18="""","""",TO_TEXT('Respuestas de formulario 1'!K18))"),"") | L18: =IFERROR(__xludf.DUMMYFUNCTION("IF('Respuestas de formulario 1'!L18="""","""",TO_TEXT('Respuestas de formulario 1'!L18))"),"") | M18: =IFERROR(__xludf.DUMMYFUNCTION("IF('Respuestas de formulario 1'!M18="""","""",TO_TEXT('Respuestas de formulario 1'!M18))"),"") | N18: =IF(A18="","",IFERROR(YEAR(A18),"")) -> 2022 | O18: =IF(A18="","",IFERROR(TEXT(A18,"mmmm"),"")) -> noviembre | P18: Boasso Lucas
A19: ='Respuestas de formulario 1'!A19 -> 44895.838 | B19: ='Respuestas de formulario 1'!B19 -> Druetta | C19: ='Respuestas de formulario 1'!C19 -> Joaquín | D19: ='Respuestas de formulario 1'!D19 -> joadruetta@gmail.com | E19: ='Respuestas de formulario 1'!E19 -> 35936 | F19: ='Respuestas de formulario 1'!F19 -> 4081605 | G19: =IFERROR(__xludf.DUMMYFUNCTION("IF('Respuestas de formulario 1'!G19="""","""",IF(LEFT(REGEXREPLACE(TO_TEXT('Respuestas de formulario 1'!G19),""[^0-9]"",""""),2)=""54"",""+""&REGEXREPLACE(TO_TEXT('Respuestas de formulario 1'!G19),""[^0-9]"",""""),""+54""&REGEXREPLACE(TO_TEXT('Respuestas "&"de formulario 1'!G19),""[^0-9]"","""")))"),"+543513861638") -> +543513861638 | H19: ='Respuestas de formulario 1'!S19 -> 2022 | I19: =IFERROR(__xludf.DUMMYFUNCTION("IF('Respuestas de formulario 1'!I19="""","""",TO_TEXT('Respuestas de formulario 1'!I19))"),"Particular") -> Particular | J19: =IFERROR(__xludf.DUMMYFUNCTION("IF('Respuestas de formulario 1'!J19<>"""",UPPER(TRIM(TO_TEXT('Respuestas de formulario 1'!J19))),IF('Respuestas de formulario 1'!O19<>"""",UPPER(TRIM(TO_TEXT('Respuestas de formulario 1'!O19))),""""))"),"") | K19: =IFERROR(__xludf.DUMMYFUNCTION("IF('Respuestas de formulario 1'!K19="""","""",TO_TEXT('Respuestas de formulario 1'!K19))"),"") | L19: =IFERROR(__xludf.DUMMYFUNCTION("IF('Respuestas de formulario 1'!L19="""","""",TO_TEXT('Respuestas de formulario 1'!L19))"),"") | M19: =IFERROR(__xludf.DUMMYFUNCTION("IF('Respuestas de formulario 1'!M19="""","""",TO_TEXT('Respuestas de formulario 1'!M19))"),"") | N19: =IF(A19="","",IFERROR(YEAR(A19),"")) -> 2022 | O19: =IF(A19="","",IFERROR(TEXT(A19,"mmmm"),"")) -> noviembre | P19: Druetta Joaquín
A20: ='Respuestas de formulario 1'!A20 -> 44897.848 | B20: ='Respuestas de formulario 1'!B20 -> Hilbe | C20: ='Respuestas de formulario 1'!C20 -> Estela | D20: ='Respuestas de formulario 1'!D20 -> Estelahilbe5@hotmail.com | E20: ='Respuestas de formulario 1'!E20 -> 19420 | F20: ='Respuestas de formulario 1'!F20 -> 10756516 | G20: =IFERROR(__xludf.DUMMYFUNCTION("IF('Respuestas de formulario 1'!G20="""","""",IF(LEFT(REGEXREPLACE(TO_TEXT('Respuestas de formulario 1'!G20),""[^0-9]"",""""),2)=""54"",""+""&REGEXREPLACE(TO_TEXT('Respuestas de formulario 1'!G20),""[^0-9]"",""""),""+54""&REGEXREPLACE(TO_TEXT('Respuestas "&"de formulario 1'!G20),""[^0-9]"","""")))"),"+543513123179") -> +543513123179 | H20: ='Respuestas de formulario 1'!S20 -> 2022 | I20: =IFERROR(__xludf.DUMMYFUNCTION("IF('Respuestas de formulario 1'!I20="""","""",TO_TEXT('Respuestas de formulario 1'!I20))"),"Obra social") -> Obra social | J20: =IFERROR(__xludf.DUMMYFUNCTION("IF('Respuestas de formulario 1'!J20<>"""",UPPER(TRIM(TO_TEXT('Respuestas de formulario 1'!J20))),IF('Respuestas de formulario 1'!O20<>"""",UPPER(TRIM(TO_TEXT('Respuestas de formulario 1'!O20))),""""))"),"JERARQUICO SALUD") -> JERARQUICO SALUD | K20: =IFERROR(__xludf.DUMMYFUNCTION("IF('Respuestas de formulario 1'!K20="""","""",TO_TEXT('Respuestas de formulario 1'!K20))"),"") | L20: =IFERROR(__xludf.DUMMYFUNCTION("IF('Respuestas de formulario 1'!L20="""","""",TO_TEXT('Respuestas de formulario 1'!L20))"),"") | M20: =IFERROR(__xludf.DUMMYFUNCTION("IF('Respuestas de formulario 1'!M20="""","""",TO_TEXT('Respuestas de formulario 1'!M20))"),"") | N20: =IF(A20="","",IFERROR(YEAR(A20),"")) -> 2022 | O20: =IF(A20="","",IFERROR(TEXT(A20,"mmmm"),"")) -> diciembre | P20: Hilbe Estela
A21: ='Respuestas de formulario 1'!A21 -> 44901.883 | B21: ='Respuestas de formulario 1'!B21 -> Conrero | C21: ='Respuestas de formulario 1'!C21 -> Valentino | D21: ='Respuestas de formulario 1'!D21 -> vconrero@gmail.com | E21: ='Respuestas de formulario 1'!E21 -> 37698 | F21: ='Respuestas de formulario 1'!F21 -> 44694075 | G21: =IFERROR(__xludf.DUMMYFUNCTION("IF('Respuestas de formulario 1'!G21="""","""",IF(LEFT(REGEXREPLACE(TO_TEXT('Respuestas de formulario 1'!G21),""[^0-9]"",""""),2)=""54"",""+""&REGEXREPLACE(TO_TEXT('Respuestas de formulario 1'!G21),""[^0-9]"",""""),""+54""&REGEXREPLACE(TO_TEXT('Respuestas "&"de formulario 1'!G21),""[^0-9]"","""")))"),"+543515290969") -> +543515290969 | H21: ='Respuestas de formulario 1'!S21 -> 2022 | I21: =IFERROR(__xludf.DUMMYFUNCTION("IF('Respuestas de formulario 1'!I21="""","""",TO_TEXT('Respuestas de formulario 1'!I21))"),"Obra social") -> Obra social | J21: =IFERROR(__xludf.DUMMYFUNCTION("IF('Respuestas de formulario 1'!J21<>"""",UPPER(TRIM(TO_TEXT('Respuestas de formulario 1'!J21))),IF('Respuestas de formulario 1'!O21<>"""",UPPER(TRIM(TO_TEXT('Respuestas de formulario 1'!O21))),""""))"),"MEDIFÉ") -> MEDIFÉ | K21: =IFERROR(__xludf.DUMMYFUNCTION("IF('Respuestas de formulario 1'!K21="""","""",TO_TEXT('Respuestas de formulario 1'!K21))"),"") | L21: =IFERROR(__xludf.DUMMYFUNCTION("IF('Respuestas de formulario 1'!L21="""","""",TO_TEXT('Respuestas de formulario 1'!L21))"),"") | M21: =IFERROR(__xludf.DUMMYFUNCTION("IF('Respuestas de formulario 1'!M21="""","""",TO_TEXT('Respuestas de formulario 1'!M21))"),"") | N21: =IF(A21="","",IFERROR(YEAR(A21),"")) -> 2022 | O21: =IF(A21="","",IFERROR(TEXT(A21,"mmmm"),"")) -> diciembre | P21: Conrero Valentino
A22: ='Respuestas de formulario 1'!A22 -> 44902.416 | B22: ='Respuestas de formulario 1'!B22 -> Gonzalez | C22: ='Respuestas de formulario 1'!C22 -> Nicolas | D22: ='Respuestas de formulario 1'!D22 -> Nicomatigonzalez@hotmail.com | E22: ='Respuestas de formulario 1'!E22 -> 34786 | F22: ='Respuestas de formulario 1'!F22 -> 38749170 | G22: =IFERROR(__xludf.DUMMYFUNCTION("IF('Respuestas de formulario 1'!G22="""","""",IF(LEFT(REGEXREPLACE(TO_TEXT('Respuestas de formulario 1'!G22),""[^0-9]"",""""),2)=""54"",""+""&REGEXREPLACE(TO_TEXT('Respuestas de formulario 1'!G22),""[^0-9]"",""""),""+54""&REGEXREPLACE(TO_TEXT('Respuestas "&"de formulario 1'!G22),""[^0-9]"","""")))"),"+543512558234") -> +543512558234 | H22: ='Respuestas de formulario 1'!S22 -> 2022 | I22: =IFERROR(__xludf.DUMMYFUNCTION("IF('Respuestas de formulario 1'!I22="""","""",TO_TEXT('Respuestas de formulario 1'!I22))"),"Particular") -> Particular | J22: =IFERROR(__xludf.DUMMYFUNCTION("IF('Respuestas de formulario 1'!J22<>"""",UPPER(TRIM(TO_TEXT('Respuestas de formulario 1'!J22))),IF('Respuestas de formulario 1'!O22<>"""",UPPER(TRIM(TO_TEXT('Respuestas de formulario 1'!O22))),""""))"),"") | K22: =IFERROR(__xludf.DUMMYFUNCTION("IF('Respuestas de formulario 1'!K22="""","""",TO_TEXT('Respuestas de formulario 1'!K22))"),"") | L22: =IFERROR(__xludf.DUMMYFUNCTION("IF('Respuestas de formulario 1'!L22="""","""",TO_TEXT('Respuestas de formulario 1'!L22))"),"") | M22: =IFERROR(__xludf.DUMMYFUNCTION("IF('Respuestas de formulario 1'!M22="""","""",TO_TEXT('Respuestas de formulario 1'!M22))"),"") | N22: =IF(A22="","",IFERROR(YEAR(A22),"")) -> 2022 | O22: =IF(A22="","",IFERROR(TEXT(A22,"mmmm"),"")) -> diciembre | P22: Gonzalez Nicolas
A23: ='Respuestas de formulario 1'!A23 -> 44907.7 | B23: ='Respuestas de formulario 1'!B23 -> Araujo | C23: ='Respuestas de formulario 1'!C23 -> Dora Susana | D23: ='Respuestas de formulario 1'!D23 -> sietejuana@gmail.com | E23: ='Respuestas de formulario 1'!E23 -> 16564 | F23: ='Respuestas de formulario 1'!F23 -> 4647485 | G23: =IFERROR(__xludf.DUMMYFUNCTION("IF('Respuestas de formulario 1'!G23="""","""",IF(LEFT(REGEXREPLACE(TO_TEXT('Respuestas de formulario 1'!G23),""[^0-9]"",""""),2)=""54"",""+""&REGEXREPLACE(TO_TEXT('Respuestas de formulario 1'!G23),""[^0-9]"",""""),""+54""&REGEXREPLACE(TO_TEXT('Respuestas "&"de formulario 1'!G23),""[^0-9]"","""")))"),"+543513503636") -> +543513503636 | H23: ='Respuestas de formulario 1'!S23 -> 2022 | I23: =IFERROR(__xludf.DUMMYFUNCTION("IF('Respuestas de formulario 1'!I23="""","""",TO_TEXT('Respuestas de formulario 1'!I23))"),"Obra social") -> Obra social | J23: =IFERROR(__xludf.DUMMYFUNCTION("IF('Respuestas de formulario 1'!J23<>"""",UPPER(TRIM(TO_TEXT('Respuestas de formulario 1'!J23))),IF('Respuestas de formulario 1'!O23<>"""",UPPER(TRIM(TO_TEXT('Respuestas de formulario 1'!O23))),""""))"),"APROSS") -> APROSS | K23: =IFERROR(__xludf.DUMMYFUNCTION("IF('Respuestas de formulario 1'!K23="""","""",TO_TEXT('Respuestas de formulario 1'!K23))"),"") | L23: =IFERROR(__xludf.DUMMYFUNCTION("IF('Respuestas de formulario 1'!L23="""","""",TO_TEXT('Respuestas de formulario 1'!L23))"),"") | M23: =IFERROR(__xludf.DUMMYFUNCTION("IF('Respuestas de formulario 1'!M23="""","""",TO_TEXT('Respuestas de formulario 1'!M23))"),"") | N23: =IF(A23="","",IFERROR(YEAR(A23),"")) -> 2022 | O23: =IF(A23="","",IFERROR(TEXT(A23,"mmmm"),"")) -> diciembre | P23: Araujo Dora Susana
A24: ='Respuestas de formulario 1'!A24 -> 44908.351 | B24: ='Respuestas de formulario 1'!B24 -> Boasi | C24: ='Respuestas de formulario 1'!C24 -> Ivana | D24: ='Respuestas de formulario 1'!D24 -> ivanaboasi@gmail.com | E24: ='Respuestas de formulario 1'!E24 -> 30556 | F24: ='Respuestas de formulario 1'!F24 -> 30469315 | G24: =IFERROR(__xludf.DUMMYFUNCTION("IF('Respuestas de formulario 1'!G24="""","""",IF(LEFT(REGEXREPLACE(TO_TEXT('Respuestas de formulario 1'!G24),""[^0-9]"",""""),2)=""54"",""+""&REGEXREPLACE(TO_TEXT('Respuestas de formulario 1'!G24),""[^0-9]"",""""),""+54""&REGEXREPLACE(TO_TEXT('Respuestas "&"de formulario 1'!G24),""[^0-9]"","""")))"),"+543513732026") -> +543513732026 | H24: ='Respuestas de formulario 1'!S24 -> 2022 | I24: =IFERROR(__xludf.DUMMYFUNCTION("IF('Respuestas de formulario 1'!I24="""","""",TO_TEXT('Respuestas de formulario 1'!I24))"),"Particular") -> Particular | J24: =IFERROR(__xludf.DUMMYFUNCTION("IF('Respuestas de formulario 1'!J24<>"""",UPPER(TRIM(TO_TEXT('Respuestas de formulario 1'!J24))),IF('Respuestas de formulario 1'!O24<>"""",UPPER(TRIM(TO_TEXT('Respuestas de formulario 1'!O24))),""""))"),"") | K24: =IFERROR(__xludf.DUMMYFUNCTION("IF('Respuestas de formulario 1'!K24="""","""",TO_TEXT('Respuestas de formulario 1'!K24))"),"") | L24: =IFERROR(__xludf.DUMMYFUNCTION("IF('Respuestas de formulario 1'!L24="""","""",TO_TEXT('Respuestas de formulario 1'!L24))"),"") | M24: =IFERROR(__xludf.DUMMYFUNCTION("IF('Respuestas de formulario 1'!M24="""","""",TO_TEXT('Respuestas de formulario 1'!M24))"),"") | N24: =IF(A24="","",IFERROR(YEAR(A24),"")) -> 2022 | O24: =IF(A24="","",IFERROR(TEXT(A24,"mmmm"),"")) -> diciembre | P24: Boasi Ivana
A25: ='Respuestas de formulario 1'!A25 -> 44908.902 | B25: ='Respuestas de formulario 1'!B25 -> Ferreyra | C25: ='Respuestas de formulario 1'!C25 -> Ariel | D25: ='Respuestas de formulario 1'!D25 -> ariel.jferreyra@gmail.com | E25: ='Respuestas de formulario 1'!E25 -> ramos | F25: ='Respuestas de formulario 1'!F25 -> 24356325 | G25: =IFERROR(__xludf.DUMMYFUNCTION("IF('Respuestas de formulario 1'!G25="""","""",IF(LEFT(REGEXREPLACE(TO_TEXT('Respuestas de formulario 1'!G25),""[^0-9]"",""""),2)=""54"",""+""&REGEXREPLACE(TO_TEXT('Respuestas de formulario 1'!G25),""[^0-9]"",""""),""+54""&REGEXREPLACE(TO_TEXT('Respuestas "&"de formulario 1'!G25),""[^0-9]"","""")))"),"+543516535435") -> +543516535435 | H25: ='Respuestas de formulario 1'!S25 -> 2022 | I25: =IFERROR(__xludf.DUMMYFUNCTION("IF('Respuestas de formulario 1'!I25="""","""",TO_TEXT('Respuestas de formulario 1'!I25))"),"Obra social") -> Obra social | J25: =IFERROR(__xludf.DUMMYFUNCTION("IF('Respuestas de formulario 1'!J25<>"""",UPPER(TRIM(TO_TEXT('Respuestas de formulario 1'!J25))),IF('Respuestas de formulario 1'!O25<>"""",UPPER(TRIM(TO_TEXT('Respuestas de formulario 1'!O25))),""""))"),"") | K25: =IFERROR(__xludf.DUMMYFUNCTION("IF('Respuestas de formulario 1'!K25="""","""",TO_TEXT('Respuestas de formulario 1'!K25))"),"") | L25: =IFERROR(__xludf.DUMMYFUNCTION("IF('Respuestas de formulario 1'!L25="""","""",TO_TEXT('Respuestas de formulario 1'!L25))"),"") | M25: =IFERROR(__xludf.DUMMYFUNCTION("IF('Respuestas de formulario 1'!M25="""","""",TO_TEXT('Respuestas de formulario 1'!M25))"),"") | N25: =IF(A25="","",IFERROR(YEAR(A25),"")) -> 2022 | O25: =IF(A25="","",IFERROR(TEXT(A25,"mmmm"),"")) -> diciembre | P25: Ferreyra Ariel
A26: ='Respuestas de formulario 1'!A26 -> 44909.906 | B26: ='Respuestas de formulario 1'!B26 -> Baena | C26: ='Respuestas de formulario 1'!C26 -> Gustavo Ariel | D26: ='Respuestas de formulario 1'!D26 -> arielbaena@hotmail.com.ar | E26: ='Respuestas de formulario 1'!E26 -> 26901 | F26: ='Respuestas de formulario 1'!F26 -> 23440420 | G26: =IFERROR(__xludf.DUMMYFUNCTION("IF('Respuestas de formulario 1'!G26="""","""",IF(LEFT(REGEXREPLACE(TO_TEXT('Respuestas de formulario 1'!G26),""[^0-9]"",""""),2)=""54"",""+""&REGEXREPLACE(TO_TEXT('Respuestas de formulario 1'!G26),""[^0-9]"",""""),""+54""&REGEXREPLACE(TO_TEXT('Respuestas "&"de formulario 1'!G26),""[^0-9]"","""")))"),"+543516419517") -> +543516419517 | H26: ='Respuestas de formulario 1'!S26 -> 2022 | I26: =IFERROR(__xludf.DUMMYFUNCTION("IF('Respuestas de formulario 1'!I26="""","""",TO_TEXT('Respuestas de formulario 1'!I26))"),"Obra social") -> Obra social | J26: =IFERROR(__xludf.DUMMYFUNCTION("IF('Respuestas de formulario 1'!J26<>"""",UPPER(TRIM(TO_TEXT('Respuestas de formulario 1'!J26))),IF('Respuestas de formulario 1'!O26<>"""",UPPER(TRIM(TO_TEXT('Respuestas de formulario 1'!O26))),""""))"),"APROSS") -> APROSS | K26: =IFERROR(__xludf.DUMMYFUNCTION("IF('Respuestas de formulario 1'!K26="""","""",TO_TEXT('Respuestas de formulario 1'!K26))"),"") | L26: =IFERROR(__xludf.DUMMYFUNCTION("IF('Respuestas de formulario 1'!L26="""","""",TO_TEXT('Respuestas de formulario 1'!L26))"),"") | M26: =IFERROR(__xludf.DUMMYFUNCTION("IF('Respuestas de formulario 1'!M26="""","""",TO_TEXT('Respuestas de formulario 1'!M26))"),"") | N26: =IF(A26="","",IFERROR(YEAR(A26),"")) -> 2022 | O26: =IF(A26="","",IFERROR(TEXT(A26,"mmmm"),"")) -> diciembre | P26: Baena Gustavo Ariel
A27: ='Respuestas de formulario 1'!A27 -> 44911.649 | B27: ='Respuestas de formulario 1'!B27 -> Lozano | C27: ='Respuestas de formulario 1'!C27 -> Ezequiel | D27: ='Respuestas de formulario 1'!D27 -> ezelozano7@gmail.com | E27: ='Respuestas de formulario 1'!E27 -> 34581 | F27: ='Respuestas de formulario 1'!F27 -> 38412070 | G27: =IFERROR(__xludf.DUMMYFUNCTION("IF('Respuestas de formulario 1'!G27="""","""",IF(LEFT(REGEXREPLACE(TO_TEXT('Respuestas de formulario 1'!G27),""[^0-9]"",""""),2)=""54"",""+""&REGEXREPLACE(TO_TEXT('Respuestas de formulario 1'!G27),""[^0-9]"",""""),""+54""&REGEXREPLACE(TO_TEXT('Respuestas "&"de formulario 1'!G27),""[^0-9]"","""")))"),"+543517384848") -> +543517384848 | H27: ='Respuestas de formulario 1'!S27 -> 2022 | I27: =IFERROR(__xludf.DUMMYFUNCTION("IF('Respuestas de formulario 1'!I27="""","""",TO_TEXT('Respuestas de formulario 1'!I27))"),"Particular") -> Particular | J27: =IFERROR(__xludf.DUMMYFUNCTION("IF('Respuestas de formulario 1'!J27<>"""",UPPER(TRIM(TO_TEXT('Respuestas de formulario 1'!J27))),IF('Respuestas de formulario 1'!O27<>"""",UPPER(TRIM(TO_TEXT('Respuestas de formulario 1'!O27))),""""))"),"") | K27: =IFERROR(__xludf.DUMMYFUNCTION("IF('Respuestas de formulario 1'!K27="""","""",TO_TEXT('Respuestas de formulario 1'!K27))"),"") | L27: =IFERROR(__xludf.DUMMYFUNCTION("IF('Respuestas de formulario 1'!L27="""","""",TO_TEXT('Respuestas de formulario 1'!L27))"),"") | M27: =IFERROR(__xludf.DUMMYFUNCTION("IF('Respuestas de formulario 1'!M27="""","""",TO_TEXT('Respuestas de formulario 1'!M27))"),"") | N27: =IF(A27="","",IFERROR(YEAR(A27),"")) -> 2022 | O27: =IF(A27="","",IFERROR(TEXT(A27,"mmmm"),"")) -> diciembre | P27: Lozano Ezequiel
A28: ='Respuestas de formulario 1'!A28 -> 44918.476 | B28: ='Respuestas de formulario 1'!B28 -> Lazcano | C28: ='Respuestas de formulario 1'!C28 -> Stella | D28: ='Respuestas de formulario 1'!D28 | E28: ='Respuestas de formulario 1'!E28 -> 16642 | F28: ='Respuestas de formulario 1'!F28 -> 5210099 | G28: =IFERROR(__xludf.DUMMYFUNCTION("IF('Respuestas de formulario 1'!G28="""","""",IF(LEFT(REGEXREPLACE(TO_TEXT('Respuestas de formulario 1'!G28),""[^0-9]"",""""),2)=""54"",""+""&REGEXREPLACE(TO_TEXT('Respuestas de formulario 1'!G28),""[^0-9]"",""""),""+54""&REGEXREPLACE(TO_TEXT('Respuestas "&"de formulario 1'!G28),""[^0-9]"","""")))"),"+543512757694") -> +543512757694 | H28: ='Respuestas de formulario 1'!S28 -> 2022 | I28: =IFERROR(__xludf.DUMMYFUNCTION("IF('Respuestas de formulario 1'!I28="""","""",TO_TEXT('Respuestas de formulario 1'!I28))"),"Obra social") -> Obra social | J28: =IFERROR(__xludf.DUMMYFUNCTION("IF('Respuestas de formulario 1'!J28<>"""",UPPER(TRIM(TO_TEXT('Respuestas de formulario 1'!J28))),IF('Respuestas de formulario 1'!O28<>"""",UPPER(TRIM(TO_TEXT('Respuestas de formulario 1'!O28))),""""))"),"APROSS") -> APROSS | K28: =IFERROR(__xludf.DUMMYFUNCTION("IF('Respuestas de formulario 1'!K28="""","""",TO_TEXT('Respuestas de formulario 1'!K28))"),"") | L28: =IFERROR(__xludf.DUMMYFUNCTION("IF('Respuestas de formulario 1'!L28="""","""",TO_TEXT('Respuestas de formulario 1'!L28))"),"") | M28: =IFERROR(__xludf.DUMMYFUNCTION("IF('Respuestas de formulario 1'!M28="""","""",TO_TEXT('Respuestas de formulario 1'!M28))"),"") | N28: =IF(A28="","",IFERROR(YEAR(A28),"")) -> 2022 | O28: =IF(A28="","",IFERROR(TEXT(A28,"mmmm"),"")) -> diciembre | P28: Lazcano Stella
A29: ='Respuestas de formulario 1'!A29 -> 44920.965 | B29: ='Respuestas de formulario 1'!B29 -> Accornero | C29: ='Respuestas de formulario 1'!C29 -> Ignacio | D29: ='Respuestas de formulario 1'!D29 -> nachoaccornero@hotmail.com | E29: ='Respuestas de formulario 1'!E29 -> 35767 | F29: ='Respuestas de formulario 1'!F29 -> 40815684 | G29: =IFERROR(__xludf.DUMMYFUNCTION("IF('Respuestas de formulario 1'!G29="""","""",IF(LEFT(REGEXREPLACE(TO_TEXT('Respuestas de formulario 1'!G29),""[^0-9]"",""""),2)=""54"",""+""&REGEXREPLACE(TO_TEXT('Respuestas de formulario 1'!G29),""[^0-9]"",""""),""+54""&REGEXREPLACE(TO_TEXT('Respuestas "&"de formulario 1'!G29),""[^0-9]"","""")))"),"+54665987371") -> +54665987371 | H29: ='Respuestas de formulario 1'!S29 -> 2022 | I29: =IFERROR(__xludf.DUMMYFUNCTION("IF('Respuestas de formulario 1'!I29="""","""",TO_TEXT('Respuestas de formulario 1'!I29))"),"Particular") -> Particular | J29: =IFERROR(__xludf.DUMMYFUNCTION("IF('Respuestas de formulario 1'!J29<>"""",UPPER(TRIM(TO_TEXT('Respuestas de formulario 1'!J29))),IF('Respuestas de formulario 1'!O29<>"""",UPPER(TRIM(TO_TEXT('Respuestas de formulario 1'!O29))),""""))"),"") | K29: =IFERROR(__xludf.DUMMYFUNCTION("IF('Respuestas de formulario 1'!K29="""","""",TO_TEXT('Respuestas de formulario 1'!K29))"),"") | L29: =IFERROR(__xludf.DUMMYFUNCTION("IF('Respuestas de formulario 1'!L29="""","""",TO_TEXT('Respuestas de formulario 1'!L29))"),"") | M29: =IFERROR(__xludf.DUMMYFUNCTION("IF('Respuestas de formulario 1'!M29="""","""",TO_TEXT('Respuestas de formulario 1'!M29))"),"") | N29: =IF(A29="","",IFERROR(YEAR(A29),"")) -> 2022 | O29: =IF(A29="","",IFERROR(TEXT(A29,"mmmm"),"")) -> diciembre | P29: Accornero Ignacio
A30: ='Respuestas de formulario 1'!A30 -> 44921.73 | B30: ='Respuestas de formulario 1'!B30 -> Ortelli | C30: ='Respuestas de formulario 1'!C30 -> Esther | D30: ='Respuestas de formulario 1'!D30 -> esther.tarantino@hotmail.com | E30: ='Respuestas de formulario 1'!E30 -> 16144 | F30: ='Respuestas de formulario 1'!F30 -> 4789045 | G30: =IFERROR(__xludf.DUMMYFUNCTION("IF('Respuestas de formulario 1'!G30="""","""",IF(LEFT(REGEXREPLACE(TO_TEXT('Respuestas de formulario 1'!G30),""[^0-9]"",""""),2)=""54"",""+""&REGEXREPLACE(TO_TEXT('Respuestas de formulario 1'!G30),""[^0-9]"",""""),""+54""&REGEXREPLACE(TO_TEXT('Respuestas "&"de formulario 1'!G30),""[^0-9]"","""")))"),"+543515306152") -> +543515306152 | H30: ='Respuestas de formulario 1'!S30 -> 2022 | I30: =IFERROR(__xludf.DUMMYFUNCTION("IF('Respuestas de formulario 1'!I30="""","""",TO_TEXT('Respuestas de formulario 1'!I30))"),"Obra social") -> Obra social | J30: =IFERROR(__xludf.DUMMYFUNCTION("IF('Respuestas de formulario 1'!J30<>"""",UPPER(TRIM(TO_TEXT('Respuestas de formulario 1'!J30))),IF('Respuestas de formulario 1'!O30<>"""",UPPER(TRIM(TO_TEXT('Respuestas de formulario 1'!O30))),""""))"),"CPCE") -> CPCE | K30: =IFERROR(__xludf.DUMMYFUNCTION("IF('Respuestas de formulario 1'!K30="""","""",TO_TEXT('Respuestas de formulario 1'!K30))"),"") | L30: =IFERROR(__xludf.DUMMYFUNCTION("IF('Respuestas de formulario 1'!L30="""","""",TO_TEXT('Respuestas de formulario 1'!L30))"),"") | M30: =IFERROR(__xludf.DUMMYFUNCTION("IF('Respuestas de formulario 1'!M30="""","""",TO_TEXT('Respuestas de formulario 1'!M30))"),"") | N30: =IF(A30="","",IFERROR(YEAR(A30),"")) -> 2022 | O30: =IF(A30="","",IFERROR(TEXT(A30,"mmmm"),"")) -> diciembre | P30: Ortelli Esther
A31: ='Respuestas de formulario 1'!A31 -> 44923.411 | B31: ='Respuestas de formulario 1'!B31 -> Sibona | C31: ='Respuestas de formulario 1'!C31 -> Karina | D31: ='Respuestas de formulario 1'!D31 -> karinasibona@hotmail.com | E31: ='Respuestas de formulario 1'!E31 -> 26650 | F31: ='Respuestas de formulario 1'!F31 -> 22795191 | G31: =IFERROR(__xludf.DUMMYFUNCTION("IF('Respuestas de formulario 1'!G31="""","""",IF(LEFT(REGEXREPLACE(TO_TEXT('Respuestas de formulario 1'!G31),""[^0-9]"",""""),2)=""54"",""+""&REGEXREPLACE(TO_TEXT('Respuestas de formulario 1'!G31),""[^0-9]"",""""),""+54""&REGEXREPLACE(TO_TEXT('Respuestas "&"de formulario 1'!G31),""[^0-9]"","""")))"),"+543512588741") -> +543512588741 | H31: ='Respuestas de formulario 1'!S31 -> 2022 | I31: =IFERROR(__xludf.DUMMYFUNCTION("IF('Respuestas de formulario 1'!I31="""","""",TO_TEXT('Respuestas de formulario 1'!I31))"),"Obra social") -> Obra social | J31: =IFERROR(__xludf.DUMMYFUNCTION("IF('Respuestas de formulario 1'!J31<>"""",UPPER(TRIM(TO_TEXT('Respuestas de formulario 1'!J31))),IF('Respuestas de formulario 1'!O31<>"""",UPPER(TRIM(TO_TEXT('Respuestas de formulario 1'!O31))),""""))"),"CPCE") -> CPCE | K31: =IFERROR(__xludf.DUMMYFUNCTION("IF('Respuestas de formulario 1'!K31="""","""",TO_TEXT('Respuestas de formulario 1'!K31))"),"") | L31: =IFERROR(__xludf.DUMMYFUNCTION("IF('Respuestas de formulario 1'!L31="""","""",TO_TEXT('Respuestas de formulario 1'!L31))"),"") | M31: =IFERROR(__xludf.DUMMYFUNCTION("IF('Respuestas de formulario 1'!M31="""","""",TO_TEXT('Respuestas de formulario 1'!M31))"),"") | N31: =IF(A31="","",IFERROR(YEAR(A31),"")) -> 2022 | O31: =IF(A31="","",IFERROR(TEXT(A31,"mmmm"),"")) -> diciembre | P31: Sibona Karina
A32: ='Respuestas de formulario 1'!A32 -> 44923.412 | B32: ='Respuestas de formulario 1'!B32 -> Pepi | C32: ='Respuestas de formulario 1'!C32 -> Bettina | D32: ='Respuestas de formulario 1'!D32 -> karinasibona@hotmail.com | E32: ='Respuestas de formulario 1'!E32 -> 41264 | F32: ='Respuestas de formulario 1'!F32 -> 52466966 | G32: =IFERROR(__xludf.DUMMYFUNCTION("IF('Respuestas de formulario 1'!G32="""","""",IF(LEFT(REGEXREPLACE(TO_TEXT('Respuestas de formulario 1'!G32),""[^0-9]"",""""),2)=""54"",""+""&REGEXREPLACE(TO_TEXT('Respuestas de formulario 1'!G32),""[^0-9]"",""""),""+54""&REGEXREPLACE(TO_TEXT('Respuestas "&"de formulario 1'!G32),""[^0-9]"","""")))"),"+543512588741") -> +543512588741 | H32: ='Respuestas de formulario 1'!S32 -> 2022 | I32: =IFERROR(__xludf.DUMMYFUNCTION("IF('Respuestas de formulario 1'!I32="""","""",TO_TEXT('Respuestas de formulario 1'!I32))"),"Obra social") -> Obra social | J32: =IFERROR(__xludf.DUMMYFUNCTION("IF('Respuestas de formulario 1'!J32<>"""",UPPER(TRIM(TO_TEXT('Respuestas de formulario 1'!J32))),IF('Respuestas de formulario 1'!O32<>"""",UPPER(TRIM(TO_TEXT('Respuestas de formulario 1'!O32))),""""))"),"CPCE") -> CPCE | K32: =IFERROR(__xludf.DUMMYFUNCTION("IF('Respuestas de formulario 1'!K32="""","""",TO_TEXT('Respuestas de formulario 1'!K32))"),"") | L32: =IFERROR(__xludf.DUMMYFUNCTION("IF('Respuestas de formulario 1'!L32="""","""",TO_TEXT('Respuestas de formulario 1'!L32))"),"") | M32: =IFERROR(__xludf.DUMMYFUNCTION("IF('Respuestas de formulario 1'!M32="""","""",TO_TEXT('Respuestas de formulario 1'!M32))"),"") | N32: =IF(A32="","",IFERROR(YEAR(A32),"")) -> 2022 | O32: =IF(A32="","",IFERROR(TEXT(A32,"mmmm"),"")) -> diciembre | P32: Pepi Bettina
A33: ='Respuestas de formulario 1'!A33 -> 44924.73 | B33: ='Respuestas de formulario 1'!B33 -> Cardoni | C33: ='Respuestas de formulario 1'!C33 -> Gino | D33: ='Respuestas de formulario 1'!D33 -> gino.baret@gmail.com | E33: ='Respuestas de formulario 1'!E33 -> 31877 | F33: ='Respuestas de formulario 1'!F33 -> 33117511 | G33: =IFERROR(__xludf.DUMMYFUNCTION("IF('Respuestas de formulario 1'!G33="""","""",IF(LEFT(REGEXREPLACE(TO_TEXT('Respuestas de formulario 1'!G33),""[^0-9]"",""""),2)=""54"",""+""&REGEXREPLACE(TO_TEXT('Respuestas de formulario 1'!G33),""[^0-9]"",""""),""+54""&REGEXREPLACE(TO_TEXT('Respuestas "&"de formulario 1'!G33),""[^0-9]"","""")))"),"+543512287296") -> +543512287296 | H33: ='Respuestas de formulario 1'!S33 -> 2022 | I33: =IFERROR(__xludf.DUMMYFUNCTION("IF('Respuestas de formulario 1'!I33="""","""",TO_TEXT('Respuestas de formulario 1'!I33))"),"Particular") -> Particular | J33: =IFERROR(__xludf.DUMMYFUNCTION("IF('Respuestas de formulario 1'!J33<>"""",UPPER(TRIM(TO_TEXT('Respuestas de formulario 1'!J33))),IF('Respuestas de formulario 1'!O33<>"""",UPPER(TRIM(TO_TEXT('Respuestas de formulario 1'!O33))),""""))"),"") | K33: =IFERROR(__xludf.DUMMYFUNCTION("IF('Respuestas de formulario 1'!K33="""","""",TO_TEXT('Respuestas de formulario 1'!K33))"),"") | L33: =IFERROR(__xludf.DUMMYFUNCTION("IF('Respuestas de formulario 1'!L33="""","""",TO_TEXT('Respuestas de formulario 1'!L33))"),"") | M33: =IFERROR(__xludf.DUMMYFUNCTION("IF('Respuestas de formulario 1'!M33="""","""",TO_TEXT('Respuestas de formulario 1'!M33))"),"") | N33: =IF(A33="","",IFERROR(YEAR(A33),"")) -> 2022 | O33: =IF(A33="","",IFERROR(TEXT(A33,"mmmm"),"")) -> diciembre | P33: Cardoni Gino
A34: ='Respuestas de formulario 1'!A34 -> 44924.838 | B34: ='Respuestas de formulario 1'!B34 -> Gutiérrez | C34: ='Respuestas de formulario 1'!C34 -> Ángela nora | D34: ='Respuestas de formulario 1'!D34 -> angelanoragutierrez03@gmail.com | E34: ='Respuestas de formulario 1'!E34 -> 18600 | F34: ='Respuestas de formulario 1'!F34 -> 6259516 | G34: =IFERROR(__xludf.DUMMYFUNCTION("IF('Respuestas de formulario 1'!G34="""","""",IF(LEFT(REGEXREPLACE(TO_TEXT('Respuestas de formulario 1'!G34),""[^0-9]"",""""),2)=""54"",""+""&REGEXREPLACE(TO_TEXT('Respuestas de formulario 1'!G34),""[^0-9]"",""""),""+54""&REGEXREPLACE(TO_TEXT('Respuestas "&"de formulario 1'!G34),""[^0-9]"","""")))"),"+543512484269") -> +543512484269 | H34: ='Respuestas de formulario 1'!S34 -> 2022 | I34: =IFERROR(__xludf.DUMMYFUNCTION("IF('Respuestas de formulario 1'!I34="""","""",TO_TEXT('Respuestas de formulario 1'!I34))"),"Obra social") -> Obra social | J34: =IFERROR(__xludf.DUMMYFUNCTION("IF('Respuestas de formulario 1'!J34<>"""",UPPER(TRIM(TO_TEXT('Respuestas de formulario 1'!J34))),IF('Respuestas de formulario 1'!O34<>"""",UPPER(TRIM(TO_TEXT('Respuestas de formulario 1'!O34))),""""))"),"APROSS") -> APROSS | K34: =IFERROR(__xludf.DUMMYFUNCTION("IF('Respuestas de formulario 1'!K34="""","""",TO_TEXT('Respuestas de formulario 1'!K34))"),"") | L34: =IFERROR(__xludf.DUMMYFUNCTION("IF('Respuestas de formulario 1'!L34="""","""",TO_TEXT('Respuestas de formulario 1'!L34))"),"") | M34: =IFERROR(__xludf.DUMMYFUNCTION("IF('Respuestas de formulario 1'!M34="""","""",TO_TEXT('Respuestas de formulario 1'!M34))"),"") | N34: =IF(A34="","",IFERROR(YEAR(A34),"")) -> 2022 | O34: =IF(A34="","",IFERROR(TEXT(A34,"mmmm"),"")) -> diciembre | P34: Gutiérrez Ángela nora
A35: ='Respuestas de formulario 1'!A35 -> 44926.812 | B35: ='Respuestas de formulario 1'!B35 -> Heredia Pereyra | C35: ='Respuestas de formulario 1'!C35 -> Mercedes Andrea | D35: ='Respuestas de formulario 1'!D35 -> mercedesahp@hotmail.com | E35: ='Respuestas de formulario 1'!E35 -> 29279 | F35: ='Respuestas de formulario 1'!F35 -> 27955896 | G35: =IFERROR(__xludf.DUMMYFUNCTION("IF('Respuestas de formulario 1'!G35="""","""",IF(LEFT(REGEXREPLACE(TO_TEXT('Respuestas de formulario 1'!G35),""[^0-9]"",""""),2)=""54"",""+""&REGEXREPLACE(TO_TEXT('Respuestas de formulario 1'!G35),""[^0-9]"",""""),""+54""&REGEXREPLACE(TO_TEXT('Respuestas "&"de formulario 1'!G35),""[^0-9]"","""")))"),"+543513401354") -> +543513401354 | H35: ='Respuestas de formulario 1'!S35 -> 2022 | I35: =IFERROR(__xludf.DUMMYFUNCTION("IF('Respuestas de formulario 1'!I35="""","""",TO_TEXT('Respuestas de formulario 1'!I35))"),"Obra social") -> Obra social | J35: =IFERROR(__xludf.DUMMYFUNCTION("IF('Respuestas de formulario 1'!J35<>"""",UPPER(TRIM(TO_TEXT('Respuestas de formulario 1'!J35))),IF('Respuestas de formulario 1'!O35<>"""",UPPER(TRIM(TO_TEXT('Respuestas de formulario 1'!O35))),""""))"),"APROSS") -> APROSS | K35: =IFERROR(__xludf.DUMMYFUNCTION("IF('Respuestas de formulario 1'!K35="""","""",TO_TEXT('Respuestas de formulario 1'!K35))"),"") | L35: =IFERROR(__xludf.DUMMYFUNCTION("IF('Respuestas de formulario 1'!L35="""","""",TO_TEXT('Respuestas de formulario 1'!L35))"),"") | M35: =IFERROR(__xludf.DUMMYFUNCTION("IF('Respuestas de formulario 1'!M35="""","""",TO_TEXT('Respuestas de formulario 1'!M35))"),"") | N35: =IF(A35="","",IFERROR(YEAR(A35),"")) -> 2022 | O35: =IF(A35="","",IFERROR(TEXT(A35,"mmmm"),"")) -> diciembre | P35: Heredia Pereyra Mercedes Andrea
A36: ='Respuestas de formulario 1'!A36 -> 44928.448 | B36: ='Respuestas de formulario 1'!B36 -> Perini | C36: ='Respuestas de formulario 1'!C36 -> Leonardo | D36: ='Respuestas de formulario 1'!D36 -> Lf04_cba@hotmail.com | E36: ='Respuestas de formulario 1'!E36 -> 32451 | F36: ='Respuestas de formulario 1'!F36 -> 34069704 | G36: =IFERROR(__xludf.DUMMYFUNCTION("IF('Respuestas de formulario 1'!G36="""","""",IF(LEFT(REGEXREPLACE(TO_TEXT('Respuestas de formulario 1'!G36),""[^0-9]"",""""),2)=""54"",""+""&REGEXREPLACE(TO_TEXT('Respuestas de formulario 1'!G36),""[^0-9]"",""""),""+54""&REGEXREPLACE(TO_TEXT('Respuestas "&"de formulario 1'!G36),""[^0-9]"","""")))"),"+543512615886") -> +543512615886 | H36: ='Respuestas de formulario 1'!S36 -> 2023 | I36: =IFERROR(__xludf.DUMMYFUNCTION("IF('Respuestas de formulario 1'!I36="""","""",TO_TEXT('Respuestas de formulario 1'!I36))"),"Particular") -> Particular | J36: =IFERROR(__xludf.DUMMYFUNCTION("IF('Respuestas de formulario 1'!J36<>"""",UPPER(TRIM(TO_TEXT('Respuestas de formulario 1'!J36))),IF('Respuestas de formulario 1'!O36<>"""",UPPER(TRIM(TO_TEXT('Respuestas de formulario 1'!O36))),""""))"),"") | K36: =IFERROR(__xludf.DUMMYFUNCTION("IF('Respuestas de formulario 1'!K36="""","""",TO_TEXT('Respuestas de formulario 1'!K36))"),"") | L36: =IFERROR(__xludf.DUMMYFUNCTION("IF('Respuestas de formulario 1'!L36="""","""",TO_TEXT('Respuestas de formulario 1'!L36))"),"") | M36: =IFERROR(__xludf.DUMMYFUNCTION("IF('Respuestas de formulario 1'!M36="""","""",TO_TEXT('Respuestas de formulario 1'!M36))"),"") | N36: =IF(A36="","",IFERROR(YEAR(A36),"")) -> 2023 | O36: =IF(A36="","",IFERROR(TEXT(A36,"mmmm"),"")) -> enero | P36: Perini Leonardo
A37: ='Respuestas de formulario 1'!A37 -> 44928.826 | B37: ='Respuestas de formulario 1'!B37 -> Brun | C37: ='Respuestas de formulario 1'!C37 -> Luciano | D37: ='Respuestas de formulario 1'!D37 -> lucianobrun@hotmail.com | E37: ='Respuestas de formulario 1'!E37 -> 29722 | F37: ='Respuestas de formulario 1'!F37 -> 28850950 | G37: =IFERROR(__xludf.DUMMYFUNCTION("IF('Respuestas de formulario 1'!G37="""","""",IF(LEFT(REGEXREPLACE(TO_TEXT('Respuestas de formulario 1'!G37),""[^0-9]"",""""),2)=""54"",""+""&REGEXREPLACE(TO_TEXT('Respuestas de formulario 1'!G37),""[^0-9]"",""""),""+54""&REGEXREPLACE(TO_TEXT('Respuestas "&"de formulario 1'!G37),""[^0-9]"","""")))"),"+543513904324") -> +543513904324 | H37: ='Respuestas de formulario 1'!S37 -> 2023 | I37: =IFERROR(__xludf.DUMMYFUNCTION("IF('Respuestas de formulario 1'!I37="""","""",TO_TEXT('Respuestas de formulario 1'!I37))"),"Particular") -> Particular | J37: =IFERROR(__xludf.DUMMYFUNCTION("IF('Respuestas de formulario 1'!J37<>"""",UPPER(TRIM(TO_TEXT('Respuestas de formulario 1'!J37))),IF('Respuestas de formulario 1'!O37<>"""",UPPER(TRIM(TO_TEXT('Respuestas de formulario 1'!O37))),""""))"),"") | K37: =IFERROR(__xludf.DUMMYFUNCTION("IF('Respuestas de formulario 1'!K37="""","""",TO_TEXT('Respuestas de formulario 1'!K37))"),"") | L37: =IFERROR(__xludf.DUMMYFUNCTION("IF('Respuestas de formulario 1'!L37="""","""",TO_TEXT('Respuestas de formulario 1'!L37))"),"") | M37: =IFERROR(__xludf.DUMMYFUNCTION("IF('Respuestas de formulario 1'!M37="""","""",TO_TEXT('Respuestas de formulario 1'!M37))"),"") | N37: =IF(A37="","",IFERROR(YEAR(A37),"")) -> 2023 | O37: =IF(A37="","",IFERROR(TEXT(A37,"mmmm"),"")) -> enero | P37: Brun Luciano
A38: ='Respuestas de formulario 1'!A38 -> 44930.686 | B38: ='Respuestas de formulario 1'!B38 -> Dolivo | C38: ='Respuestas de formulario 1'!C38 -> Josefina | D38: ='Respuestas de formulario 1'!D38 -> dolivojosefina@gmail.com | E38: ='Respuestas de formulario 1'!E38 -> 33208 | F38: ='Respuestas de formulario 1'!F38 -> 35564552 | G38: =IFERROR(__xludf.DUMMYFUNCTION("IF('Respuestas de formulario 1'!G38="""","""",IF(LEFT(REGEXREPLACE(TO_TEXT('Respuestas de formulario 1'!G38),""[^0-9]"",""""),2)=""54"",""+""&REGEXREPLACE(TO_TEXT('Respuestas de formulario 1'!G38),""[^0-9]"",""""),""+54""&REGEXREPLACE(TO_TEXT('Respuestas "&"de formulario 1'!G38),""[^0-9]"","""")))"),"+543525454941") -> +543525454941 | H38: ='Respuestas de formulario 1'!S38 -> 2023 | I38: =IFERROR(__xludf.DUMMYFUNCTION("IF('Respuestas de formulario 1'!I38="""","""",TO_TEXT('Respuestas de formulario 1'!I38))"),"Obra social") -> Obra social | J38: =IFERROR(__xludf.DUMMYFUNCTION("IF('Respuestas de formulario 1'!J38<>"""",UPPER(TRIM(TO_TEXT('Respuestas de formulario 1'!J38))),IF('Respuestas de formulario 1'!O38<>"""",UPPER(TRIM(TO_TEXT('Respuestas de formulario 1'!O38))),""""))"),"SANCOR") -> SANCOR | K38: =IFERROR(__xludf.DUMMYFUNCTION("IF('Respuestas de formulario 1'!K38="""","""",TO_TEXT('Respuestas de formulario 1'!K38))"),"") | L38: =IFERROR(__xludf.DUMMYFUNCTION("IF('Respuestas de formulario 1'!L38="""","""",TO_TEXT('Respuestas de formulario 1'!L38))"),"") | M38: =IFERROR(__xludf.DUMMYFUNCTION("IF('Respuestas de formulario 1'!M38="""","""",TO_TEXT('Respuestas de formulario 1'!M38))"),"") | N38: =IF(A38="","",IFERROR(YEAR(A38),"")) -> 2023 | O38: =IF(A38="","",IFERROR(TEXT(A38,"mmmm"),"")) -> enero | P38: Dolivo Josefina
A39: ='Respuestas de formulario 1'!A39 -> 44930.971 | B39: ='Respuestas de formulario 1'!B39 -> LASTRA | C39: ='Respuestas de formulario 1'!C39 -> MELISA | D39: ='Respuestas de formulario 1'!D39 -> MELISALASTRA@GMAIL.COM | E39: ='Respuestas de formulario 1'!E39 -> 32449 | F39: ='Respuestas de formulario 1'!F39 -> 33976093 | G39: =IFERROR(__xludf.DUMMYFUNCTION("IF('Respuestas de formulario 1'!G39="""","""",IF(LEFT(REGEXREPLACE(TO_TEXT('Respuestas de formulario 1'!G39),""[^0-9]"",""""),2)=""54"",""+""&REGEXREPLACE(TO_TEXT('Respuestas de formulario 1'!G39),""[^0-9]"",""""),""+54""&REGEXREPLACE(TO_TEXT('Respuestas "&"de formulario 1'!G39),""[^0-9]"","""")))"),"+543512441614") -> +543512441614 | H39: ='Respuestas de formulario 1'!S39 -> 2023 | I39: =IFERROR(__xludf.DUMMYFUNCTION("IF('Respuestas de formulario 1'!I39="""","""",TO_TEXT('Respuestas de formulario 1'!I39))"),"Obra social") -> Obra social | J39: =IFERROR(__xludf.DUMMYFUNCTION("IF('Respuestas de formulario 1'!J39<>"""",UPPER(TRIM(TO_TEXT('Respuestas de formulario 1'!J39))),IF('Respuestas de formulario 1'!O39<>"""",UPPER(TRIM(TO_TEXT('Respuestas de formulario 1'!O39))),""""))"),"A.P.M") -> A.P.M | K39: =IFERROR(__xludf.DUMMYFUNCTION("IF('Respuestas de formulario 1'!K39="""","""",TO_TEXT('Respuestas de formulario 1'!K39))"),"") | L39: =IFERROR(__xludf.DUMMYFUNCTION("IF('Respuestas de formulario 1'!L39="""","""",TO_TEXT('Respuestas de formulario 1'!L39))"),"") | M39: =IFERROR(__xludf.DUMMYFUNCTION("IF('Respuestas de formulario 1'!M39="""","""",TO_TEXT('Respuestas de formulario 1'!M39))"),"") | N39: =IF(A39="","",IFERROR(YEAR(A39),"")) -> 2023 | O39: =IF(A39="","",IFERROR(TEXT(A39,"mmmm"),"")) -> enero | P39: LASTRA MELISA
A40: ='Respuestas de formulario 1'!A40 -> 44932.671 | B40: ='Respuestas de formulario 1'!B40 -> Menzi | C40: ='Respuestas de formulario 1'!C40 -> Antonio | D40: ='Respuestas de formulario 1'!D40 -> tony.menzi@gmail.com | E40: ='Respuestas de formulario 1'!E40 -> 35720 | F40: ='Respuestas de formulario 1'!F40 -> 40686489 | G40: =IFERROR(__xludf.DUMMYFUNCTION("IF('Respuestas de formulario 1'!G40="""","""",IF(LEFT(REGEXREPLACE(TO_TEXT('Respuestas de formulario 1'!G40),""[^0-9]"",""""),2)=""54"",""+""&REGEXREPLACE(TO_TEXT('Respuestas de formulario 1'!G40),""[^0-9]"",""""),""+54""&REGEXREPLACE(TO_TEXT('Respuestas "&"de formulario 1'!G40),""[^0-9]"","""")))"),"+543512064245") -> +543512064245 | H40: ='Respuestas de formulario 1'!S40 -> 2023 | I40: =IFERROR(__xludf.DUMMYFUNCTION("IF('Respuestas de formulario 1'!I40="""","""",TO_TEXT('Respuestas de formulario 1'!I40))"),"Obra social") -> Obra social | J40: =IFERROR(__xludf.DUMMYFUNCTION("IF('Respuestas de formulario 1'!J40<>"""",UPPER(TRIM(TO_TEXT('Respuestas de formulario 1'!J40))),IF('Respuestas de formulario 1'!O40<>"""",UPPER(TRIM(TO_TEXT('Respuestas de formulario 1'!O40))),""""))"),"PREVENCIÓN") -> PREVENCIÓN | K40: =IFERROR(__xludf.DUMMYFUNCTION("IF('Respuestas de formulario 1'!K40="""","""",TO_TEXT('Respuestas de formulario 1'!K40))"),"") | L40: =IFERROR(__xludf.DUMMYFUNCTION("IF('Respuestas de formulario 1'!L40="""","""",TO_TEXT('Respuestas de formulario 1'!L40))"),"") | M40: =IFERROR(__xludf.DUMMYFUNCTION("IF('Respuestas de formulario 1'!M40="""","""",TO_TEXT('Respuestas de formulario 1'!M40))"),"") | N40: =IF(A40="","",IFERROR(YEAR(A40),"")) -> 2023 | O40: =IF(A40="","",IFERROR(TEXT(A40,"mmmm"),"")) -> enero | P40: Menzi Antonio
A41: ='Respuestas de formulario 1'!A41 -> 44935.811 | B41: ='Respuestas de formulario 1'!B41 -> MARQUEZ | C41: ='Respuestas de formulario 1'!C41 -> ELENA BEATRIZ | D41: ='Respuestas de formulario 1'!D41 -> elenabeatrizmarquez@g.mail.com | E41: ='Respuestas de formulario 1'!E41 -> 20145 | F41: ='Respuestas de formulario 1'!F41 -> 11745268 | G41: =IFERROR(__xludf.DUMMYFUNCTION("IF('Respuestas de formulario 1'!G41="""","""",IF(LEFT(REGEXREPLACE(TO_TEXT('Respuestas de formulario 1'!G41),""[^0-9]"",""""),2)=""54"",""+""&REGEXREPLACE(TO_TEXT('Respuestas de formulario 1'!G41),""[^0-9]"",""""),""+54""&REGEXREPLACE(TO_TEXT('Respuestas "&"de formulario 1'!G41),""[^0-9]"","""")))"),"+543512770181") -> +543512770181 | H41: ='Respuestas de formulario 1'!S41 -> 2023 | I41: =IFERROR(__xludf.DUMMYFUNCTION("IF('Respuestas de formulario 1'!I41="""","""",TO_TEXT('Respuestas de formulario 1'!I41))"),"Obra social") -> Obra social | J41: =IFERROR(__xludf.DUMMYFUNCTION("IF('Respuestas de formulario 1'!J41<>"""",UPPER(TRIM(TO_TEXT('Respuestas de formulario 1'!J41))),IF('Respuestas de formulario 1'!O41<>"""",UPPER(TRIM(TO_TEXT('Respuestas de formulario 1'!O41))),""""))"),"APROSS") -> APROSS | K41: =IFERROR(__xludf.DUMMYFUNCTION("IF('Respuestas de formulario 1'!K41="""","""",TO_TEXT('Respuestas de formulario 1'!K41))"),"") | L41: =IFERROR(__xludf.DUMMYFUNCTION("IF('Respuestas de formulario 1'!L41="""","""",TO_TEXT('Respuestas de formulario 1'!L41))"),"") | M41: =IFERROR(__xludf.DUMMYFUNCTION("IF('Respuestas de formulario 1'!M41="""","""",TO_TEXT('Respuestas de formulario 1'!M41))"),"") | N41: =IF(A41="","",IFERROR(YEAR(A41),"")) -> 2023 | O41: =IF(A41="","",IFERROR(TEXT(A41,"mmmm"),"")) -> enero | P41: MARQUEZ ELENA BEATRIZ
A42: ='Respuestas de formulario 1'!A42 -> 44937.558 | B42: ='Respuestas de formulario 1'!B42 -> Nievas Acosta | C42: ='Respuestas de formulario 1'!C42 -> Marcos Daniel | D42: ='Respuestas de formulario 1'!D42 -> Mnievasacosta@gmail.com | E42: ='Respuestas de formulario 1'!E42 -> 34033 | F42: ='Respuestas de formulario 1'!F42 -> 37317203 | G42: =IFERROR(__xludf.DUMMYFUNCTION("IF('Respuestas de formulario 1'!G42="""","""",IF(LEFT(REGEXREPLACE(TO_TEXT('Respuestas de formulario 1'!G42),""[^0-9]"",""""),2)=""54"",""+""&REGEXREPLACE(TO_TEXT('Respuestas de formulario 1'!G42),""[^0-9]"",""""),""+54""&REGEXREPLACE(TO_TEXT('Respuestas "&"de formulario 1'!G42),""[^0-9]"","""")))"),"+543516558107") -> +543516558107 | H42: ='Respuestas de formulario 1'!S42 -> 2023 | I42: =IFERROR(__xludf.DUMMYFUNCTION("IF('Respuestas de formulario 1'!I42="""","""",TO_TEXT('Respuestas de formulario 1'!I42))"),"Particular") -> Particular | J42: =IFERROR(__xludf.DUMMYFUNCTION("IF('Respuestas de formulario 1'!J42<>"""",UPPER(TRIM(TO_TEXT('Respuestas de formulario 1'!J42))),IF('Respuestas de formulario 1'!O42<>"""",UPPER(TRIM(TO_TEXT('Respuestas de formulario 1'!O42))),""""))"),"") | K42: =IFERROR(__xludf.DUMMYFUNCTION("IF('Respuestas de formulario 1'!K42="""","""",TO_TEXT('Respuestas de formulario 1'!K42))"),"") | L42: =IFERROR(__xludf.DUMMYFUNCTION("IF('Respuestas de formulario 1'!L42="""","""",TO_TEXT('Respuestas de formulario 1'!L42))"),"") | M42: =IFERROR(__xludf.DUMMYFUNCTION("IF('Respuestas de formulario 1'!M42="""","""",TO_TEXT('Respuestas de formulario 1'!M42))"),"") | N42: =IF(A42="","",IFERROR(YEAR(A42),"")) -> 2023 | O42: =IF(A42="","",IFERROR(TEXT(A42,"mmmm"),"")) -> enero | P42: Nievas Acosta Marcos Daniel
A43: ='Respuestas de formulario 1'!A43 -> 44942.87 | B43: ='Respuestas de formulario 1'!B43 -> Vocos | C43: ='Respuestas de formulario 1'!C43 -> Lucia | D43: ='Respuestas de formulario 1'!D43 | E43: ='Respuestas de formulario 1'!E43 -> 32574 | F43: ='Respuestas de formulario 1'!F43 -> 34315567 | G43: =IFERROR(__xludf.DUMMYFUNCTION("IF('Respuestas de formulario 1'!G43="""","""",IF(LEFT(REGEXREPLACE(TO_TEXT('Respuestas de formulario 1'!G43),""[^0-9]"",""""),2)=""54"",""+""&REGEXREPLACE(TO_TEXT('Respuestas de formulario 1'!G43),""[^0-9]"",""""),""+54""&REGEXREPLACE(TO_TEXT('Respuestas "&"de formulario 1'!G43),""[^0-9]"","""")))"),"+5417677271846") -> +5417677271846 | H43: ='Respuestas de formulario 1'!S43 -> 2023 | I43: =IFERROR(__xludf.DUMMYFUNCTION("IF('Respuestas de formulario 1'!I43="""","""",TO_TEXT('Respuestas de formulario 1'!I43))"),"Particular") -> Particular | J43: =IFERROR(__xludf.DUMMYFUNCTION("IF('Respuestas de formulario 1'!J43<>"""",UPPER(TRIM(TO_TEXT('Respuestas de formulario 1'!J43))),IF('Respuestas de formulario 1'!O43<>"""",UPPER(TRIM(TO_TEXT('Respuestas de formulario 1'!O43))),""""))"),"") | K43: =IFERROR(__xludf.DUMMYFUNCTION("IF('Respuestas de formulario 1'!K43="""","""",TO_TEXT('Respuestas de formulario 1'!K43))"),"") | L43: =IFERROR(__xludf.DUMMYFUNCTION("IF('Respuestas de formulario 1'!L43="""","""",TO_TEXT('Respuestas de formulario 1'!L43))"),"") | M43: =IFERROR(__xludf.DUMMYFUNCTION("IF('Respuestas de formulario 1'!M43="""","""",TO_TEXT('Respuestas de formulario 1'!M43))"),"") | N43: =IF(A43="","",IFERROR(YEAR(A43),"")) -> 2023 | O43: =IF(A43="","",IFERROR(TEXT(A43,"mmmm"),"")) -> enero | P43: Vocos Lucia
A44: ='Respuestas de formulario 1'!A44 -> 44951.763 | B44: ='Respuestas de formulario 1'!B44 -> Garino | C44: ='Respuestas de formulario 1'!C44 -> Dario | D44: ='Respuestas de formulario 1'!D44 -> dariog128@hotmail.com | E44: ='Respuestas de formulario 1'!E44 -> 32583 | F44: ='Respuestas de formulario 1'!F44 -> 34247843 | G44: =IFERROR(__xludf.DUMMYFUNCTION("IF('Respuestas de formulario 1'!G44="""","""",IF(LEFT(REGEXREPLACE(TO_TEXT('Respuestas de formulario 1'!G44),""[^0-9]"",""""),2)=""54"",""+""&REGEXREPLACE(TO_TEXT('Respuestas de formulario 1'!G44),""[^0-9]"",""""),""+54""&REGEXREPLACE(TO_TEXT('Respuestas "&"de formulario 1'!G44),""[^0-9]"","""")))"),"+543515571888") -> +543515571888 | H44: ='Respuestas de formulario 1'!S44 -> 2023 | I44: =IFERROR(__xludf.DUMMYFUNCTION("IF('Respuestas de formulario 1'!I44="""","""",TO_TEXT('Respuestas de formulario 1'!I44))"),"Particular") -> Particular | J44: =IFERROR(__xludf.DUMMYFUNCTION("IF('Respuestas de formulario 1'!J44<>"""",UPPER(TRIM(TO_TEXT('Respuestas de formulario 1'!J44))),IF('Respuestas de formulario 1'!O44<>"""",UPPER(TRIM(TO_TEXT('Respuestas de formulario 1'!O44))),""""))"),"") | K44: =IFERROR(__xludf.DUMMYFUNCTION("IF('Respuestas de formulario 1'!K44="""","""",TO_TEXT('Respuestas de formulario 1'!K44))"),"") | L44: =IFERROR(__xludf.DUMMYFUNCTION("IF('Respuestas de formulario 1'!L44="""","""",TO_TEXT('Respuestas de formulario 1'!L44))"),"") | M44: =IFERROR(__xludf.DUMMYFUNCTION("IF('Respuestas de formulario 1'!M44="""","""",TO_TEXT('Respuestas de formulario 1'!M44))"),"") | N44: =IF(A44="","",IFERROR(YEAR(A44),"")) -> 2023 | O44: =IF(A44="","",IFERROR(TEXT(A44,"mmmm"),"")) -> enero | P44: Garino Dario
A45: ='Respuestas de formulario 1'!A45 -> 44953.489 | B45: ='Respuestas de formulario 1'!B45 -> layus | C45: ='Respuestas de formulario 1'!C45 -> Daniel | D45: ='Respuestas de formulario 1'!D45 -> dansocias77@gmail.com | E45: ='Respuestas de formulario 1'!E45 -> 28046 | F45: ='Respuestas de formulario 1'!F45 -> 26177948 | G45: =IFERROR(__xludf.DUMMYFUNCTION("IF('Respuestas de formulario 1'!G45="""","""",IF(LEFT(REGEXREPLACE(TO_TEXT('Respuestas de formulario 1'!G45),""[^0-9]"",""""),2)=""54"",""+""&REGEXREPLACE(TO_TEXT('Respuestas de formulario 1'!G45),""[^0-9]"",""""),""+54""&REGEXREPLACE(TO_TEXT('Respuestas "&"de formulario 1'!G45),""[^0-9]"","""")))"),"+543515471689") -> +543515471689 | H45: ='Respuestas de formulario 1'!S45 -> 2023 | I45: =IFERROR(__xludf.DUMMYFUNCTION("IF('Respuestas de formulario 1'!I45="""","""",TO_TEXT('Respuestas de formulario 1'!I45))"),"Obra social") -> Obra social | J45: =IFERROR(__xludf.DUMMYFUNCTION("IF('Respuestas de formulario 1'!J45<>"""",UPPER(TRIM(TO_TEXT('Respuestas de formulario 1'!J45))),IF('Respuestas de formulario 1'!O45<>"""",UPPER(TRIM(TO_TEXT('Respuestas de formulario 1'!O45))),""""))"),"PREVENCIÓN") -> PREVENCIÓN | K45: =IFERROR(__xludf.DUMMYFUNCTION("IF('Respuestas de formulario 1'!K45="""","""",TO_TEXT('Respuestas de formulario 1'!K45))"),"") | L45: =IFERROR(__xludf.DUMMYFUNCTION("IF('Respuestas de formulario 1'!L45="""","""",TO_TEXT('Respuestas de formulario 1'!L45))"),"") | M45: =IFERROR(__xludf.DUMMYFUNCTION("IF('Respuestas de formulario 1'!M45="""","""",TO_TEXT('Respuestas de formulario 1'!M45))"),"") | N45: =IF(A45="","",IFERROR(YEAR(A45),"")) -> 2023 | O45: =IF(A45="","",IFERROR(TEXT(A45,"mmmm"),"")) -> enero | P45: layus Daniel
A46: ='Respuestas de formulario 1'!A46 -> 44953.495 | B46: ='Respuestas de formulario 1'!B46 -> Retter | C46: ='Respuestas de formulario 1'!C46 -> Norma | D46: ='Respuestas de formulario 1'!D46 -> normaretter@hotmail.com | E46: ='Respuestas de formulario 1'!E46 -> 18169 | F46: ='Respuestas de formulario 1'!F46 -> 6132407 | G46: =IFERROR(__xludf.DUMMYFUNCTION("IF('Respuestas de formulario 1'!G46="""","""",IF(LEFT(REGEXREPLACE(TO_TEXT('Respuestas de formulario 1'!G46),""[^0-9]"",""""),2)=""54"",""+""&REGEXREPLACE(TO_TEXT('Respuestas de formulario 1'!G46),""[^0-9]"",""""),""+54""&REGEXREPLACE(TO_TEXT('Respuestas "&"de formulario 1'!G46),""[^0-9]"","""")))"),"+543513241502") -> +543513241502 | H46: ='Respuestas de formulario 1'!S46 -> 2023 | I46: =IFERROR(__xludf.DUMMYFUNCTION("IF('Respuestas de formulario 1'!I46="""","""",TO_TEXT('Respuestas de formulario 1'!I46))"),"Obra social") -> Obra social | J46: =IFERROR(__xludf.DUMMYFUNCTION("IF('Respuestas de formulario 1'!J46<>"""",UPPER(TRIM(TO_TEXT('Respuestas de formulario 1'!J46))),IF('Respuestas de formulario 1'!O46<>"""",UPPER(TRIM(TO_TEXT('Respuestas de formulario 1'!O46))),""""))"),"DASPU") -> DASPU | K46: =IFERROR(__xludf.DUMMYFUNCTION("IF('Respuestas de formulario 1'!K46="""","""",TO_TEXT('Respuestas de formulario 1'!K46))"),"") | L46: =IFERROR(__xludf.DUMMYFUNCTION("IF('Respuestas de formulario 1'!L46="""","""",TO_TEXT('Respuestas de formulario 1'!L46))"),"") | M46: =IFERROR(__xludf.DUMMYFUNCTION("IF('Respuestas de formulario 1'!M46="""","""",TO_TEXT('Respuestas de formulario 1'!M46))"),"") | N46: =IF(A46="","",IFERROR(YEAR(A46),"")) -> 2023 | O46: =IF(A46="","",IFERROR(TEXT(A46,"mmmm"),"")) -> enero | P46: Retter Norma
A47: ='Respuestas de formulario 1'!A47 -> 44953.502 | B47: ='Respuestas de formulario 1'!B47 -> Bracco | C47: ='Respuestas de formulario 1'!C47 -> Munir | D47: ='Respuestas de formulario 1'!D47 -> munirbracco@hotmail.com | E47: ='Respuestas de formulario 1'!E47 -> 27251 | F47: ='Respuestas de formulario 1'!F47 -> 24088161 | G47: =IFERROR(__xludf.DUMMYFUNCTION("IF('Respuestas de formulario 1'!G47="""","""",IF(LEFT(REGEXREPLACE(TO_TEXT('Respuestas de formulario 1'!G47),""[^0-9]"",""""),2)=""54"",""+""&REGEXREPLACE(TO_TEXT('Respuestas de formulario 1'!G47),""[^0-9]"",""""),""+54""&REGEXREPLACE(TO_TEXT('Respuestas "&"de formulario 1'!G47),""[^0-9]"","""")))"),"+543515185921") -> +543515185921 | H47: ='Respuestas de formulario 1'!S47 -> 2023 | I47: =IFERROR(__xludf.DUMMYFUNCTION("IF('Respuestas de formulario 1'!I47="""","""",TO_TEXT('Respuestas de formulario 1'!I47))"),"Obra social") -> Obra social | J47: =IFERROR(__xludf.DUMMYFUNCTION("IF('Respuestas de formulario 1'!J47<>"""",UPPER(TRIM(TO_TEXT('Respuestas de formulario 1'!J47))),IF('Respuestas de formulario 1'!O47<>"""",UPPER(TRIM(TO_TEXT('Respuestas de formulario 1'!O47))),""""))"),"AE SAN PEDRO") -> AE SAN PEDRO | K47: =IFERROR(__xludf.DUMMYFUNCTION("IF('Respuestas de formulario 1'!K47="""","""",TO_TEXT('Respuestas de formulario 1'!K47))"),"") | L47: =IFERROR(__xludf.DUMMYFUNCTION("IF('Respuestas de formulario 1'!L47="""","""",TO_TEXT('Respuestas de formulario 1'!L47))"),"") | M47: =IFERROR(__xludf.DUMMYFUNCTION("IF('Respuestas de formulario 1'!M47="""","""",TO_TEXT('Respuestas de formulario 1'!M47))"),"") | N47: =IF(A47="","",IFERROR(YEAR(A47),"")) -> 2023 | O47: =IF(A47="","",IFERROR(TEXT(A47,"mmmm"),"")) -> enero | P47: Bracco Munir
A48: ='Respuestas de formulario 1'!A48 -> 44953.742 | B48: ='Respuestas de formulario 1'!B48 -> Rodriguez | C48: ='Respuestas de formulario 1'!C48 -> Reinaldo | D48: ='Respuestas de formulario 1'!D48 -> Estelahilbe5@hotmail.com | E48: ='Respuestas de formulario 1'!E48 -> 18352 | F48: ='Respuestas de formulario 1'!F48 -> 7868456 | G48: =IFERROR(__xludf.DUMMYFUNCTION("IF('Respuestas de formulario 1'!G48="""","""",IF(LEFT(REGEXREPLACE(TO_TEXT('Respuestas de formulario 1'!G48),""[^0-9]"",""""),2)=""54"",""+""&REGEXREPLACE(TO_TEXT('Respuestas de formulario 1'!G48),""[^0-9]"",""""),""+54""&REGEXREPLACE(TO_TEXT('Respuestas "&"de formulario 1'!G48),""[^0-9]"","""")))"),"+543491464298") -> +543491464298 | H48: ='Respuestas de formulario 1'!S48 -> 2023 | I48: =IFERROR(__xludf.DUMMYFUNCTION("IF('Respuestas de formulario 1'!I48="""","""",TO_TEXT('Respuestas de formulario 1'!I48))"),"Obra social") -> Obra social | J48: =IFERROR(__xludf.DUMMYFUNCTION("IF('Respuestas de formulario 1'!J48<>"""",UPPER(TRIM(TO_TEXT('Respuestas de formulario 1'!J48))),IF('Respuestas de formulario 1'!O48<>"""",UPPER(TRIM(TO_TEXT('Respuestas de formulario 1'!O48))),""""))"),"JERARQUICOS SALUD") -> JERARQUICOS SALUD | K48: =IFERROR(__xludf.DUMMYFUNCTION("IF('Respuestas de formulario 1'!K48="""","""",TO_TEXT('Respuestas de formulario 1'!K48))"),"") | L48: =IFERROR(__xludf.DUMMYFUNCTION("IF('Respuestas de formulario 1'!L48="""","""",TO_TEXT('Respuestas de formulario 1'!L48))"),"") | M48: =IFERROR(__xludf.DUMMYFUNCTION("IF('Respuestas de formulario 1'!M48="""","""",TO_TEXT('Respuestas de formulario 1'!M48))"),"") | N48: =IF(A48="","",IFERROR(YEAR(A48),"")) -> 2023 | O48: =IF(A48="","",IFERROR(TEXT(A48,"mmmm"),"")) -> enero | P48: Rodriguez Reinaldo
A49: ='Respuestas de formulario 1'!A49 -> 44956.413 | B49: ='Respuestas de formulario 1'!B49 -> Vega Machado | C49: ='Respuestas de formulario 1'!C49 -> Alejandro | D49: ='Respuestas de formulario 1'!D49 -> alejandro.vega79@gmail.com | E49: ='Respuestas de formulario 1'!E49 -> 28911 | F49: ='Respuestas de formulario 1'!F49 -> 27172103 | G49: =IFERROR(__xludf.DUMMYFUNCTION("IF('Respuestas de formulario 1'!G49="""","""",IF(LEFT(REGEXREPLACE(TO_TEXT('Respuestas de formulario 1'!G49),""[^0-9]"",""""),2)=""54"",""+""&REGEXREPLACE(TO_TEXT('Respuestas de formulario 1'!G49),""[^0-9]"",""""),""+54""&REGEXREPLACE(TO_TEXT('Respuestas "&"de formulario 1'!G49),""[^0-9]"","""")))"),"+543515583969") -> +543515583969 | H49: ='Respuestas de formulario 1'!S49 -> 2023 | I49: =IFERROR(__xludf.DUMMYFUNCTION("IF('Respuestas de formulario 1'!I49="""","""",TO_TEXT('Respuestas de formulario 1'!I49))"),"Particular") -> Particular | J49: =IFERROR(__xludf.DUMMYFUNCTION("IF('Respuestas de formulario 1'!J49<>"""",UPPER(TRIM(TO_TEXT('Respuestas de formulario 1'!J49))),IF('Respuestas de formulario 1'!O49<>"""",UPPER(TRIM(TO_TEXT('Respuestas de formulario 1'!O49))),""""))"),"") | K49: =IFERROR(__xludf.DUMMYFUNCTION("IF('Respuestas de formulario 1'!K49="""","""",TO_TEXT('Respuestas de formulario 1'!K49))"),"") | L49: =IFERROR(__xludf.DUMMYFUNCTION("IF('Respuestas de formulario 1'!L49="""","""",TO_TEXT('Respuestas de formulario 1'!L49))"),"") | M49: =IFERROR(__xludf.DUMMYFUNCTION("IF('Respuestas de formulario 1'!M49="""","""",TO_TEXT('Respuestas de formulario 1'!M49))"),"") | N49: =IF(A49="","",IFERROR(YEAR(A49),"")) -> 2023 | O49: =IF(A49="","",IFERROR(TEXT(A49,"mmmm"),"")) -> enero | P49: Vega Machado Alejandro
A50: ='Respuestas de formulario 1'!A50 -> 44957.464 | B50: ='Respuestas de formulario 1'!B50 -> Vega | C50: ='Respuestas de formulario 1'!C50 -> Maria belen | D50: ='Respuestas de formulario 1'!D50 | E50: ='Respuestas de formulario 1'!E50 -> 44957 | F50: ='Respuestas de formulario 1'!F50 -> 31523085 | G50: =IFERROR(__xludf.DUMMYFUNCTION("IF('Respuestas de formulario 1'!G50="""","""",IF(LEFT(REGEXREPLACE(TO_TEXT('Respuestas de formulario 1'!G50),""[^0-9]"",""""),2)=""54"",""+""&REGEXREPLACE(TO_TEXT('Respuestas de formulario 1'!G50),""[^0-9]"",""""),""+54""&REGEXREPLACE(TO_TEXT('Respuestas "&"de formulario 1'!G50),""[^0-9]"","""")))"),"+543513798148") -> +543513798148 | H50: ='Respuestas de formulario 1'!S50 -> 2023 | I50: =IFERROR(__xludf.DUMMYFUNCTION("IF('Respuestas de formulario 1'!I50="""","""",TO_TEXT('Respuestas de formulario 1'!I50))"),"Obra social") -> Obra social | J50: =IFERROR(__xludf.DUMMYFUNCTION("IF('Respuestas de formulario 1'!J50<>"""",UPPER(TRIM(TO_TEXT('Respuestas de formulario 1'!J50))),IF('Respuestas de formulario 1'!O50<>"""",UPPER(TRIM(TO_TEXT('Respuestas de formulario 1'!O50))),""""))"),"APROSS") -> APROSS | K50: =IFERROR(__xludf.DUMMYFUNCTION("IF('Respuestas de formulario 1'!K50="""","""",TO_TEXT('Respuestas de formulario 1'!K50))"),"") | L50: =IFERROR(__xludf.DUMMYFUNCTION("IF('Respuestas de formulario 1'!L50="""","""",TO_TEXT('Respuestas de formulario 1'!L50))"),"") | M50: =IFERROR(__xludf.DUMMYFUNCTION("IF('Respuestas de formulario 1'!M50="""","""",TO_TEXT('Respuestas de formulario 1'!M50))"),"") | N50: =IF(A50="","",IFERROR(YEAR(A50),"")) -> 2023 | O50: =IF(A50="","",IFERROR(TEXT(A50,"mmmm"),"")) -> enero | P50: Vega Maria belen
A51: ='Respuestas de formulario 1'!A51 -> 44957.682 | B51: ='Respuestas de formulario 1'!B51 -> Micheloud | C51: ='Respuestas de formulario 1'!C51 -> Santiago | D51: ='Respuestas de formulario 1'!D51 -> caroponce_@hotmail.com | E51: ='Respuestas de formulario 1'!E51 -> 40598 | F51: ='Respuestas de formulario 1'!F51 -> 50631375 | G51: =IFERROR(__xludf.DUMMYFUNCTION("IF('Respuestas de formulario 1'!G51="""","""",IF(LEFT(REGEXREPLACE(TO_TEXT('Respuestas de formulario 1'!G51),""[^0-9]"",""""),2)=""54"",""+""&REGEXREPLACE(TO_TEXT('Respuestas de formulario 1'!G51),""[^0-9]"",""""),""+54""&REGEXREPLACE(TO_TEXT('Respuestas "&"de formulario 1'!G51),""[^0-9]"","""")))"),"+543513287710") -> +543513287710 | H51: ='Respuestas de formulario 1'!S51 -> 2023 | I51: =IFERROR(__xludf.DUMMYFUNCTION("IF('Respuestas de formulario 1'!I51="""","""",TO_TEXT('Respuestas de formulario 1'!I51))"),"Particular") -> Particular | J51: =IFERROR(__xludf.DUMMYFUNCTION("IF('Respuestas de formulario 1'!J51<>"""",UPPER(TRIM(TO_TEXT('Respuestas de formulario 1'!J51))),IF('Respuestas de formulario 1'!O51<>"""",UPPER(TRIM(TO_TEXT('Respuestas de formulario 1'!O51))),""""))"),"") | K51: =IFERROR(__xludf.DUMMYFUNCTION("IF('Respuestas de formulario 1'!K51="""","""",TO_TEXT('Respuestas de formulario 1'!K51))"),"") | L51: =IFERROR(__xludf.DUMMYFUNCTION("IF('Respuestas de formulario 1'!L51="""","""",TO_TEXT('Respuestas de formulario 1'!L51))"),"") | M51: =IFERROR(__xludf.DUMMYFUNCTION("IF('Respuestas de formulario 1'!M51="""","""",TO_TEXT('Respuestas de formulario 1'!M51))"),"") | N51: =IF(A51="","",IFERROR(YEAR(A51),"")) -> 2023 | O51: =IF(A51="","",IFERROR(TEXT(A51,"mmmm"),"")) -> enero | P51: Micheloud Santiago
A52: ='Respuestas de formulario 1'!A52 -> 44957.746 | B52: ='Respuestas de formulario 1'!B52 -> Palacios | C52: ='Respuestas de formulario 1'!C52 -> Santiago | D52: ='Respuestas de formulario 1'!D52 -> santipalacios17@hotmail.com | E52: ='Respuestas de formulario 1'!E52 -> 36599 | F52: ='Respuestas de formulario 1'!F52 -> 42697056 | G52: =IFERROR(__xludf.DUMMYFUNCTION("IF('Respuestas de formulario 1'!G52="""","""",IF(LEFT(REGEXREPLACE(TO_TEXT('Respuestas de formulario 1'!G52),""[^0-9]"",""""),2)=""54"",""+""&REGEXREPLACE(TO_TEXT('Respuestas de formulario 1'!G52),""[^0-9]"",""""),""+54""&REGEXREPLACE(TO_TEXT('Respuestas "&"de formulario 1'!G52),""[^0-9]"","""")))"),"+543516160854") -> +543516160854 | H52: ='Respuestas de formulario 1'!S52 -> 2023 | I52: =IFERROR(__xludf.DUMMYFUNCTION("IF('Respuestas de formulario 1'!I52="""","""",TO_TEXT('Respuestas de formulario 1'!I52))"),"Particular") -> Particular | J52: =IFERROR(__xludf.DUMMYFUNCTION("IF('Respuestas de formulario 1'!J52<>"""",UPPER(TRIM(TO_TEXT('Respuestas de formulario 1'!J52))),IF('Respuestas de formulario 1'!O52<>"""",UPPER(TRIM(TO_TEXT('Respuestas de formulario 1'!O52))),""""))"),"") | K52: =IFERROR(__xludf.DUMMYFUNCTION("IF('Respuestas de formulario 1'!K52="""","""",TO_TEXT('Respuestas de formulario 1'!K52))"),"") | L52: =IFERROR(__xludf.DUMMYFUNCTION("IF('Respuestas de formulario 1'!L52="""","""",TO_TEXT('Respuestas de formulario 1'!L52))"),"") | M52: =IFERROR(__xludf.DUMMYFUNCTION("IF('Respuestas de formulario 1'!M52="""","""",TO_TEXT('Respuestas de formulario 1'!M52))"),"") | N52: =IF(A52="","",IFERROR(YEAR(A52),"")) -> 2023 | O52: =IF(A52="","",IFERROR(TEXT(A52,"mmmm"),"")) -> enero | P52: Palacios Santiago
A53: ='Respuestas de formulario 1'!A53 -> 44959.758 | B53: ='Respuestas de formulario 1'!B53 -> Viberti | C53: ='Respuestas de formulario 1'!C53 -> Carlos | D53: ='Respuestas de formulario 1'!D53 | E53: ='Respuestas de formulario 1'!E53 -> 14333 | F53: ='Respuestas de formulario 1'!F53 -> 6385089 | G53: =IFERROR(__xludf.DUMMYFUNCTION("IF('Respuestas de formulario 1'!G53="""","""",IF(LEFT(REGEXREPLACE(TO_TEXT('Respuestas de formulario 1'!G53),""[^0-9]"",""""),2)=""54"",""+""&REGEXREPLACE(TO_TEXT('Respuestas de formulario 1'!G53),""[^0-9]"",""""),""+54""&REGEXREPLACE(TO_TEXT('Respuestas "&"de formulario 1'!G53),""[^0-9]"","""")))"),"+543515385789") -> +543515385789 | H53: ='Respuestas de formulario 1'!S53 -> 2023 | I53: =IFERROR(__xludf.DUMMYFUNCTION("IF('Respuestas de formulario 1'!I53="""","""",TO_TEXT('Respuestas de formulario 1'!I53))"),"Obra social") -> Obra social | J53: =IFERROR(__xludf.DUMMYFUNCTION("IF('Respuestas de formulario 1'!J53<>"""",UPPER(TRIM(TO_TEXT('Respuestas de formulario 1'!J53))),IF('Respuestas de formulario 1'!O53<>"""",UPPER(TRIM(TO_TEXT('Respuestas de formulario 1'!O53))),""""))"),"APROSS") -> APROSS | K53: =IFERROR(__xludf.DUMMYFUNCTION("IF('Respuestas de formulario 1'!K53="""","""",TO_TEXT('Respuestas de formulario 1'!K53))"),"") | L53: =IFERROR(__xludf.DUMMYFUNCTION("IF('Respuestas de formulario 1'!L53="""","""",TO_TEXT('Respuestas de formulario 1'!L53))"),"") | M53: =IFERROR(__xludf.DUMMYFUNCTION("IF('Respuestas de formulario 1'!M53="""","""",TO_TEXT('Respuestas de formulario 1'!M53))"),"") | N53: =IF(A53="","",IFERROR(YEAR(A53),"")) -> 2023 | O53: =IF(A53="","",IFERROR(TEXT(A53,"mmmm"),"")) -> febrero | P53: Viberti Carlos
A54: ='Respuestas de formulario 1'!A54 -> 44959.82 | B54: ='Respuestas de formulario 1'!B54 -> Arrieta | C54: ='Respuestas de formulario 1'!C54 -> Claudio Carlos | D54: ='Respuestas de formulario 1'!D54 -> ccarrieta@gmail.com | E54: ='Respuestas de formulario 1'!E54 -> 27145 | F54: ='Respuestas de formulario 1'!F54 -> 23824551 | G54: =IFERROR(__xludf.DUMMYFUNCTION("IF('Respuestas de formulario 1'!G54="""","""",IF(LEFT(REGEXREPLACE(TO_TEXT('Respuestas de formulario 1'!G54),""[^0-9]"",""""),2)=""54"",""+""&REGEXREPLACE(TO_TEXT('Respuestas de formulario 1'!G54),""[^0-9]"",""""),""+54""&REGEXREPLACE(TO_TEXT('Respuestas "&"de formulario 1'!G54),""[^0-9]"","""")))"),"+543516137697") -> +543516137697 | H54: ='Respuestas de formulario 1'!S54 -> 2023 | I54: =IFERROR(__xludf.DUMMYFUNCTION("IF('Respuestas de formulario 1'!I54="""","""",TO_TEXT('Respuestas de formulario 1'!I54))"),"Obra social") -> Obra social | J54: =IFERROR(__xludf.DUMMYFUNCTION("IF('Respuestas de formulario 1'!J54<>"""",UPPER(TRIM(TO_TEXT('Respuestas de formulario 1'!J54))),IF('Respuestas de formulario 1'!O54<>"""",UPPER(TRIM(TO_TEXT('Respuestas de formulario 1'!O54))),""""))"),"APROSS") -> APROSS | K54: =IFERROR(__xludf.DUMMYFUNCTION("IF('Respuestas de formulario 1'!K54="""","""",TO_TEXT('Respuestas de formulario 1'!K54))"),"") | L54: =IFERROR(__xludf.DUMMYFUNCTION("IF('Respuestas de formulario 1'!L54="""","""",TO_TEXT('Respuestas de formulario 1'!L54))"),"") | M54: =IFERROR(__xludf.DUMMYFUNCTION("IF('Respuestas de formulario 1'!M54="""","""",TO_TEXT('Respuestas de formulario 1'!M54))"),"") | N54: =IF(A54="","",IFERROR(YEAR(A54),"")) -> 2023 | O54: =IF(A54="","",IFERROR(TEXT(A54,"mmmm"),"")) -> febrero | P54: Arrieta Claudio Carlos
A55: ='Respuestas de formulario 1'!A55 -> 44959.883 | B55: ='Respuestas de formulario 1'!B55 -> Martinez | C55: ='Respuestas de formulario 1'!C55 -> Sergio dario | D55: ='Respuestas de formulario 1'!D55 -> Sergiooomartinezz.@gmail. | E55: ='Respuestas de formulario 1'!E55 -> 23655 | F55: ='Respuestas de formulario 1'!F55 -> 17154620 | G55: =IFERROR(__xludf.DUMMYFUNCTION("IF('Respuestas de formulario 1'!G55="""","""",IF(LEFT(REGEXREPLACE(TO_TEXT('Respuestas de formulario 1'!G55),""[^0-9]"",""""),2)=""54"",""+""&REGEXREPLACE(TO_TEXT('Respuestas de formulario 1'!G55),""[^0-9]"",""""),""+54""&REGEXREPLACE(TO_TEXT('Respuestas "&"de formulario 1'!G55),""[^0-9]"","""")))"),"+543513516889") -> +543513516889 | H55: ='Respuestas de formulario 1'!S55 -> 2023 | I55: =IFERROR(__xludf.DUMMYFUNCTION("IF('Respuestas de formulario 1'!I55="""","""",TO_TEXT('Respuestas de formulario 1'!I55))"),"Particular") -> Particular | J55: =IFERROR(__xludf.DUMMYFUNCTION("IF('Respuestas de formulario 1'!J55<>"""",UPPER(TRIM(TO_TEXT('Respuestas de formulario 1'!J55))),IF('Respuestas de formulario 1'!O55<>"""",UPPER(TRIM(TO_TEXT('Respuestas de formulario 1'!O55))),""""))"),"") | K55: =IFERROR(__xludf.DUMMYFUNCTION("IF('Respuestas de formulario 1'!K55="""","""",TO_TEXT('Respuestas de formulario 1'!K55))"),"") | L55: =IFERROR(__xludf.DUMMYFUNCTION("IF('Respuestas de formulario 1'!L55="""","""",TO_TEXT('Respuestas de formulario 1'!L55))"),"") | M55: =IFERROR(__xludf.DUMMYFUNCTION("IF('Respuestas de formulario 1'!M55="""","""",TO_TEXT('Respuestas de formulario 1'!M55))"),"") | N55: =IF(A55="","",IFERROR(YEAR(A55),"")) -> 2023 | O55: =IF(A55="","",IFERROR(TEXT(A55,"mmmm"),"")) -> febrero | P55: Martinez Sergio dario
A56: ='Respuestas de formulario 1'!A56 -> 44960.458 | B56: ='Respuestas de formulario 1'!B56 -> Ibarra | C56: ='Respuestas de formulario 1'!C56 -> Marta | D56: ='Respuestas de formulario 1'!D56 -> draibarrajaramillo@gmail.com | E56: ='Respuestas de formulario 1'!E56 -> 19122 | F56: ='Respuestas de formulario 1'!F56 -> 10377891 | G56: =IFERROR(__xludf.DUMMYFUNCTION("IF('Respuestas de formulario 1'!G56="""","""",IF(LEFT(REGEXREPLACE(TO_TEXT('Respuestas de formulario 1'!G56),""[^0-9]"",""""),2)=""54"",""+""&REGEXREPLACE(TO_TEXT('Respuestas de formulario 1'!G56),""[^0-9]"",""""),""+54""&REGEXREPLACE(TO_TEXT('Respuestas "&"de formulario 1'!G56),""[^0-9]"","""")))"),"+543516505375") -> +543516505375 | H56: ='Respuestas de formulario 1'!S56 -> 2023 | I56: =IFERROR(__xludf.DUMMYFUNCTION("IF('Respuestas de formulario 1'!I56="""","""",TO_TEXT('Respuestas de formulario 1'!I56))"),"Obra social") -> Obra social | J56: =IFERROR(__xludf.DUMMYFUNCTION("IF('Respuestas de formulario 1'!J56<>"""",UPPER(TRIM(TO_TEXT('Respuestas de formulario 1'!J56))),IF('Respuestas de formulario 1'!O56<>"""",UPPER(TRIM(TO_TEXT('Respuestas de formulario 1'!O56))),""""))"),"APROSS") -> APROSS | K56: =IFERROR(__xludf.DUMMYFUNCTION("IF('Respuestas de formulario 1'!K56="""","""",TO_TEXT('Respuestas de formulario 1'!K56))"),"") | L56: =IFERROR(__xludf.DUMMYFUNCTION("IF('Respuestas de formulario 1'!L56="""","""",TO_TEXT('Respuestas de formulario 1'!L56))"),"") | M56: =IFERROR(__xludf.DUMMYFUNCTION("IF('Respuestas de formulario 1'!M56="""","""",TO_TEXT('Respuestas de formulario 1'!M56))"),"") | N56: =IF(A56="","",IFERROR(YEAR(A56),"")) -> 2023 | O56: =IF(A56="","",IFERROR(TEXT(A56,"mmmm"),"")) -> febrero | P56: Ibarra Marta
A57: ='Respuestas de formulario 1'!A57 -> 44960.464 | B57: ='Respuestas de formulario 1'!B57 -> Avila | C57: ='Respuestas de formulario 1'!C57 -> Patricia | D57: ='Respuestas de formulario 1'!D57 -> avilapati@hotmail.com | E57: ='Respuestas de formulario 1'!E57 -> 21135 | F57: ='Respuestas de formulario 1'!F57 -> 13597824 | G57: =IFERROR(__xludf.DUMMYFUNCTION("IF('Respuestas de formulario 1'!G57="""","""",IF(LEFT(REGEXREPLACE(TO_TEXT('Respuestas de formulario 1'!G57),""[^0-9]"",""""),2)=""54"",""+""&REGEXREPLACE(TO_TEXT('Respuestas de formulario 1'!G57),""[^0-9]"",""""),""+54""&REGEXREPLACE(TO_TEXT('Respuestas "&"de formulario 1'!G57),""[^0-9]"","""")))"),"+543512774033") -> +543512774033 | H57: ='Respuestas de formulario 1'!S57 -> 2023 | I57: =IFERROR(__xludf.DUMMYFUNCTION("IF('Respuestas de formulario 1'!I57="""","""",TO_TEXT('Respuestas de formulario 1'!I57))"),"Obra social") -> Obra social | J57: =IFERROR(__xludf.DUMMYFUNCTION("IF('Respuestas de formulario 1'!J57<>"""",UPPER(TRIM(TO_TEXT('Respuestas de formulario 1'!J57))),IF('Respuestas de formulario 1'!O57<>"""",UPPER(TRIM(TO_TEXT('Respuestas de formulario 1'!O57))),""""))"),"APROSS") -> APROSS | K57: =IFERROR(__xludf.DUMMYFUNCTION("IF('Respuestas de formulario 1'!K57="""","""",TO_TEXT('Respuestas de formulario 1'!K57))"),"") | L57: =IFERROR(__xludf.DUMMYFUNCTION("IF('Respuestas de formulario 1'!L57="""","""",TO_TEXT('Respuestas de formulario 1'!L57))"),"") | M57: =IFERROR(__xludf.DUMMYFUNCTION("IF('Respuestas de formulario 1'!M57="""","""",TO_TEXT('Respuestas de formulario 1'!M57))"),"") | N57: =IF(A57="","",IFERROR(YEAR(A57),"")) -> 2023 | O57: =IF(A57="","",IFERROR(TEXT(A57,"mmmm"),"")) -> febrero | P57: Avila Patricia
A58: ='Respuestas de formulario 1'!A58 -> 44964.14 | B58: ='Respuestas de formulario 1'!B58 -> Teran | C58: ='Respuestas de formulario 1'!C58 -> Emanuel | D58: ='Respuestas de formulario 1'!D58 -> emanuelterande05@gmail.com | E58: ='Respuestas de formulario 1'!E58 -> 37330 | F58: ='Respuestas de formulario 1'!F58 -> 43812470 | G58: =IFERROR(__xludf.DUMMYFUNCTION("IF('Respuestas de formulario 1'!G58="""","""",IF(LEFT(REGEXREPLACE(TO_TEXT('Respuestas de formulario 1'!G58),""[^0-9]"",""""),2)=""54"",""+""&REGEXREPLACE(TO_TEXT('Respuestas de formulario 1'!G58),""[^0-9]"",""""),""+54""&REGEXREPLACE(TO_TEXT('Respuestas "&"de formulario 1'!G58),""[^0-9]"","""")))"),"+543518137350") -> +543518137350 | H58: ='Respuestas de formulario 1'!S58 -> 2023 | I58: =IFERROR(__xludf.DUMMYFUNCTION("IF('Respuestas de formulario 1'!I58="""","""",TO_TEXT('Respuestas de formulario 1'!I58))"),"Particular") -> Particular | J58: =IFERROR(__xludf.DUMMYFUNCTION("IF('Respuestas de formulario 1'!J58<>"""",UPPER(TRIM(TO_TEXT('Respuestas de formulario 1'!J58))),IF('Respuestas de formulario 1'!O58<>"""",UPPER(TRIM(TO_TEXT('Respuestas de formulario 1'!O58))),""""))"),"") | K58: =IFERROR(__xludf.DUMMYFUNCTION("IF('Respuestas de formulario 1'!K58="""","""",TO_TEXT('Respuestas de formulario 1'!K58))"),"") | L58: =IFERROR(__xludf.DUMMYFUNCTION("IF('Respuestas de formulario 1'!L58="""","""",TO_TEXT('Respuestas de formulario 1'!L58))"),"") | M58: =IFERROR(__xludf.DUMMYFUNCTION("IF('Respuestas de formulario 1'!M58="""","""",TO_TEXT('Respuestas de formulario 1'!M58))"),"") | N58: =IF(A58="","",IFERROR(YEAR(A58),"")) -> 2023 | O58: =IF(A58="","",IFERROR(TEXT(A58,"mmmm"),"")) -> febrero | P58: Teran Emanuel
A59: ='Respuestas de formulario 1'!A59 -> 44964.713 | B59: ='Respuestas de formulario 1'!B59 -> Abadie | C59: ='Respuestas de formulario 1'!C59 -> Raul | D59: ='Respuestas de formulario 1'!D59 -> raulgabadie@hotmail.com | E59: ='Respuestas de formulario 1'!E59 -> 27999 | F59: ='Respuestas de formulario 1'!F59 -> 25281585 | G59: =IFERROR(__xludf.DUMMYFUNCTION("IF('Respuestas de formulario 1'!G59="""","""",IF(LEFT(REGEXREPLACE(TO_TEXT('Respuestas de formulario 1'!G59),""[^0-9]"",""""),2)=""54"",""+""&REGEXREPLACE(TO_TEXT('Respuestas de formulario 1'!G59),""[^0-9]"",""""),""+54""&REGEXREPLACE(TO_TEXT('Respuestas "&"de formulario 1'!G59),""[^0-9]"","""")))"),"+543516655602") -> +543516655602 | H59: ='Respuestas de formulario 1'!S59 -> 2023 | I59: =IFERROR(__xludf.DUMMYFUNCTION("IF('Respuestas de formulario 1'!I59="""","""",TO_TEXT('Respuestas de formulario 1'!I59))"),"Particular") -> Particular | J59: =IFERROR(__xludf.DUMMYFUNCTION("IF('Respuestas de formulario 1'!J59<>"""",UPPER(TRIM(TO_TEXT('Respuestas de formulario 1'!J59))),IF('Respuestas de formulario 1'!O59<>"""",UPPER(TRIM(TO_TEXT('Respuestas de formulario 1'!O59))),""""))"),"") | K59: =IFERROR(__xludf.DUMMYFUNCTION("IF('Respuestas de formulario 1'!K59="""","""",TO_TEXT('Respuestas de formulario 1'!K59))"),"") | L59: =IFERROR(__xludf.DUMMYFUNCTION("IF('Respuestas de formulario 1'!L59="""","""",TO_TEXT('Respuestas de formulario 1'!L59))"),"") | M59: =IFERROR(__xludf.DUMMYFUNCTION("IF('Respuestas de formulario 1'!M59="""","""",TO_TEXT('Respuestas de formulario 1'!M59))"),"") | N59: =IF(A59="","",IFERROR(YEAR(A59),"")) -> 2023 | O59: =IF(A59="","",IFERROR(TEXT(A59,"mmmm"),"")) -> febrero | P59: Abadie Raul
A60: ='Respuestas de formulario 1'!A60 -> 44964.886 | B60: ='Respuestas de formulario 1'!B60 -> Ceballos | C60: ='Respuestas de formulario 1'!C60 -> José | D60: ='Respuestas de formulario 1'!D60 -> Jose.maria.ceballos94@gmail.com | E60: ='Respuestas de formulario 1'!E60 -> 34699 | F60: ='Respuestas de formulario 1'!F60 -> 38645431 | G60: =IFERROR(__xludf.DUMMYFUNCTION("IF('Respuestas de formulario 1'!G60="""","""",IF(LEFT(REGEXREPLACE(TO_TEXT('Respuestas de formulario 1'!G60),""[^0-9]"",""""),2)=""54"",""+""&REGEXREPLACE(TO_TEXT('Respuestas de formulario 1'!G60),""[^0-9]"",""""),""+54""&REGEXREPLACE(TO_TEXT('Respuestas "&"de formulario 1'!G60),""[^0-9]"","""")))"),"+543517590683") -> +543517590683 | H60: ='Respuestas de formulario 1'!S60 -> 2023 | I60: =IFERROR(__xludf.DUMMYFUNCTION("IF('Respuestas de formulario 1'!I60="""","""",TO_TEXT('Respuestas de formulario 1'!I60))"),"Obra social") -> Obra social | J60: =IFERROR(__xludf.DUMMYFUNCTION("IF('Respuestas de formulario 1'!J60<>"""",UPPER(TRIM(TO_TEXT('Respuestas de formulario 1'!J60))),IF('Respuestas de formulario 1'!O60<>"""",UPPER(TRIM(TO_TEXT('Respuestas de formulario 1'!O60))),""""))"),"PREVENCIÓN") -> PREVENCIÓN | K60: =IFERROR(__xludf.DUMMYFUNCTION("IF('Respuestas de formulario 1'!K60="""","""",TO_TEXT('Respuestas de formulario 1'!K60))"),"") | L60: =IFERROR(__xludf.DUMMYFUNCTION("IF('Respuestas de formulario 1'!L60="""","""",TO_TEXT('Respuestas de formulario 1'!L60))"),"") | M60: =IFERROR(__xludf.DUMMYFUNCTION("IF('Respuestas de formulario 1'!M60="""","""",TO_TEXT('Respuestas de formulario 1'!M60))"),"") | N60: =IF(A60="","",IFERROR(YEAR(A60),"")) -> 2023 | O60: =IF(A60="","",IFERROR(TEXT(A60,"mmmm"),"")) -> febrero | P60: Ceballos José
A61: ='Respuestas de formulario 1'!A61 -> 44967.533 | B61: ='Respuestas de formulario 1'!B61 -> Raffin | C61: ='Respuestas de formulario 1'!C61 -> Vilma Rosa | D61: ='Respuestas de formulario 1'!D61 -> vraffin002@gmail.com | E61: ='Respuestas de formulario 1'!E61 -> 25111 | F61: ='Respuestas de formulario 1'!F61 -> 20454528 | G61: =IFERROR(__xludf.DUMMYFUNCTION("IF('Respuestas de formulario 1'!G61="""","""",IF(LEFT(REGEXREPLACE(TO_TEXT('Respuestas de formulario 1'!G61),""[^0-9]"",""""),2)=""54"",""+""&REGEXREPLACE(TO_TEXT('Respuestas de formulario 1'!G61),""[^0-9]"",""""),""+54""&REGEXREPLACE(TO_TEXT('Respuestas "&"de formulario 1'!G61),""[^0-9]"","""")))"),"+543515389887") -> +543515389887 | H61: ='Respuestas de formulario 1'!S61 -> 2023 | I61: =IFERROR(__xludf.DUMMYFUNCTION("IF('Respuestas de formulario 1'!I61="""","""",TO_TEXT('Respuestas de formulario 1'!I61))"),"Particular") -> Particular | J61: =IFERROR(__xludf.DUMMYFUNCTION("IF('Respuestas de formulario 1'!J61<>"""",UPPER(TRIM(TO_TEXT('Respuestas de formulario 1'!J61))),IF('Respuestas de formulario 1'!O61<>"""",UPPER(TRIM(TO_TEXT('Respuestas de formulario 1'!O61))),""""))"),"") | K61: =IFERROR(__xludf.DUMMYFUNCTION("IF('Respuestas de formulario 1'!K61="""","""",TO_TEXT('Respuestas de formulario 1'!K61))"),"") | L61: =IFERROR(__xludf.DUMMYFUNCTION("IF('Respuestas de formulario 1'!L61="""","""",TO_TEXT('Respuestas de formulario 1'!L61))"),"") | M61: =IFERROR(__xludf.DUMMYFUNCTION("IF('Respuestas de formulario 1'!M61="""","""",TO_TEXT('Respuestas de formulario 1'!M61))"),"") | N61: =IF(A61="","",IFERROR(YEAR(A61),"")) -> 2023 | O61: =IF(A61="","",IFERROR(TEXT(A61,"mmmm"),"")) -> febrero | P61: Raffin Vilma Rosa
A62: ='Respuestas de formulario 1'!A62 -> 44970.443 | B62: ='Respuestas de formulario 1'!B62 -> ICIKSON | C62: ='Respuestas de formulario 1'!C62 -> Tomas | D62: ='Respuestas de formulario 1'!D62 -> tomasicikson@gmail.com | E62: ='Respuestas de formulario 1'!E62 -> 35040 | F62: ='Respuestas de formulario 1'!F62 -> 40520046 | G62: =IFERROR(__xludf.DUMMYFUNCTION("IF('Respuestas de formulario 1'!G62="""","""",IF(LEFT(REGEXREPLACE(TO_TEXT('Respuestas de formulario 1'!G62),""[^0-9]"",""""),2)=""54"",""+""&REGEXREPLACE(TO_TEXT('Respuestas de formulario 1'!G62),""[^0-9]"",""""),""+54""&REGEXREPLACE(TO_TEXT('Respuestas "&"de formulario 1'!G62),""[^0-9]"","""")))"),"+543516113790") -> +543516113790 | H62: ='Respuestas de formulario 1'!S62 -> 2023 | I62: =IFERROR(__xludf.DUMMYFUNCTION("IF('Respuestas de formulario 1'!I62="""","""",TO_TEXT('Respuestas de formulario 1'!I62))"),"Particular") -> Particular | J62: =IFERROR(__xludf.DUMMYFUNCTION("IF('Respuestas de formulario 1'!J62<>"""",UPPER(TRIM(TO_TEXT('Respuestas de formulario 1'!J62))),IF('Respuestas de formulario 1'!O62<>"""",UPPER(TRIM(TO_TEXT('Respuestas de formulario 1'!O62))),""""))"),"") | K62: =IFERROR(__xludf.DUMMYFUNCTION("IF('Respuestas de formulario 1'!K62="""","""",TO_TEXT('Respuestas de formulario 1'!K62))"),"") | L62: =IFERROR(__xludf.DUMMYFUNCTION("IF('Respuestas de formulario 1'!L62="""","""",TO_TEXT('Respuestas de formulario 1'!L62))"),"") | M62: =IFERROR(__xludf.DUMMYFUNCTION("IF('Respuestas de formulario 1'!M62="""","""",TO_TEXT('Respuestas de formulario 1'!M62))"),"") | N62: =IF(A62="","",IFERROR(YEAR(A62),"")) -> 2023 | O62: =IF(A62="","",IFERROR(TEXT(A62,"mmmm"),"")) -> febrero | P62: ICIKSON Tomas
A63: ='Respuestas de formulario 1'!A63 -> 44970.649 | B63: ='Respuestas de formulario 1'!B63 -> Rios giache | C63: ='Respuestas de formulario 1'!C63 -> Luciano lucas | D63: ='Respuestas de formulario 1'!D63 -> Lucianolucasrg98@gmail.com | E63: ='Respuestas de formulario 1'!E63 -> 35949 | F63: ='Respuestas de formulario 1'!F63 -> 41279824 | G63: =IFERROR(__xludf.DUMMYFUNCTION("IF('Respuestas de formulario 1'!G63="""","""",IF(LEFT(REGEXREPLACE(TO_TEXT('Respuestas de formulario 1'!G63),""[^0-9]"",""""),2)=""54"",""+""&REGEXREPLACE(TO_TEXT('Respuestas de formulario 1'!G63),""[^0-9]"",""""),""+54""&REGEXREPLACE(TO_TEXT('Respuestas "&"de formulario 1'!G63),""[^0-9]"","""")))"),"+543512893805") -> +543512893805 | H63: ='Respuestas de formulario 1'!S63 -> 2023 | I63: =IFERROR(__xludf.DUMMYFUNCTION("IF('Respuestas de formulario 1'!I63="""","""",TO_TEXT('Respuestas de formulario 1'!I63))"),"Particular") -> Particular | J63: =IFERROR(__xludf.DUMMYFUNCTION("IF('Respuestas de formulario 1'!J63<>"""",UPPER(TRIM(TO_TEXT('Respuestas de formulario 1'!J63))),IF('Respuestas de formulario 1'!O63<>"""",UPPER(TRIM(TO_TEXT('Respuestas de formulario 1'!O63))),""""))"),"") | K63: =IFERROR(__xludf.DUMMYFUNCTION("IF('Respuestas de formulario 1'!K63="""","""",TO_TEXT('Respuestas de formulario 1'!K63))"),"") | L63: =IFERROR(__xludf.DUMMYFUNCTION("IF('Respuestas de formulario 1'!L63="""","""",TO_TEXT('Respuestas de formulario 1'!L63))"),"") | M63: =IFERROR(__xludf.DUMMYFUNCTION("IF('Respuestas de formulario 1'!M63="""","""",TO_TEXT('Respuestas de formulario 1'!M63))"),"") | N63: =IF(A63="","",IFERROR(YEAR(A63),"")) -> 2023 | O63: =IF(A63="","",IFERROR(TEXT(A63,"mmmm"),"")) -> febrero | P63: Rios giache Luciano lucas
A64: ='Respuestas de formulario 1'!A64 -> 44970.799 | B64: ='Respuestas de formulario 1'!B64 -> Ruiz | C64: ='Respuestas de formulario 1'!C64 -> Luis | D64: ='Respuestas de formulario 1'!D64 -> Lruizgalizi@gmail.com | E64: ='Respuestas de formulario 1'!E64 -> 33653 | F64: ='Respuestas de formulario 1'!F64 -> 36147980 | G64: =IFERROR(__xludf.DUMMYFUNCTION("IF('Respuestas de formulario 1'!G64="""","""",IF(LEFT(REGEXREPLACE(TO_TEXT('Respuestas de formulario 1'!G64),""[^0-9]"",""""),2)=""54"",""+""&REGEXREPLACE(TO_TEXT('Respuestas de formulario 1'!G64),""[^0-9]"",""""),""+54""&REGEXREPLACE(TO_TEXT('Respuestas "&"de formulario 1'!G64),""[^0-9]"","""")))"),"+543518142452") -> +543518142452 | H64: ='Respuestas de formulario 1'!S64 -> 2023 | I64: =IFERROR(__xludf.DUMMYFUNCTION("IF('Respuestas de formulario 1'!I64="""","""",TO_TEXT('Respuestas de formulario 1'!I64))"),"Particular") -> Particular | J64: =IFERROR(__xludf.DUMMYFUNCTION("IF('Respuestas de formulario 1'!J64<>"""",UPPER(TRIM(TO_TEXT('Respuestas de formulario 1'!J64))),IF('Respuestas de formulario 1'!O64<>"""",UPPER(TRIM(TO_TEXT('Respuestas de formulario 1'!O64))),""""))"),"") | K64: =IFERROR(__xludf.DUMMYFUNCTION("IF('Respuestas de formulario 1'!K64="""","""",TO_TEXT('Respuestas de formulario 1'!K64))"),"") | L64: =IFERROR(__xludf.DUMMYFUNCTION("IF('Respuestas de formulario 1'!L64="""","""",TO_TEXT('Respuestas de formulario 1'!L64))"),"") | M64: =IFERROR(__xludf.DUMMYFUNCTION("IF('Respuestas de formulario 1'!M64="""","""",TO_TEXT('Respuestas de formulario 1'!M64))"),"") | N64: =IF(A64="","",IFERROR(YEAR(A64),"")) -> 2023 | O64: =IF(A64="","",IFERROR(TEXT(A64,"mmmm"),"")) -> febrero | P64: Ruiz Luis
A65: ='Respuestas de formulario 1'!A65 -> 44971.425 | B65: ='Respuestas de formulario 1'!B65 -> Martinez | C65: ='Respuestas de formulario 1'!C65 -> Joaquin Adolfo | D65: ='Respuestas de formulario 1'!D65 | E65: ='Respuestas de formulario 1'!E65 -> 19629 | F65: ='Respuestas de formulario 1'!F65 -> 10903673 | G65: =IFERROR(__xludf.DUMMYFUNCTION("IF('Respuestas de formulario 1'!G65="""","""",IF(LEFT(REGEXREPLACE(TO_TEXT('Respuestas de formulario 1'!G65),""[^0-9]"",""""),2)=""54"",""+""&REGEXREPLACE(TO_TEXT('Respuestas de formulario 1'!G65),""[^0-9]"",""""),""+54""&REGEXREPLACE(TO_TEXT('Respuestas "&"de formulario 1'!G65),""[^0-9]"","""")))"),"+543516566224") -> +543516566224 | H65: ='Respuestas de formulario 1'!S65 -> 2023 | I65: =IFERROR(__xludf.DUMMYFUNCTION("IF('Respuestas de formulario 1'!I65="""","""",TO_TEXT('Respuestas de formulario 1'!I65))"),"Obra social") -> Obra social | J65: =IFERROR(__xludf.DUMMYFUNCTION("IF('Respuestas de formulario 1'!J65<>"""",UPPER(TRIM(TO_TEXT('Respuestas de formulario 1'!J65))),IF('Respuestas de formulario 1'!O65<>"""",UPPER(TRIM(TO_TEXT('Respuestas de formulario 1'!O65))),""""))"),"APROSS") -> APROSS | K65: =IFERROR(__xludf.DUMMYFUNCTION("IF('Respuestas de formulario 1'!K65="""","""",TO_TEXT('Respuestas de formulario 1'!K65))"),"") | L65: =IFERROR(__xludf.DUMMYFUNCTION("IF('Respuestas de formulario 1'!L65="""","""",TO_TEXT('Respuestas de formulario 1'!L65))"),"") | M65: =IFERROR(__xludf.DUMMYFUNCTION("IF('Respuestas de formulario 1'!M65="""","""",TO_TEXT('Respuestas de formulario 1'!M65))"),"") | N65: =IF(A65="","",IFERROR(YEAR(A65),"")) -> 2023 | O65: =IF(A65="","",IFERROR(TEXT(A65,"mmmm"),"")) -> febrero | P65: Martinez Joaquin Adolfo
A66: ='Respuestas de formulario 1'!A66 -> 44971.496 | B66: ='Respuestas de formulario 1'!B66 -> Inbrechts | C66: ='Respuestas de formulario 1'!C66 -> Lisett | D66: ='Respuestas de formulario 1'!D66 -> inbrechts@gmail.com | E66: ='Respuestas de formulario 1'!E66 -> 31725 | F66: ='Respuestas de formulario 1'!F66 -> 95826217 | G66: =IFERROR(__xludf.DUMMYFUNCTION("IF('Respuestas de formulario 1'!G66="""","""",IF(LEFT(REGEXREPLACE(TO_TEXT('Respuestas de formulario 1'!G66),""[^0-9]"",""""),2)=""54"",""+""&REGEXREPLACE(TO_TEXT('Respuestas de formulario 1'!G66),""[^0-9]"",""""),""+54""&REGEXREPLACE(TO_TEXT('Respuestas "&"de formulario 1'!G66),""[^0-9]"","""")))"),"+543513475295") -> +543513475295 | H66: ='Respuestas de formulario 1'!S66 -> 2023 | I66: =IFERROR(__xludf.DUMMYFUNCTION("IF('Respuestas de formulario 1'!I66="""","""",TO_TEXT('Respuestas de formulario 1'!I66))"),"Particular") -> Particular | J66: =IFERROR(__xludf.DUMMYFUNCTION("IF('Respuestas de formulario 1'!J66<>"""",UPPER(TRIM(TO_TEXT('Respuestas de formulario 1'!J66))),IF('Respuestas de formulario 1'!O66<>"""",UPPER(TRIM(TO_TEXT('Respuestas de formulario 1'!O66))),""""))"),"") | K66: =IFERROR(__xludf.DUMMYFUNCTION("IF('Respuestas de formulario 1'!K66="""","""",TO_TEXT('Respuestas de formulario 1'!K66))"),"") | L66: =IFERROR(__xludf.DUMMYFUNCTION("IF('Respuestas de formulario 1'!L66="""","""",TO_TEXT('Respuestas de formulario 1'!L66))"),"") | M66: =IFERROR(__xludf.DUMMYFUNCTION("IF('Respuestas de formulario 1'!M66="""","""",TO_TEXT('Respuestas de formulario 1'!M66))"),"") | N66: =IF(A66="","",IFERROR(YEAR(A66),"")) -> 2023 | O66: =IF(A66="","",IFERROR(TEXT(A66,"mmmm"),"")) -> febrero | P66: Inbrechts Lisett
A67: ='Respuestas de formulario 1'!A67 -> 44971.499 | B67: ='Respuestas de formulario 1'!B67 -> Gutiérrez | C67: ='Respuestas de formulario 1'!C67 -> Ledis | D67: ='Respuestas de formulario 1'!D67 -> inbrechts@gmail.com | E67: ='Respuestas de formulario 1'!E67 -> 23350 | F67: ='Respuestas de formulario 1'!F67 -> 39153938 | G67: =IFERROR(__xludf.DUMMYFUNCTION("IF('Respuestas de formulario 1'!G67="""","""",IF(LEFT(REGEXREPLACE(TO_TEXT('Respuestas de formulario 1'!G67),""[^0-9]"",""""),2)=""54"",""+""&REGEXREPLACE(TO_TEXT('Respuestas de formulario 1'!G67),""[^0-9]"",""""),""+54""&REGEXREPLACE(TO_TEXT('Respuestas "&"de formulario 1'!G67),""[^0-9]"","""")))"),"+543513475295") -> +543513475295 | H67: ='Respuestas de formulario 1'!S67 -> 2023 | I67: =IFERROR(__xludf.DUMMYFUNCTION("IF('Respuestas de formulario 1'!I67="""","""",TO_TEXT('Respuestas de formulario 1'!I67))"),"Particular") -> Particular | J67: =IFERROR(__xludf.DUMMYFUNCTION("IF('Respuestas de formulario 1'!J67<>"""",UPPER(TRIM(TO_TEXT('Respuestas de formulario 1'!J67))),IF('Respuestas de formulario 1'!O67<>"""",UPPER(TRIM(TO_TEXT('Respuestas de formulario 1'!O67))),""""))"),"") | K67: =IFERROR(__xludf.DUMMYFUNCTION("IF('Respuestas de formulario 1'!K67="""","""",TO_TEXT('Respuestas de formulario 1'!K67))"),"") | L67: =IFERROR(__xludf.DUMMYFUNCTION("IF('Respuestas de formulario 1'!L67="""","""",TO_TEXT('Respuestas de formulario 1'!L67))"),"") | M67: =IFERROR(__xludf.DUMMYFUNCTION("IF('Respuestas de formulario 1'!M67="""","""",TO_TEXT('Respuestas de formulario 1'!M67))"),"") | N67: =IF(A67="","",IFERROR(YEAR(A67),"")) -> 2023 | O67: =IF(A67="","",IFERROR(TEXT(A67,"mmmm"),"")) -> febrero | P67: Gutiérrez Ledis
A68: ='Respuestas de formulario 1'!A68 -> 44972.484 | B68: ='Respuestas de formulario 1'!B68 -> Galarce | C68: ='Respuestas de formulario 1'!C68 -> Carlos | D68: ='Respuestas de formulario 1'!D68 -> Cag1@hotmail.com.ar | E68: ='Respuestas de formulario 1'!E68 -> 28696 | F68: ='Respuestas de formulario 1'!F68 -> 26672639 | G68: =IFERROR(__xludf.DUMMYFUNCTION("IF('Respuestas de formulario 1'!G68="""","""",IF(LEFT(REGEXREPLACE(TO_TEXT('Respuestas de formulario 1'!G68),""[^0-9]"",""""),2)=""54"",""+""&REGEXREPLACE(TO_TEXT('Respuestas de formulario 1'!G68),""[^0-9]"",""""),""+54""&REGEXREPLACE(TO_TEXT('Respuestas "&"de formulario 1'!G68),""[^0-9]"","""")))"),"+543513642210") -> +543513642210 | H68: ='Respuestas de formulario 1'!S68 -> 2023 | I68: =IFERROR(__xludf.DUMMYFUNCTION("IF('Respuestas de formulario 1'!I68="""","""",TO_TEXT('Respuestas de formulario 1'!I68))"),"Particular") -> Particular | J68: =IFERROR(__xludf.DUMMYFUNCTION("IF('Respuestas de formulario 1'!J68<>"""",UPPER(TRIM(TO_TEXT('Respuestas de formulario 1'!J68))),IF('Respuestas de formulario 1'!O68<>"""",UPPER(TRIM(TO_TEXT('Respuestas de formulario 1'!O68))),""""))"),"") | K68: =IFERROR(__xludf.DUMMYFUNCTION("IF('Respuestas de formulario 1'!K68="""","""",TO_TEXT('Respuestas de formulario 1'!K68))"),"") | L68: =IFERROR(__xludf.DUMMYFUNCTION("IF('Respuestas de formulario 1'!L68="""","""",TO_TEXT('Respuestas de formulario 1'!L68))"),"") | M68: =IFERROR(__xludf.DUMMYFUNCTION("IF('Respuestas de formulario 1'!M68="""","""",TO_TEXT('Respuestas de formulario 1'!M68))"),"") | N68: =IF(A68="","",IFERROR(YEAR(A68),"")) -> 2023 | O68: =IF(A68="","",IFERROR(TEXT(A68,"mmmm"),"")) -> febrero | P68: Galarce Carlos
A69: ='Respuestas de formulario 1'!A69 -> 44972.782 | B69: ='Respuestas de formulario 1'!B69 -> Aisa | C69: ='Respuestas de formulario 1'!C69 -> Ruben | D69: ='Respuestas de formulario 1'!D69 -> rubenelderaisa@hotmail.com | E69: ='Respuestas de formulario 1'!E69 -> 21530 | F69: ='Respuestas de formulario 1'!F69 -> 12671913 | G69: =IFERROR(__xludf.DUMMYFUNCTION("IF('Respuestas de formulario 1'!G69="""","""",IF(LEFT(REGEXREPLACE(TO_TEXT('Respuestas de formulario 1'!G69),""[^0-9]"",""""),2)=""54"",""+""&REGEXREPLACE(TO_TEXT('Respuestas de formulario 1'!G69),""[^0-9]"",""""),""+54""&REGEXREPLACE(TO_TEXT('Respuestas "&"de formulario 1'!G69),""[^0-9]"","""")))"),"+543515415895") -> +543515415895 | H69: ='Respuestas de formulario 1'!S69 -> 2023 | I69: =IFERROR(__xludf.DUMMYFUNCTION("IF('Respuestas de formulario 1'!I69="""","""",TO_TEXT('Respuestas de formulario 1'!I69))"),"Particular") -> Particular | J69: =IFERROR(__xludf.DUMMYFUNCTION("IF('Respuestas de formulario 1'!J69<>"""",UPPER(TRIM(TO_TEXT('Respuestas de formulario 1'!J69))),IF('Respuestas de formulario 1'!O69<>"""",UPPER(TRIM(TO_TEXT('Respuestas de formulario 1'!O69))),""""))"),"") | K69: =IFERROR(__xludf.DUMMYFUNCTION("IF('Respuestas de formulario 1'!K69="""","""",TO_TEXT('Respuestas de formulario 1'!K69))"),"") | L69: =IFERROR(__xludf.DUMMYFUNCTION("IF('Respuestas de formulario 1'!L69="""","""",TO_TEXT('Respuestas de formulario 1'!L69))"),"") | M69: =IFERROR(__xludf.DUMMYFUNCTION("IF('Respuestas de formulario 1'!M69="""","""",TO_TEXT('Respuestas de formulario 1'!M69))"),"") | N69: =IF(A69="","",IFERROR(YEAR(A69),"")) -> 2023 | O69: =IF(A69="","",IFERROR(TEXT(A69,"mmmm"),"")) -> febrero | P69: Aisa Ruben
A70: ='Respuestas de formulario 1'!A70 -> 44972.796 | B70: ='Respuestas de formulario 1'!B70 -> Reyna | C70: ='Respuestas de formulario 1'!C70 -> Lucas | D70: ='Respuestas de formulario 1'!D70 -> lucasereyna@gmail.com | E70: ='Respuestas de formulario 1'!E70 -> 31862 | F70: ='Respuestas de formulario 1'!F70 -> 32925170 | G70: =IFERROR(__xludf.DUMMYFUNCTION("IF('Respuestas de formulario 1'!G70="""","""",IF(LEFT(REGEXREPLACE(TO_TEXT('Respuestas de formulario 1'!G70),""[^0-9]"",""""),2)=""54"",""+""&REGEXREPLACE(TO_TEXT('Respuestas de formulario 1'!G70),""[^0-9]"",""""),""+54""&REGEXREPLACE(TO_TEXT('Respuestas "&"de formulario 1'!G70),""[^0-9]"","""")))"),"+543515131485") -> +543515131485 | H70: ='Respuestas de formulario 1'!S70 -> 2023 | I70: =IFERROR(__xludf.DUMMYFUNCTION("IF('Respuestas de formulario 1'!I70="""","""",TO_TEXT('Respuestas de formulario 1'!I70))"),"Particular") -> Particular | J70: =IFERROR(__xludf.DUMMYFUNCTION("IF('Respuestas de formulario 1'!J70<>"""",UPPER(TRIM(TO_TEXT('Respuestas de formulario 1'!J70))),IF('Respuestas de formulario 1'!O70<>"""",UPPER(TRIM(TO_TEXT('Respuestas de formulario 1'!O70))),""""))"),"") | K70: =IFERROR(__xludf.DUMMYFUNCTION("IF('Respuestas de formulario 1'!K70="""","""",TO_TEXT('Respuestas de formulario 1'!K70))"),"") | L70: =IFERROR(__xludf.DUMMYFUNCTION("IF('Respuestas de formulario 1'!L70="""","""",TO_TEXT('Respuestas de formulario 1'!L70))"),"") | M70: =IFERROR(__xludf.DUMMYFUNCTION("IF('Respuestas de formulario 1'!M70="""","""",TO_TEXT('Respuestas de formulario 1'!M70))"),"") | N70: =IF(A70="","",IFERROR(YEAR(A70),"")) -> 2023 | O70: =IF(A70="","",IFERROR(TEXT(A70,"mmmm"),"")) -> febrero | P70: Reyna Lucas
A71: ='Respuestas de formulario 1'!A71 -> 44974.513 | B71: ='Respuestas de formulario 1'!B71 -> Quiligotti | C71: ='Respuestas de formulario 1'!C71 -> Pablo | D71: ='Respuestas de formulario 1'!D71 -> pabloquiligotti@gmail.com | E71: ='Respuestas de formulario 1'!E71 -> 30214 | F71: ='Respuestas de formulario 1'!F71 -> 29706314 | G71: =IFERROR(__xludf.DUMMYFUNCTION("IF('Respuestas de formulario 1'!G71="""","""",IF(LEFT(REGEXREPLACE(TO_TEXT('Respuestas de formulario 1'!G71),""[^0-9]"",""""),2)=""54"",""+""&REGEXREPLACE(TO_TEXT('Respuestas de formulario 1'!G71),""[^0-9]"",""""),""+54""&REGEXREPLACE(TO_TEXT('Respuestas "&"de formulario 1'!G71),""[^0-9]"","""")))"),"+543516870843") -> +543516870843 | H71: ='Respuestas de formulario 1'!S71 -> 2023 | I71: =IFERROR(__xludf.DUMMYFUNCTION("IF('Respuestas de formulario 1'!I71="""","""",TO_TEXT('Respuestas de formulario 1'!I71))"),"Obra social") -> Obra social | J71: =IFERROR(__xludf.DUMMYFUNCTION("IF('Respuestas de formulario 1'!J71<>"""",UPPER(TRIM(TO_TEXT('Respuestas de formulario 1'!J71))),IF('Respuestas de formulario 1'!O71<>"""",UPPER(TRIM(TO_TEXT('Respuestas de formulario 1'!O71))),""""))"),"FEDERADA SALUD") -> FEDERADA SALUD | K71: =IFERROR(__xludf.DUMMYFUNCTION("IF('Respuestas de formulario 1'!K71="""","""",TO_TEXT('Respuestas de formulario 1'!K71))"),"") | L71: =IFERROR(__xludf.DUMMYFUNCTION("IF('Respuestas de formulario 1'!L71="""","""",TO_TEXT('Respuestas de formulario 1'!L71))"),"") | M71: =IFERROR(__xludf.DUMMYFUNCTION("IF('Respuestas de formulario 1'!M71="""","""",TO_TEXT('Respuestas de formulario 1'!M71))"),"") | N71: =IF(A71="","",IFERROR(YEAR(A71),"")) -> 2023 | O71: =IF(A71="","",IFERROR(TEXT(A71,"mmmm"),"")) -> febrero | P71: Quiligotti Pablo
A72: ='Respuestas de formulario 1'!A72 -> 44978.723 | B72: ='Respuestas de formulario 1'!B72 -> Armando | C72: ='Respuestas de formulario 1'!C72 -> Marcos | D72: ='Respuestas de formulario 1'!D72 -> marcos.armando1@gmail.com | E72: ='Respuestas de formulario 1'!E72 -> 32509 | F72: ='Respuestas de formulario 1'!F72 -> 34130395 | G72: =IFERROR(__xludf.DUMMYFUNCTION("IF('Respuestas de formulario 1'!G72="""","""",IF(LEFT(REGEXREPLACE(TO_TEXT('Respuestas de formulario 1'!G72),""[^0-9]"",""""),2)=""54"",""+""&REGEXREPLACE(TO_TEXT('Respuestas de formulario 1'!G72),""[^0-9]"",""""),""+54""&REGEXREPLACE(TO_TEXT('Respuestas "&"de formulario 1'!G72),""[^0-9]"","""")))"),"+543513887184") -> +543513887184 | H72: ='Respuestas de formulario 1'!S72 -> 2023 | I72: =IFERROR(__xludf.DUMMYFUNCTION("IF('Respuestas de formulario 1'!I72="""","""",TO_TEXT('Respuestas de formulario 1'!I72))"),"Particular") -> Particular | J72: =IFERROR(__xludf.DUMMYFUNCTION("IF('Respuestas de formulario 1'!J72<>"""",UPPER(TRIM(TO_TEXT('Respuestas de formulario 1'!J72))),IF('Respuestas de formulario 1'!O72<>"""",UPPER(TRIM(TO_TEXT('Respuestas de formulario 1'!O72))),""""))"),"") | K72: =IFERROR(__xludf.DUMMYFUNCTION("IF('Respuestas de formulario 1'!K72="""","""",TO_TEXT('Respuestas de formulario 1'!K72))"),"") | L72: =IFERROR(__xludf.DUMMYFUNCTION("IF('Respuestas de formulario 1'!L72="""","""",TO_TEXT('Respuestas de formulario 1'!L72))"),"") | M72: =IFERROR(__xludf.DUMMYFUNCTION("IF('Respuestas de formulario 1'!M72="""","""",TO_TEXT('Respuestas de formulario 1'!M72))"),"") | N72: =IF(A72="","",IFERROR(YEAR(A72),"")) -> 2023 | O72: =IF(A72="","",IFERROR(TEXT(A72,"mmmm"),"")) -> febrero | P72: Armando Marcos
A73: ='Respuestas de formulario 1'!A73 -> 44978.802 | B73: ='Respuestas de formulario 1'!B73 -> Heredia | C73: ='Respuestas de formulario 1'!C73 -> Andres | D73: ='Respuestas de formulario 1'!D73 -> andresheredia911@gmail.com | E73: ='Respuestas de formulario 1'!E73 -> 35500 | F73: ='Respuestas de formulario 1'!F73 -> 40248804 | G73: =IFERROR(__xludf.DUMMYFUNCTION("IF('Respuestas de formulario 1'!G73="""","""",IF(LEFT(REGEXREPLACE(TO_TEXT('Respuestas de formulario 1'!G73),""[^0-9]"",""""),2)=""54"",""+""&REGEXREPLACE(TO_TEXT('Respuestas de formulario 1'!G73),""[^0-9]"",""""),""+54""&REGEXREPLACE(TO_TEXT('Respuestas "&"de formulario 1'!G73),""[^0-9]"","""")))"),"+543515331363") -> +543515331363 | H73: ='Respuestas de formulario 1'!S73 -> 2023 | I73: =IFERROR(__xludf.DUMMYFUNCTION("IF('Respuestas de formulario 1'!I73="""","""",TO_TEXT('Respuestas de formulario 1'!I73))"),"Obra social") -> Obra social | J73: =IFERROR(__xludf.DUMMYFUNCTION("IF('Respuestas de formulario 1'!J73<>"""",UPPER(TRIM(TO_TEXT('Respuestas de formulario 1'!J73))),IF('Respuestas de formulario 1'!O73<>"""",UPPER(TRIM(TO_TEXT('Respuestas de formulario 1'!O73))),""""))"),"DASPU") -> DASPU | K73: =IFERROR(__xludf.DUMMYFUNCTION("IF('Respuestas de formulario 1'!K73="""","""",TO_TEXT('Respuestas de formulario 1'!K73))"),"") | L73: =IFERROR(__xludf.DUMMYFUNCTION("IF('Respuestas de formulario 1'!L73="""","""",TO_TEXT('Respuestas de formulario 1'!L73))"),"") | M73: =IFERROR(__xludf.DUMMYFUNCTION("IF('Respuestas de formulario 1'!M73="""","""",TO_TEXT('Respuestas de formulario 1'!M73))"),"") | N73: =IF(A73="","",IFERROR(YEAR(A73),"")) -> 2023 | O73: =IF(A73="","",IFERROR(TEXT(A73,"mmmm"),"")) -> febrero | P73: Heredia Andres
A74: ='Respuestas de formulario 1'!A74 -> 44979.692 | B74: ='Respuestas de formulario 1'!B74 -> Sebastián | C74: ='Respuestas de formulario 1'!C74 -> Octavio | D74: ='Respuestas de formulario 1'!D74 -> octaviosebastiann@gmail.com | E74: ='Respuestas de formulario 1'!E74 -> 34072 | F74: ='Respuestas de formulario 1'!F74 -> 37476306 | G74: =IFERROR(__xludf.DUMMYFUNCTION("IF('Respuestas de formulario 1'!G74="""","""",IF(LEFT(REGEXREPLACE(TO_TEXT('Respuestas de formulario 1'!G74),""[^0-9]"",""""),2)=""54"",""+""&REGEXREPLACE(TO_TEXT('Respuestas de formulario 1'!G74),""[^0-9]"",""""),""+54""&REGEXREPLACE(TO_TEXT('Respuestas "&"de formulario 1'!G74),""[^0-9]"","""")))"),"+543517060825") -> +543517060825 | H74: ='Respuestas de formulario 1'!S74 -> 2023 | I74: =IFERROR(__xludf.DUMMYFUNCTION("IF('Respuestas de formulario 1'!I74="""","""",TO_TEXT('Respuestas de formulario 1'!I74))"),"Particular") -> Particular | J74: =IFERROR(__xludf.DUMMYFUNCTION("IF('Respuestas de formulario 1'!J74<>"""",UPPER(TRIM(TO_TEXT('Respuestas de formulario 1'!J74))),IF('Respuestas de formulario 1'!O74<>"""",UPPER(TRIM(TO_TEXT('Respuestas de formulario 1'!O74))),""""))"),"") | K74: =IFERROR(__xludf.DUMMYFUNCTION("IF('Respuestas de formulario 1'!K74="""","""",TO_TEXT('Respuestas de formulario 1'!K74))"),"") | L74: =IFERROR(__xludf.DUMMYFUNCTION("IF('Respuestas de formulario 1'!L74="""","""",TO_TEXT('Respuestas de formulario 1'!L74))"),"") | M74: =IFERROR(__xludf.DUMMYFUNCTION("IF('Respuestas de formulario 1'!M74="""","""",TO_TEXT('Respuestas de formulario 1'!M74))"),"") | N74: =IF(A74="","",IFERROR(YEAR(A74),"")) -> 2023 | O74: =IF(A74="","",IFERROR(TEXT(A74,"mmmm"),"")) -> febrero | P74: Sebastián Octavio
A75: ='Respuestas de formulario 1'!A75 -> 44979.801 | B75: ='Respuestas de formulario 1'!B75 -> Fernández | C75: ='Respuestas de formulario 1'!C75 -> Marcos Gabriel | D75: ='Respuestas de formulario 1'!D75 -> markosgabriel_1206@hotmail.com | E75: ='Respuestas de formulario 1'!E75 -> 28653 | F75: ='Respuestas de formulario 1'!F75 -> 26484703 | G75: =IFERROR(__xludf.DUMMYFUNCTION("IF('Respuestas de formulario 1'!G75="""","""",IF(LEFT(REGEXREPLACE(TO_TEXT('Respuestas de formulario 1'!G75),""[^0-9]"",""""),2)=""54"",""+""&REGEXREPLACE(TO_TEXT('Respuestas de formulario 1'!G75),""[^0-9]"",""""),""+54""&REGEXREPLACE(TO_TEXT('Respuestas "&"de formulario 1'!G75),""[^0-9]"","""")))"),"+543516324625") -> +543516324625 | H75: ='Respuestas de formulario 1'!S75 -> 2023 | I75: =IFERROR(__xludf.DUMMYFUNCTION("IF('Respuestas de formulario 1'!I75="""","""",TO_TEXT('Respuestas de formulario 1'!I75))"),"Obra social") -> Obra social | J75: =IFERROR(__xludf.DUMMYFUNCTION("IF('Respuestas de formulario 1'!J75<>"""",UPPER(TRIM(TO_TEXT('Respuestas de formulario 1'!J75))),IF('Respuestas de formulario 1'!O75<>"""",UPPER(TRIM(TO_TEXT('Respuestas de formulario 1'!O75))),""""))"),"APROMED") -> APROMED | K75: =IFERROR(__xludf.DUMMYFUNCTION("IF('Respuestas de formulario 1'!K75="""","""",TO_TEXT('Respuestas de formulario 1'!K75))"),"") | L75: =IFERROR(__xludf.DUMMYFUNCTION("IF('Respuestas de formulario 1'!L75="""","""",TO_TEXT('Respuestas de formulario 1'!L75))"),"") | M75: =IFERROR(__xludf.DUMMYFUNCTION("IF('Respuestas de formulario 1'!M75="""","""",TO_TEXT('Respuestas de formulario 1'!M75))"),"") | N75: =IF(A75="","",IFERROR(YEAR(A75),"")) -> 2023 | O75: =IF(A75="","",IFERROR(TEXT(A75,"mmmm"),"")) -> febrero | P75: Fernández Marcos Gabriel
A76: ='Respuestas de formulario 1'!A76 -> 44985.698 | B76: ='Respuestas de formulario 1'!B76 -> Cantonati | C76: ='Respuestas de formulario 1'!C76 -> María Belén | D76: ='Respuestas de formulario 1'!D76 -> Belcantonati@hotmail.com | E76: ='Respuestas de formulario 1'!E76 -> 31031 | F76: ='Respuestas de formulario 1'!F76 -> 31187943 | G76: =IFERROR(__xludf.DUMMYFUNCTION("IF('Respuestas de formulario 1'!G76="""","""",IF(LEFT(REGEXREPLACE(TO_TEXT('Respuestas de formulario 1'!G76),""[^0-9]"",""""),2)=""54"",""+""&REGEXREPLACE(TO_TEXT('Respuestas de formulario 1'!G76),""[^0-9]"",""""),""+54""&REGEXREPLACE(TO_TEXT('Respuestas "&"de formulario 1'!G76),""[^0-9]"","""")))"),"+543516330590") -> +543516330590 | H76: ='Respuestas de formulario 1'!S76 -> 2023 | I76: =IFERROR(__xludf.DUMMYFUNCTION("IF('Respuestas de formulario 1'!I76="""","""",TO_TEXT('Respuestas de formulario 1'!I76))"),"Particular") -> Particular | J76: =IFERROR(__xludf.DUMMYFUNCTION("IF('Respuestas de formulario 1'!J76<>"""",UPPER(TRIM(TO_TEXT('Respuestas de formulario 1'!J76))),IF('Respuestas de formulario 1'!O76<>"""",UPPER(TRIM(TO_TEXT('Respuestas de formulario 1'!O76))),""""))"),"") | K76: =IFERROR(__xludf.DUMMYFUNCTION("IF('Respuestas de formulario 1'!K76="""","""",TO_TEXT('Respuestas de formulario 1'!K76))"),"") | L76: =IFERROR(__xludf.DUMMYFUNCTION("IF('Respuestas de formulario 1'!L76="""","""",TO_TEXT('Respuestas de formulario 1'!L76))"),"") | M76: =IFERROR(__xludf.DUMMYFUNCTION("IF('Respuestas de formulario 1'!M76="""","""",TO_TEXT('Respuestas de formulario 1'!M76))"),"") | N76: =IF(A76="","",IFERROR(YEAR(A76),"")) -> 2023 | O76: =IF(A76="","",IFERROR(TEXT(A76,"mmmm"),"")) -> febrero | P76: Cantonati María Belén
A77: ='Respuestas de formulario 1'!A77 -> 44986.359 | B77: ='Respuestas de formulario 1'!B77 -> Druetta | C77: ='Respuestas de formulario 1'!C77 -> Camila | D77: ='Respuestas de formulario 1'!D77 -> camidrue@gmail.com | E77: ='Respuestas de formulario 1'!E77 -> 36796 | F77: ='Respuestas de formulario 1'!F77 -> 42892997 | G77: =IFERROR(__xludf.DUMMYFUNCTION("IF('Respuestas de formulario 1'!G77="""","""",IF(LEFT(REGEXREPLACE(TO_TEXT('Respuestas de formulario 1'!G77),""[^0-9]"",""""),2)=""54"",""+""&REGEXREPLACE(TO_TEXT('Respuestas de formulario 1'!G77),""[^0-9]"",""""),""+54""&REGEXREPLACE(TO_TEXT('Respuestas "&"de formulario 1'!G77),""[^0-9]"","""")))"),"+543512024838") -> +543512024838 | H77: ='Respuestas de formulario 1'!S77 -> 2023 | I77: =IFERROR(__xludf.DUMMYFUNCTION("IF('Respuestas de formulario 1'!I77="""","""",TO_TEXT('Respuestas de formulario 1'!I77))"),"Particular") -> Particular | J77: =IFERROR(__xludf.DUMMYFUNCTION("IF('Respuestas de formulario 1'!J77<>"""",UPPER(TRIM(TO_TEXT('Respuestas de formulario 1'!J77))),IF('Respuestas de formulario 1'!O77<>"""",UPPER(TRIM(TO_TEXT('Respuestas de formulario 1'!O77))),""""))"),"") | K77: =IFERROR(__xludf.DUMMYFUNCTION("IF('Respuestas de formulario 1'!K77="""","""",TO_TEXT('Respuestas de formulario 1'!K77))"),"") | L77: =IFERROR(__xludf.DUMMYFUNCTION("IF('Respuestas de formulario 1'!L77="""","""",TO_TEXT('Respuestas de formulario 1'!L77))"),"") | M77: =IFERROR(__xludf.DUMMYFUNCTION("IF('Respuestas de formulario 1'!M77="""","""",TO_TEXT('Respuestas de formulario 1'!M77))"),"") | N77: =IF(A77="","",IFERROR(YEAR(A77),"")) -> 2023 | O77: =IF(A77="","",IFERROR(TEXT(A77,"mmmm"),"")) -> marzo | P77: Druetta Camila
A78: ='Respuestas de formulario 1'!A78 -> 44986.474 | B78: ='Respuestas de formulario 1'!B78 -> CASTRO | C78: ='Respuestas de formulario 1'!C78 -> Mirta Cristina | D78: ='Respuestas de formulario 1'!D78 -> micricas@hotmail.com | E78: ='Respuestas de formulario 1'!E78 -> 26826 | F78: ='Respuestas de formulario 1'!F78 -> 23198663 | G78: =IFERROR(__xludf.DUMMYFUNCTION("IF('Respuestas de formulario 1'!G78="""","""",IF(LEFT(REGEXREPLACE(TO_TEXT('Respuestas de formulario 1'!G78),""[^0-9]"",""""),2)=""54"",""+""&REGEXREPLACE(TO_TEXT('Respuestas de formulario 1'!G78),""[^0-9]"",""""),""+54""&REGEXREPLACE(TO_TEXT('Respuestas "&"de formulario 1'!G78),""[^0-9]"","""")))"),"+543516520221") -> +543516520221 | H78: ='Respuestas de formulario 1'!S78 -> 2023 | I78: =IFERROR(__xludf.DUMMYFUNCTION("IF('Respuestas de formulario 1'!I78="""","""",TO_TEXT('Respuestas de formulario 1'!I78))"),"Obra social") -> Obra social | J78: =IFERROR(__xludf.DUMMYFUNCTION("IF('Respuestas de formulario 1'!J78<>"""",UPPER(TRIM(TO_TEXT('Respuestas de formulario 1'!J78))),IF('Respuestas de formulario 1'!O78<>"""",UPPER(TRIM(TO_TEXT('Respuestas de formulario 1'!O78))),""""))"),"DASPU") -> DASPU | K78: =IFERROR(__xludf.DUMMYFUNCTION("IF('Respuestas de formulario 1'!K78="""","""",TO_TEXT('Respuestas de formulario 1'!K78))"),"") | L78: =IFERROR(__xludf.DUMMYFUNCTION("IF('Respuestas de formulario 1'!L78="""","""",TO_TEXT('Respuestas de formulario 1'!L78))"),"") | M78: =IFERROR(__xludf.DUMMYFUNCTION("IF('Respuestas de formulario 1'!M78="""","""",TO_TEXT('Respuestas de formulario 1'!M78))"),"") | N78: =IF(A78="","",IFERROR(YEAR(A78),"")) -> 2023 | O78: =IF(A78="","",IFERROR(TEXT(A78,"mmmm"),"")) -> marzo | P78: CASTRO Mirta Cristina
A79: ='Respuestas de formulario 1'!A79 -> 44986.644 | B79: ='Respuestas de formulario 1'!B79 -> Semeraro | C79: ='Respuestas de formulario 1'!C79 -> Nora | D79: ='Respuestas de formulario 1'!D79 -> norasemeraro@gmail.com | E79: ='Respuestas de formulario 1'!E79 -> 21195 | F79: ='Respuestas de formulario 1'!F79 -> 12270859 | G79: =IFERROR(__xludf.DUMMYFUNCTION("IF('Respuestas de formulario 1'!G79="""","""",IF(LEFT(REGEXREPLACE(TO_TEXT('Respuestas de formulario 1'!G79),""[^0-9]"",""""),2)=""54"",""+""&REGEXREPLACE(TO_TEXT('Respuestas de formulario 1'!G79),""[^0-9]"",""""),""+54""&REGEXREPLACE(TO_TEXT('Respuestas "&"de formulario 1'!G79),""[^0-9]"","""")))"),"+543516608455") -> +543516608455 | H79: ='Respuestas de formulario 1'!S79 -> 2023 | I79: =IFERROR(__xludf.DUMMYFUNCTION("IF('Respuestas de formulario 1'!I79="""","""",TO_TEXT('Respuestas de formulario 1'!I79))"),"Obra social") -> Obra social | J79: =IFERROR(__xludf.DUMMYFUNCTION("IF('Respuestas de formulario 1'!J79<>"""",UPPER(TRIM(TO_TEXT('Respuestas de formulario 1'!J79))),IF('Respuestas de formulario 1'!O79<>"""",UPPER(TRIM(TO_TEXT('Respuestas de formulario 1'!O79))),""""))"),"OSSEG") -> OSSEG | K79: =IFERROR(__xludf.DUMMYFUNCTION("IF('Respuestas de formulario 1'!K79="""","""",TO_TEXT('Respuestas de formulario 1'!K79))"),"") | L79: =IFERROR(__xludf.DUMMYFUNCTION("IF('Respuestas de formulario 1'!L79="""","""",TO_TEXT('Respuestas de formulario 1'!L79))"),"") | M79: =IFERROR(__xludf.DUMMYFUNCTION("IF('Respuestas de formulario 1'!M79="""","""",TO_TEXT('Respuestas de formulario 1'!M79))"),"") | N79: =IF(A79="","",IFERROR(YEAR(A79),"")) -> 2023 | O79: =IF(A79="","",IFERROR(TEXT(A79,"mmmm"),"")) -> marzo | P79: Semeraro Nora
A80: ='Respuestas de formulario 1'!A80 -> 44986.803 | B80: ='Respuestas de formulario 1'!B80 -> Sueldo | C80: ='Respuestas de formulario 1'!C80 -> Belkis Anabella | D80: ='Respuestas de formulario 1'!D80 -> basueldo@gmail.com | E80: ='Respuestas de formulario 1'!E80 -> 31671 | F80: ='Respuestas de formulario 1'!F80 -> 32518805 | G80: =IFERROR(__xludf.DUMMYFUNCTION("IF('Respuestas de formulario 1'!G80="""","""",IF(LEFT(REGEXREPLACE(TO_TEXT('Respuestas de formulario 1'!G80),""[^0-9]"",""""),2)=""54"",""+""&REGEXREPLACE(TO_TEXT('Respuestas de formulario 1'!G80),""[^0-9]"",""""),""+54""&REGEXREPLACE(TO_TEXT('Respuestas "&"de formulario 1'!G80),""[^0-9]"","""")))"),"+543512466755") -> +543512466755 | H80: ='Respuestas de formulario 1'!S80 -> 2023 | I80: =IFERROR(__xludf.DUMMYFUNCTION("IF('Respuestas de formulario 1'!I80="""","""",TO_TEXT('Respuestas de formulario 1'!I80))"),"Particular") -> Particular | J80: =IFERROR(__xludf.DUMMYFUNCTION("IF('Respuestas de formulario 1'!J80<>"""",UPPER(TRIM(TO_TEXT('Respuestas de formulario 1'!J80))),IF('Respuestas de formulario 1'!O80<>"""",UPPER(TRIM(TO_TEXT('Respuestas de formulario 1'!O80))),""""))"),"") | K80: =IFERROR(__xludf.DUMMYFUNCTION("IF('Respuestas de formulario 1'!K80="""","""",TO_TEXT('Respuestas de formulario 1'!K80))"),"") | L80: =IFERROR(__xludf.DUMMYFUNCTION("IF('Respuestas de formulario 1'!L80="""","""",TO_TEXT('Respuestas de formulario 1'!L80))"),"") | M80: =IFERROR(__xludf.DUMMYFUNCTION("IF('Respuestas de formulario 1'!M80="""","""",TO_TEXT('Respuestas de formulario 1'!M80))"),"") | N80: =IF(A80="","",IFERROR(YEAR(A80),"")) -> 2023 | O80: =IF(A80="","",IFERROR(TEXT(A80,"mmmm"),"")) -> marzo | P80: Sueldo Belkis Anabella
A81: ='Respuestas de formulario 1'!A81 -> 44987.389 | B81: ='Respuestas de formulario 1'!B81 -> Ponce | C81: ='Respuestas de formulario 1'!C81 -> Federico | D81: ='Respuestas de formulario 1'!D81 -> federico.jponce@gmail.com | E81: ='Respuestas de formulario 1'!E81 -> 34895 | F81: ='Respuestas de formulario 1'!F81 -> 39072489 | G81: =IFERROR(__xludf.DUMMYFUNCTION("IF('Respuestas de formulario 1'!G81="""","""",IF(LEFT(REGEXREPLACE(TO_TEXT('Respuestas de formulario 1'!G81),""[^0-9]"",""""),2)=""54"",""+""&REGEXREPLACE(TO_TEXT('Respuestas de formulario 1'!G81),""[^0-9]"",""""),""+54""&REGEXREPLACE(TO_TEXT('Respuestas "&"de formulario 1'!G81),""[^0-9]"","""")))"),"+543517502384") -> +543517502384 | H81: ='Respuestas de formulario 1'!S81 -> 2023 | I81: =IFERROR(__xludf.DUMMYFUNCTION("IF('Respuestas de formulario 1'!I81="""","""",TO_TEXT('Respuestas de formulario 1'!I81))"),"Obra social") -> Obra social | J81: =IFERROR(__xludf.DUMMYFUNCTION("IF('Respuestas de formulario 1'!J81<>"""",UPPER(TRIM(TO_TEXT('Respuestas de formulario 1'!J81))),IF('Respuestas de formulario 1'!O81<>"""",UPPER(TRIM(TO_TEXT('Respuestas de formulario 1'!O81))),""""))"),"APROSS") -> APROSS | K81: =IFERROR(__xludf.DUMMYFUNCTION("IF('Respuestas de formulario 1'!K81="""","""",TO_TEXT('Respuestas de formulario 1'!K81))"),"") | L81: =IFERROR(__xludf.DUMMYFUNCTION("IF('Respuestas de formulario 1'!L81="""","""",TO_TEXT('Respuestas de formulario 1'!L81))"),"") | M81: =IFERROR(__xludf.DUMMYFUNCTION("IF('Respuestas de formulario 1'!M81="""","""",TO_TEXT('Respuestas de formulario 1'!M81))"),"") | N81: =IF(A81="","",IFERROR(YEAR(A81),"")) -> 2023 | O81: =IF(A81="","",IFERROR(TEXT(A81,"mmmm"),"")) -> marzo | P81: Ponce Federico
A82: ='Respuestas de formulario 1'!A82 -> 44987.457 | B82: ='Respuestas de formulario 1'!B82 -> Baigorri | C82: ='Respuestas de formulario 1'!C82 -> Joel | D82: ='Respuestas de formulario 1'!D82 -> Baigorri.joel@gmail.com | E82: ='Respuestas de formulario 1'!E82 -> 31593 | F82: ='Respuestas de formulario 1'!F82 -> 32372182 | G82: =IFERROR(__xludf.DUMMYFUNCTION("IF('Respuestas de formulario 1'!G82="""","""",IF(LEFT(REGEXREPLACE(TO_TEXT('Respuestas de formulario 1'!G82),""[^0-9]"",""""),2)=""54"",""+""&REGEXREPLACE(TO_TEXT('Respuestas de formulario 1'!G82),""[^0-9]"",""""),""+54""&REGEXREPLACE(TO_TEXT('Respuestas "&"de formulario 1'!G82),""[^0-9]"","""")))"),"+543513471220") -> +543513471220 | H82: ='Respuestas de formulario 1'!S82 -> 2023 | I82: =IFERROR(__xludf.DUMMYFUNCTION("IF('Respuestas de formulario 1'!I82="""","""",TO_TEXT('Respuestas de formulario 1'!I82))"),"Particular") -> Particular | J82: =IFERROR(__xludf.DUMMYFUNCTION("IF('Respuestas de formulario 1'!J82<>"""",UPPER(TRIM(TO_TEXT('Respuestas de formulario 1'!J82))),IF('Respuestas de formulario 1'!O82<>"""",UPPER(TRIM(TO_TEXT('Respuestas de formulario 1'!O82))),""""))"),"") | K82: =IFERROR(__xludf.DUMMYFUNCTION("IF('Respuestas de formulario 1'!K82="""","""",TO_TEXT('Respuestas de formulario 1'!K82))"),"") | L82: =IFERROR(__xludf.DUMMYFUNCTION("IF('Respuestas de formulario 1'!L82="""","""",TO_TEXT('Respuestas de formulario 1'!L82))"),"") | M82: =IFERROR(__xludf.DUMMYFUNCTION("IF('Respuestas de formulario 1'!M82="""","""",TO_TEXT('Respuestas de formulario 1'!M82))"),"") | N82: =IF(A82="","",IFERROR(YEAR(A82),"")) -> 2023 | O82: =IF(A82="","",IFERROR(TEXT(A82,"mmmm"),"")) -> marzo | P82: Baigorri Joel
A83: ='Respuestas de formulario 1'!A83 -> 44988.747 | B83: ='Respuestas de formulario 1'!B83 -> Grion | C83: ='Respuestas de formulario 1'!C83 -> Alejandro | D83: ='Respuestas de formulario 1'!D83 -> alejandrogrion@gmail.com | E83: ='Respuestas de formulario 1'!E83 -> 25928 | F83: ='Respuestas de formulario 1'!F83 -> 21967210 | G83: =IFERROR(__xludf.DUMMYFUNCTION("IF('Respuestas de formulario 1'!G83="""","""",IF(LEFT(REGEXREPLACE(TO_TEXT('Respuestas de formulario 1'!G83),""[^0-9]"",""""),2)=""54"",""+""&REGEXREPLACE(TO_TEXT('Respuestas de formulario 1'!G83),""[^0-9]"",""""),""+54""&REGEXREPLACE(TO_TEXT('Respuestas "&"de formulario 1'!G83),""[^0-9]"","""")))"),"+543512388424") -> +543512388424 | H83: ='Respuestas de formulario 1'!S83 -> 2023 | I83: =IFERROR(__xludf.DUMMYFUNCTION("IF('Respuestas de formulario 1'!I83="""","""",TO_TEXT('Respuestas de formulario 1'!I83))"),"Particular") -> Particular | J83: =IFERROR(__xludf.DUMMYFUNCTION("IF('Respuestas de formulario 1'!J83<>"""",UPPER(TRIM(TO_TEXT('Respuestas de formulario 1'!J83))),IF('Respuestas de formulario 1'!O83<>"""",UPPER(TRIM(TO_TEXT('Respuestas de formulario 1'!O83))),""""))"),"") | K83: =IFERROR(__xludf.DUMMYFUNCTION("IF('Respuestas de formulario 1'!K83="""","""",TO_TEXT('Respuestas de formulario 1'!K83))"),"") | L83: =IFERROR(__xludf.DUMMYFUNCTION("IF('Respuestas de formulario 1'!L83="""","""",TO_TEXT('Respuestas de formulario 1'!L83))"),"") | M83: =IFERROR(__xludf.DUMMYFUNCTION("IF('Respuestas de formulario 1'!M83="""","""",TO_TEXT('Respuestas de formulario 1'!M83))"),"") | N83: =IF(A83="","",IFERROR(YEAR(A83),"")) -> 2023 | O83: =IF(A83="","",IFERROR(TEXT(A83,"mmmm"),"")) -> marzo | P83: Grion Alejandro
A84: ='Respuestas de formulario 1'!A84 -> 44991.51 | B84: ='Respuestas de formulario 1'!B84 -> Biani | C84: ='Respuestas de formulario 1'!C84 -> Jeremias | D84: ='Respuestas de formulario 1'!D84 -> diegoivanbiani79@gmail.com | E84: ='Respuestas de formulario 1'!E84 -> 39526 | F84: ='Respuestas de formulario 1'!F84 -> 48124818 | G84: =IFERROR(__xludf.DUMMYFUNCTION("IF('Respuestas de formulario 1'!G84="""","""",IF(LEFT(REGEXREPLACE(TO_TEXT('Respuestas de formulario 1'!G84),""[^0-9]"",""""),2)=""54"",""+""&REGEXREPLACE(TO_TEXT('Respuestas de formulario 1'!G84),""[^0-9]"",""""),""+54""&REGEXREPLACE(TO_TEXT('Respuestas "&"de formulario 1'!G84),""[^0-9]"","""")))"),"+543513357046") -> +543513357046 | H84: ='Respuestas de formulario 1'!S84 -> 2023 | I84: =IFERROR(__xludf.DUMMYFUNCTION("IF('Respuestas de formulario 1'!I84="""","""",TO_TEXT('Respuestas de formulario 1'!I84))"),"Particular") -> Particular | J84: =IFERROR(__xludf.DUMMYFUNCTION("IF('Respuestas de formulario 1'!J84<>"""",UPPER(TRIM(TO_TEXT('Respuestas de formulario 1'!J84))),IF('Respuestas de formulario 1'!O84<>"""",UPPER(TRIM(TO_TEXT('Respuestas de formulario 1'!O84))),""""))"),"") | K84: =IFERROR(__xludf.DUMMYFUNCTION("IF('Respuestas de formulario 1'!K84="""","""",TO_TEXT('Respuestas de formulario 1'!K84))"),"") | L84: =IFERROR(__xludf.DUMMYFUNCTION("IF('Respuestas de formulario 1'!L84="""","""",TO_TEXT('Respuestas de formulario 1'!L84))"),"") | M84: =IFERROR(__xludf.DUMMYFUNCTION("IF('Respuestas de formulario 1'!M84="""","""",TO_TEXT('Respuestas de formulario 1'!M84))"),"") | N84: =IF(A84="","",IFERROR(YEAR(A84),"")) -> 2023 | O84: =IF(A84="","",IFERROR(TEXT(A84,"mmmm"),"")) -> marzo | P84: Biani Jeremias
A85: ='Respuestas de formulario 1'!A85 -> 44991.863 | B85: ='Respuestas de formulario 1'!B85 -> Castro | C85: ='Respuestas de formulario 1'!C85 -> Facundo | D85: ='Respuestas de formulario 1'!D85 -> castrofacundo265@gmail.com | E85: ='Respuestas de formulario 1'!E85 -> 36204 | F85: ='Respuestas de formulario 1'!F85 -> 40506846 | G85: =IFERROR(__xludf.DUMMYFUNCTION("IF('Respuestas de formulario 1'!G85="""","""",IF(LEFT(REGEXREPLACE(TO_TEXT('Respuestas de formulario 1'!G85),""[^0-9]"",""""),2)=""54"",""+""&REGEXREPLACE(TO_TEXT('Respuestas de formulario 1'!G85),""[^0-9]"",""""),""+54""&REGEXREPLACE(TO_TEXT('Respuestas "&"de formulario 1'!G85),""[^0-9]"","""")))"),"+543542461695") -> +543542461695 | H85: ='Respuestas de formulario 1'!S85 -> 2023 | I85: =IFERROR(__xludf.DUMMYFUNCTION("IF('Respuestas de formulario 1'!I85="""","""",TO_TEXT('Respuestas de formulario 1'!I85))"),"Obra social") -> Obra social | J85: =IFERROR(__xludf.DUMMYFUNCTION("IF('Respuestas de formulario 1'!J85<>"""",UPPER(TRIM(TO_TEXT('Respuestas de formulario 1'!J85))),IF('Respuestas de formulario 1'!O85<>"""",UPPER(TRIM(TO_TEXT('Respuestas de formulario 1'!O85))),""""))"),"APROSS") -> APROSS | K85: =IFERROR(__xludf.DUMMYFUNCTION("IF('Respuestas de formulario 1'!K85="""","""",TO_TEXT('Respuestas de formulario 1'!K85))"),"") | L85: =IFERROR(__xludf.DUMMYFUNCTION("IF('Respuestas de formulario 1'!L85="""","""",TO_TEXT('Respuestas de formulario 1'!L85))"),"") | M85: =IFERROR(__xludf.DUMMYFUNCTION("IF('Respuestas de formulario 1'!M85="""","""",TO_TEXT('Respuestas de formulario 1'!M85))"),"") | N85: =IF(A85="","",IFERROR(YEAR(A85),"")) -> 2023 | O85: =IF(A85="","",IFERROR(TEXT(A85,"mmmm"),"")) -> marzo | P85: Castro Facundo
A86: ='Respuestas de formulario 1'!A86 -> 44992.498 | B86: ='Respuestas de formulario 1'!B86 -> DUARTE POLANCO | C86: ='Respuestas de formulario 1'!C86 -> AXEL MATIAS | D86: ='Respuestas de formulario 1'!D86 -> amatiasduarte@gmail.com | E86: ='Respuestas de formulario 1'!E86 -> 32925 | F86: ='Respuestas de formulario 1'!F86 -> 35054004 | G86: =IFERROR(__xludf.DUMMYFUNCTION("IF('Respuestas de formulario 1'!G86="""","""",IF(LEFT(REGEXREPLACE(TO_TEXT('Respuestas de formulario 1'!G86),""[^0-9]"",""""),2)=""54"",""+""&REGEXREPLACE(TO_TEXT('Respuestas de formulario 1'!G86),""[^0-9]"",""""),""+54""&REGEXREPLACE(TO_TEXT('Respuestas "&"de formulario 1'!G86),""[^0-9]"","""")))"),"+543513792102") -> +543513792102 | H86: ='Respuestas de formulario 1'!S86 -> 2023 | I86: =IFERROR(__xludf.DUMMYFUNCTION("IF('Respuestas de formulario 1'!I86="""","""",TO_TEXT('Respuestas de formulario 1'!I86))"),"Obra social") -> Obra social | J86: =IFERROR(__xludf.DUMMYFUNCTION("IF('Respuestas de formulario 1'!J86<>"""",UPPER(TRIM(TO_TEXT('Respuestas de formulario 1'!J86))),IF('Respuestas de formulario 1'!O86<>"""",UPPER(TRIM(TO_TEXT('Respuestas de formulario 1'!O86))),""""))"),"SANCOR") -> SANCOR | K86: =IFERROR(__xludf.DUMMYFUNCTION("IF('Respuestas de formulario 1'!K86="""","""",TO_TEXT('Respuestas de formulario 1'!K86))"),"") | L86: =IFERROR(__xludf.DUMMYFUNCTION("IF('Respuestas de formulario 1'!L86="""","""",TO_TEXT('Respuestas de formulario 1'!L86))"),"") | M86: =IFERROR(__xludf.DUMMYFUNCTION("IF('Respuestas de formulario 1'!M86="""","""",TO_TEXT('Respuestas de formulario 1'!M86))"),"") | N86: =IF(A86="","",IFERROR(YEAR(A86),"")) -> 2023 | O86: =IF(A86="","",IFERROR(TEXT(A86,"mmmm"),"")) -> marzo | P86: DUARTE POLANCO AXEL MATIAS
A87: ='Respuestas de formulario 1'!A87 -> 44992.869 | B87: ='Respuestas de formulario 1'!B87 -> Bordino | C87: ='Respuestas de formulario 1'!C87 -> Alvaro | D87: ='Respuestas de formulario 1'!D87 -> Alvarobordino1995@gmail.com | E87: ='Respuestas de formulario 1'!E87 -> 34460 | F87: ='Respuestas de formulario 1'!F87 -> 38183134 | G87: =IFERROR(__xludf.DUMMYFUNCTION("IF('Respuestas de formulario 1'!G87="""","""",IF(LEFT(REGEXREPLACE(TO_TEXT('Respuestas de formulario 1'!G87),""[^0-9]"",""""),2)=""54"",""+""&REGEXREPLACE(TO_TEXT('Respuestas de formulario 1'!G87),""[^0-9]"",""""),""+54""&REGEXREPLACE(TO_TEXT('Respuestas "&"de formulario 1'!G87),""[^0-9]"","""")))"),"+543515337720") -> +543515337720 | H87: ='Respuestas de formulario 1'!S87 -> 2023 | I87: =IFERROR(__xludf.DUMMYFUNCTION("IF('Respuestas de formulario 1'!I87="""","""",TO_TEXT('Respuestas de formulario 1'!I87))"),"Particular") -> Particular | J87: =IFERROR(__xludf.DUMMYFUNCTION("IF('Respuestas de formulario 1'!J87<>"""",UPPER(TRIM(TO_TEXT('Respuestas de formulario 1'!J87))),IF('Respuestas de formulario 1'!O87<>"""",UPPER(TRIM(TO_TEXT('Respuestas de formulario 1'!O87))),""""))"),"") | K87: =IFERROR(__xludf.DUMMYFUNCTION("IF('Respuestas de formulario 1'!K87="""","""",TO_TEXT('Respuestas de formulario 1'!K87))"),"") | L87: =IFERROR(__xludf.DUMMYFUNCTION("IF('Respuestas de formulario 1'!L87="""","""",TO_TEXT('Respuestas de formulario 1'!L87))"),"") | M87: =IFERROR(__xludf.DUMMYFUNCTION("IF('Respuestas de formulario 1'!M87="""","""",TO_TEXT('Respuestas de formulario 1'!M87))"),"") | N87: =IF(A87="","",IFERROR(YEAR(A87),"")) -> 2023 | O87: =IF(A87="","",IFERROR(TEXT(A87,"mmmm"),"")) -> marzo | P87: Bordino Alvaro
A88: ='Respuestas de formulario 1'!A88 -> 44993.774 | B88: ='Respuestas de formulario 1'!B88 -> Freno | C88: ='Respuestas de formulario 1'!C88 -> Pablo Manuel | D88: ='Respuestas de formulario 1'!D88 -> pablomanuelfreno@gmail.com | E88: ='Respuestas de formulario 1'!E88 -> 21433 | F88: ='Respuestas de formulario 1'!F88 -> 12613243 | G88: =IFERROR(__xludf.DUMMYFUNCTION("IF('Respuestas de formulario 1'!G88="""","""",IF(LEFT(REGEXREPLACE(TO_TEXT('Respuestas de formulario 1'!G88),""[^0-9]"",""""),2)=""54"",""+""&REGEXREPLACE(TO_TEXT('Respuestas de formulario 1'!G88),""[^0-9]"",""""),""+54""&REGEXREPLACE(TO_TEXT('Respuestas "&"de formulario 1'!G88),""[^0-9]"","""")))"),"+543515435327") -> +543515435327 | H88: ='Respuestas de formulario 1'!S88 -> 2023 | I88: =IFERROR(__xludf.DUMMYFUNCTION("IF('Respuestas de formulario 1'!I88="""","""",TO_TEXT('Respuestas de formulario 1'!I88))"),"Obra social") -> Obra social | J88: =IFERROR(__xludf.DUMMYFUNCTION("IF('Respuestas de formulario 1'!J88<>"""",UPPER(TRIM(TO_TEXT('Respuestas de formulario 1'!J88))),IF('Respuestas de formulario 1'!O88<>"""",UPPER(TRIM(TO_TEXT('Respuestas de formulario 1'!O88))),""""))"),"MEDIFE") -> MEDIFE | K88: =IFERROR(__xludf.DUMMYFUNCTION("IF('Respuestas de formulario 1'!K88="""","""",TO_TEXT('Respuestas de formulario 1'!K88))"),"") | L88: =IFERROR(__xludf.DUMMYFUNCTION("IF('Respuestas de formulario 1'!L88="""","""",TO_TEXT('Respuestas de formulario 1'!L88))"),"") | M88: =IFERROR(__xludf.DUMMYFUNCTION("IF('Respuestas de formulario 1'!M88="""","""",TO_TEXT('Respuestas de formulario 1'!M88))"),"") | N88: =IF(A88="","",IFERROR(YEAR(A88),"")) -> 2023 | O88: =IF(A88="","",IFERROR(TEXT(A88,"mmmm"),"")) -> marzo | P88: Freno Pablo Manuel
A89: ='Respuestas de formulario 1'!A89 -> 44998.423 | B89: ='Respuestas de formulario 1'!B89 -> Gadea | C89: ='Respuestas de formulario 1'!C89 -> Erik paul | D89: ='Respuestas de formulario 1'!D89 -> erikgadea@hotmail.com.ar | E89: ='Respuestas de formulario 1'!E89 -> 35542 | F89: ='Respuestas de formulario 1'!F89 -> 40203248 | G89: =IFERROR(__xludf.DUMMYFUNCTION("IF('Respuestas de formulario 1'!G89="""","""",IF(LEFT(REGEXREPLACE(TO_TEXT('Respuestas de formulario 1'!G89),""[^0-9]"",""""),2)=""54"",""+""&REGEXREPLACE(TO_TEXT('Respuestas de formulario 1'!G89),""[^0-9]"",""""),""+54""&REGEXREPLACE(TO_TEXT('Respuestas "&"de formulario 1'!G89),""[^0-9]"","""")))"),"+543522400613") -> +543522400613 | H89: ='Respuestas de formulario 1'!S89 -> 2023 | I89: =IFERROR(__xludf.DUMMYFUNCTION("IF('Respuestas de formulario 1'!I89="""","""",TO_TEXT('Respuestas de formulario 1'!I89))"),"Obra social") -> Obra social | J89: =IFERROR(__xludf.DUMMYFUNCTION("IF('Respuestas de formulario 1'!J89<>"""",UPPER(TRIM(TO_TEXT('Respuestas de formulario 1'!J89))),IF('Respuestas de formulario 1'!O89<>"""",UPPER(TRIM(TO_TEXT('Respuestas de formulario 1'!O89))),""""))"),"UNIMED") -> UNIMED | K89: =IFERROR(__xludf.DUMMYFUNCTION("IF('Respuestas de formulario 1'!K89="""","""",TO_TEXT('Respuestas de formulario 1'!K89))"),"") | L89: =IFERROR(__xludf.DUMMYFUNCTION("IF('Respuestas de formulario 1'!L89="""","""",TO_TEXT('Respuestas de formulario 1'!L89))"),"") | M89: =IFERROR(__xludf.DUMMYFUNCTION("IF('Respuestas de formulario 1'!M89="""","""",TO_TEXT('Respuestas de formulario 1'!M89))"),"") | N89: =IF(A89="","",IFERROR(YEAR(A89),"")) -> 2023 | O89: =IF(A89="","",IFERROR(TEXT(A89,"mmmm"),"")) -> marzo | P89: Gadea Erik paul
A90: ='Respuestas de formulario 1'!A90 -> 44999.482 | B90: ='Respuestas de formulario 1'!B90 -> Charif | C90: ='Respuestas de formulario 1'!C90 -> Asdrubal | D90: ='Respuestas de formulario 1'!D90 -> Ivoncharif556@gmail.com | E90: ='Respuestas de formulario 1'!E90 -> 26823 | F90: ='Respuestas de formulario 1'!F90 -> 23458302 | G90: =IFERROR(__xludf.DUMMYFUNCTION("IF('Respuestas de formulario 1'!G90="""","""",IF(LEFT(REGEXREPLACE(TO_TEXT('Respuestas de formulario 1'!G90),""[^0-9]"",""""),2)=""54"",""+""&REGEXREPLACE(TO_TEXT('Respuestas de formulario 1'!G90),""[^0-9]"",""""),""+54""&REGEXREPLACE(TO_TEXT('Respuestas "&"de formulario 1'!G90),""[^0-9]"","""")))"),"+543513537495") -> +543513537495 | H90: ='Respuestas de formulario 1'!S90 -> 2023 | I90: =IFERROR(__xludf.DUMMYFUNCTION("IF('Respuestas de formulario 1'!I90="""","""",TO_TEXT('Respuestas de formulario 1'!I90))"),"Particular") -> Particular | J90: =IFERROR(__xludf.DUMMYFUNCTION("IF('Respuestas de formulario 1'!J90<>"""",UPPER(TRIM(TO_TEXT('Respuestas de formulario 1'!J90))),IF('Respuestas de formulario 1'!O90<>"""",UPPER(TRIM(TO_TEXT('Respuestas de formulario 1'!O90))),""""))"),"") | K90: =IFERROR(__xludf.DUMMYFUNCTION("IF('Respuestas de formulario 1'!K90="""","""",TO_TEXT('Respuestas de formulario 1'!K90))"),"") | L90: =IFERROR(__xludf.DUMMYFUNCTION("IF('Respuestas de formulario 1'!L90="""","""",TO_TEXT('Respuestas de formulario 1'!L90))"),"") | M90: =IFERROR(__xludf.DUMMYFUNCTION("IF('Respuestas de formulario 1'!M90="""","""",TO_TEXT('Respuestas de formulario 1'!M90))"),"") | N90: =IF(A90="","",IFERROR(YEAR(A90),"")) -> 2023 | O90: =IF(A90="","",IFERROR(TEXT(A90,"mmmm"),"")) -> marzo | P90: Charif Asdrubal
A91: ='Respuestas de formulario 1'!A91 -> 45005.438 | B91: ='Respuestas de formulario 1'!B91 -> Oña | C91: ='Respuestas de formulario 1'!C91 -> Ignacio | D91: ='Respuestas de formulario 1'!D91 -> ignaona@gmail.com | E91: ='Respuestas de formulario 1'!E91 -> 31219 | F91: ='Respuestas de formulario 1'!F91 -> 31669854 | G91: =IFERROR(__xludf.DUMMYFUNCTION("IF('Respuestas de formulario 1'!G91="""","""",IF(LEFT(REGEXREPLACE(TO_TEXT('Respuestas de formulario 1'!G91),""[^0-9]"",""""),2)=""54"",""+""&REGEXREPLACE(TO_TEXT('Respuestas de formulario 1'!G91),""[^0-9]"",""""),""+54""&REGEXREPLACE(TO_TEXT('Respuestas "&"de formulario 1'!G91),""[^0-9]"","""")))"),"+543513746660") -> +543513746660 | H91: ='Respuestas de formulario 1'!S91 -> 2023 | I91: =IFERROR(__xludf.DUMMYFUNCTION("IF('Respuestas de formulario 1'!I91="""","""",TO_TEXT('Respuestas de formulario 1'!I91))"),"Obra social") -> Obra social | J91: =IFERROR(__xludf.DUMMYFUNCTION("IF('Respuestas de formulario 1'!J91<>"""",UPPER(TRIM(TO_TEXT('Respuestas de formulario 1'!J91))),IF('Respuestas de formulario 1'!O91<>"""",UPPER(TRIM(TO_TEXT('Respuestas de formulario 1'!O91))),""""))"),"PREVENCIÓN") -> PREVENCIÓN | K91: =IFERROR(__xludf.DUMMYFUNCTION("IF('Respuestas de formulario 1'!K91="""","""",TO_TEXT('Respuestas de formulario 1'!K91))"),"") | L91: =IFERROR(__xludf.DUMMYFUNCTION("IF('Respuestas de formulario 1'!L91="""","""",TO_TEXT('Respuestas de formulario 1'!L91))"),"") | M91: =IFERROR(__xludf.DUMMYFUNCTION("IF('Respuestas de formulario 1'!M91="""","""",TO_TEXT('Respuestas de formulario 1'!M91))"),"") | N91: =IF(A91="","",IFERROR(YEAR(A91),"")) -> 2023 | O91: =IF(A91="","",IFERROR(TEXT(A91,"mmmm"),"")) -> marzo | P91: Oña Ignacio
A92: ='Respuestas de formulario 1'!A92 -> 45005.455 | B92: ='Respuestas de formulario 1'!B92 -> Depaul | C92: ='Respuestas de formulario 1'!C92 -> Emilia | D92: ='Respuestas de formulario 1'!D92 -> emiliadepaul.mkt@gmail.com | E92: ='Respuestas de formulario 1'!E92 -> 36598 | F92: ='Respuestas de formulario 1'!F92 -> 42383051 | G92: =IFERROR(__xludf.DUMMYFUNCTION("IF('Respuestas de formulario 1'!G92="""","""",IF(LEFT(REGEXREPLACE(TO_TEXT('Respuestas de formulario 1'!G92),""[^0-9]"",""""),2)=""54"",""+""&REGEXREPLACE(TO_TEXT('Respuestas de formulario 1'!G92),""[^0-9]"",""""),""+54""&REGEXREPLACE(TO_TEXT('Respuestas "&"de formulario 1'!G92),""[^0-9]"","""")))"),"+543517680758") -> +543517680758 | H92: ='Respuestas de formulario 1'!S92 -> 2023 | I92: =IFERROR(__xludf.DUMMYFUNCTION("IF('Respuestas de formulario 1'!I92="""","""",TO_TEXT('Respuestas de formulario 1'!I92))"),"Obra social") -> Obra social | J92: =IFERROR(__xludf.DUMMYFUNCTION("IF('Respuestas de formulario 1'!J92<>"""",UPPER(TRIM(TO_TEXT('Respuestas de formulario 1'!J92))),IF('Respuestas de formulario 1'!O92<>"""",UPPER(TRIM(TO_TEXT('Respuestas de formulario 1'!O92))),""""))"),"PREVENCIÓN") -> PREVENCIÓN | K92: =IFERROR(__xludf.DUMMYFUNCTION("IF('Respuestas de formulario 1'!K92="""","""",TO_TEXT('Respuestas de formulario 1'!K92))"),"") | L92: =IFERROR(__xludf.DUMMYFUNCTION("IF('Respuestas de formulario 1'!L92="""","""",TO_TEXT('Respuestas de formulario 1'!L92))"),"") | M92: =IFERROR(__xludf.DUMMYFUNCTION("IF('Respuestas de formulario 1'!M92="""","""",TO_TEXT('Respuestas de formulario 1'!M92))"),"") | N92: =IF(A92="","",IFERROR(YEAR(A92),"")) -> 2023 | O92: =IF(A92="","",IFERROR(TEXT(A92,"mmmm"),"")) -> marzo | P92: Depaul Emilia
A93: ='Respuestas de formulario 1'!A93 -> 45005.548 | B93: ='Respuestas de formulario 1'!B93 -> Menacho | C93: ='Respuestas de formulario 1'!C93 -> Silvia | D93: ='Respuestas de formulario 1'!D93 -> silviambaigorri@gmail.com | E93: ='Respuestas de formulario 1'!E93 -> 24935 | F93: ='Respuestas de formulario 1'!F93 -> 20346063 | G93: =IFERROR(__xludf.DUMMYFUNCTION("IF('Respuestas de formulario 1'!G93="""","""",IF(LEFT(REGEXREPLACE(TO_TEXT('Respuestas de formulario 1'!G93),""[^0-9]"",""""),2)=""54"",""+""&REGEXREPLACE(TO_TEXT('Respuestas de formulario 1'!G93),""[^0-9]"",""""),""+54""&REGEXREPLACE(TO_TEXT('Respuestas "&"de formulario 1'!G93),""[^0-9]"","""")))"),"+543513854962") -> +543513854962 | H93: ='Respuestas de formulario 1'!S93 -> 2023 | I93: =IFERROR(__xludf.DUMMYFUNCTION("IF('Respuestas de formulario 1'!I93="""","""",TO_TEXT('Respuestas de formulario 1'!I93))"),"Particular") -> Particular | J93: =IFERROR(__xludf.DUMMYFUNCTION("IF('Respuestas de formulario 1'!J93<>"""",UPPER(TRIM(TO_TEXT('Respuestas de formulario 1'!J93))),IF('Respuestas de formulario 1'!O93<>"""",UPPER(TRIM(TO_TEXT('Respuestas de formulario 1'!O93))),""""))"),"") | K93: =IFERROR(__xludf.DUMMYFUNCTION("IF('Respuestas de formulario 1'!K93="""","""",TO_TEXT('Respuestas de formulario 1'!K93))"),"") | L93: =IFERROR(__xludf.DUMMYFUNCTION("IF('Respuestas de formulario 1'!L93="""","""",TO_TEXT('Respuestas de formulario 1'!L93))"),"") | M93: =IFERROR(__xludf.DUMMYFUNCTION("IF('Respuestas de formulario 1'!M93="""","""",TO_TEXT('Respuestas de formulario 1'!M93))"),"") | N93: =IF(A93="","",IFERROR(YEAR(A93),"")) -> 2023 | O93: =IF(A93="","",IFERROR(TEXT(A93,"mmmm"),"")) -> marzo | P93: Menacho Silvia
A94: ='Respuestas de formulario 1'!A94 -> 45005.794 | B94: ='Respuestas de formulario 1'!B94 -> Fernandez Lopez | C94: ='Respuestas de formulario 1'!C94 -> Jeronimo | D94: ='Respuestas de formulario 1'!D94 -> jerofernandezlopez@gmail.com | E94: ='Respuestas de formulario 1'!E94 -> 39119 | F94: ='Respuestas de formulario 1'!F94 -> 47662640 | G94: =IFERROR(__xludf.DUMMYFUNCTION("IF('Respuestas de formulario 1'!G94="""","""",IF(LEFT(REGEXREPLACE(TO_TEXT('Respuestas de formulario 1'!G94),""[^0-9]"",""""),2)=""54"",""+""&REGEXREPLACE(TO_TEXT('Respuestas de formulario 1'!G94),""[^0-9]"",""""),""+54""&REGEXREPLACE(TO_TEXT('Respuestas "&"de formulario 1'!G94),""[^0-9]"","""")))"),"+543518069982") -> +543518069982 | H94: ='Respuestas de formulario 1'!S94 -> 2023 | I94: =IFERROR(__xludf.DUMMYFUNCTION("IF('Respuestas de formulario 1'!I94="""","""",TO_TEXT('Respuestas de formulario 1'!I94))"),"Particular") -> Particular | J94: =IFERROR(__xludf.DUMMYFUNCTION("IF('Respuestas de formulario 1'!J94<>"""",UPPER(TRIM(TO_TEXT('Respuestas de formulario 1'!J94))),IF('Respuestas de formulario 1'!O94<>"""",UPPER(TRIM(TO_TEXT('Respuestas de formulario 1'!O94))),""""))"),"") | K94: =IFERROR(__xludf.DUMMYFUNCTION("IF('Respuestas de formulario 1'!K94="""","""",TO_TEXT('Respuestas de formulario 1'!K94))"),"") | L94: =IFERROR(__xludf.DUMMYFUNCTION("IF('Respuestas de formulario 1'!L94="""","""",TO_TEXT('Respuestas de formulario 1'!L94))"),"") | M94: =IFERROR(__xludf.DUMMYFUNCTION("IF('Respuestas de formulario 1'!M94="""","""",TO_TEXT('Respuestas de formulario 1'!M94))"),"") | N94: =IF(A94="","",IFERROR(YEAR(A94),"")) -> 2023 | O94: =IF(A94="","",IFERROR(TEXT(A94,"mmmm"),"")) -> marzo | P94: Fernandez Lopez Jeronimo
A95: ='Respuestas de formulario 1'!A95 -> 45006.655 | B95: ='Respuestas de formulario 1'!B95 -> Sosa | C95: ='Respuestas de formulario 1'!C95 -> Carlos Alberto | D95: ='Respuestas de formulario 1'!D95 -> caro-elstein@hotmail.com | E95: ='Respuestas de formulario 1'!E95 -> 25511 | F95: ='Respuestas de formulario 1'!F95 -> 21013856 | G95: =IFERROR(__xludf.DUMMYFUNCTION("IF('Respuestas de formulario 1'!G95="""","""",IF(LEFT(REGEXREPLACE(TO_TEXT('Respuestas de formulario 1'!G95),""[^0-9]"",""""),2)=""54"",""+""&REGEXREPLACE(TO_TEXT('Respuestas de formulario 1'!G95),""[^0-9]"",""""),""+54""&REGEXREPLACE(TO_TEXT('Respuestas "&"de formulario 1'!G95),""[^0-9]"","""")))"),"+543513242191") -> +543513242191 | H95: ='Respuestas de formulario 1'!S95 -> 2023 | I95: =IFERROR(__xludf.DUMMYFUNCTION("IF('Respuestas de formulario 1'!I95="""","""",TO_TEXT('Respuestas de formulario 1'!I95))"),"Obra social") -> Obra social | J95: =IFERROR(__xludf.DUMMYFUNCTION("IF('Respuestas de formulario 1'!J95<>"""",UPPER(TRIM(TO_TEXT('Respuestas de formulario 1'!J95))),IF('Respuestas de formulario 1'!O95<>"""",UPPER(TRIM(TO_TEXT('Respuestas de formulario 1'!O95))),""""))"),"OSITAC") -> OSITAC | K95: =IFERROR(__xludf.DUMMYFUNCTION("IF('Respuestas de formulario 1'!K95="""","""",TO_TEXT('Respuestas de formulario 1'!K95))"),"") | L95: =IFERROR(__xludf.DUMMYFUNCTION("IF('Respuestas de formulario 1'!L95="""","""",TO_TEXT('Respuestas de formulario 1'!L95))"),"") | M95: =IFERROR(__xludf.DUMMYFUNCTION("IF('Respuestas de formulario 1'!M95="""","""",TO_TEXT('Respuestas de formulario 1'!M95))"),"") | N95: =IF(A95="","",IFERROR(YEAR(A95),"")) -> 2023 | O95: =IF(A95="","",IFERROR(TEXT(A95,"mmmm"),"")) -> marzo | P95: Sosa Carlos Alberto
A96: ='Respuestas de formulario 1'!A96 -> 45007.518 | B96: ='Respuestas de formulario 1'!B96 -> Romano | C96: ='Respuestas de formulario 1'!C96 -> Camilo Francisco | D96: ='Respuestas de formulario 1'!D96 -> camilofranciscoromano@gmail.com | E96: ='Respuestas de formulario 1'!E96 -> 38540 | F96: ='Respuestas de formulario 1'!F96 -> 46283518 | G96: =IFERROR(__xludf.DUMMYFUNCTION("IF('Respuestas de formulario 1'!G96="""","""",IF(LEFT(REGEXREPLACE(TO_TEXT('Respuestas de formulario 1'!G96),""[^0-9]"",""""),2)=""54"",""+""&REGEXREPLACE(TO_TEXT('Respuestas de formulario 1'!G96),""[^0-9]"",""""),""+54""&REGEXREPLACE(TO_TEXT('Respuestas "&"de formulario 1'!G96),""[^0-9]"","""")))"),"+543512486914") -> +543512486914 | H96: ='Respuestas de formulario 1'!S96 -> 2023 | I96: =IFERROR(__xludf.DUMMYFUNCTION("IF('Respuestas de formulario 1'!I96="""","""",TO_TEXT('Respuestas de formulario 1'!I96))"),"Obra social") -> Obra social | J96: =IFERROR(__xludf.DUMMYFUNCTION("IF('Respuestas de formulario 1'!J96<>"""",UPPER(TRIM(TO_TEXT('Respuestas de formulario 1'!J96))),IF('Respuestas de formulario 1'!O96<>"""",UPPER(TRIM(TO_TEXT('Respuestas de formulario 1'!O96))),""""))"),"MEDIFE") -> MEDIFE | K96: =IFERROR(__xludf.DUMMYFUNCTION("IF('Respuestas de formulario 1'!K96="""","""",TO_TEXT('Respuestas de formulario 1'!K96))"),"") | L96: =IFERROR(__xludf.DUMMYFUNCTION("IF('Respuestas de formulario 1'!L96="""","""",TO_TEXT('Respuestas de formulario 1'!L96))"),"") | M96: =IFERROR(__xludf.DUMMYFUNCTION("IF('Respuestas de formulario 1'!M96="""","""",TO_TEXT('Respuestas de formulario 1'!M96))"),"") | N96: =IF(A96="","",IFERROR(YEAR(A96),"")) -> 2023 | O96: =IF(A96="","",IFERROR(TEXT(A96,"mmmm"),"")) -> marzo | P96: Romano Camilo Francisco
A97: ='Respuestas de formulario 1'!A97 -> 45012.671 | B97: ='Respuestas de formulario 1'!B97 -> España luppo | C97: ='Respuestas de formulario 1'!C97 -> Emilia | D97: ='Respuestas de formulario 1'!D97 -> Emilia040905@gmail.com | E97: ='Respuestas de formulario 1'!E97 -> 38599 | F97: ='Respuestas de formulario 1'!F97 -> 46505684 | G97: =IFERROR(__xludf.DUMMYFUNCTION("IF('Respuestas de formulario 1'!G97="""","""",IF(LEFT(REGEXREPLACE(TO_TEXT('Respuestas de formulario 1'!G97),""[^0-9]"",""""),2)=""54"",""+""&REGEXREPLACE(TO_TEXT('Respuestas de formulario 1'!G97),""[^0-9]"",""""),""+54""&REGEXREPLACE(TO_TEXT('Respuestas "&"de formulario 1'!G97),""[^0-9]"","""")))"),"+543516166272") -> +543516166272 | H97: ='Respuestas de formulario 1'!S97 -> 2023 | I97: =IFERROR(__xludf.DUMMYFUNCTION("IF('Respuestas de formulario 1'!I97="""","""",TO_TEXT('Respuestas de formulario 1'!I97))"),"Particular") -> Particular | J97: =IFERROR(__xludf.DUMMYFUNCTION("IF('Respuestas de formulario 1'!J97<>"""",UPPER(TRIM(TO_TEXT('Respuestas de formulario 1'!J97))),IF('Respuestas de formulario 1'!O97<>"""",UPPER(TRIM(TO_TEXT('Respuestas de formulario 1'!O97))),""""))"),"") | K97: =IFERROR(__xludf.DUMMYFUNCTION("IF('Respuestas de formulario 1'!K97="""","""",TO_TEXT('Respuestas de formulario 1'!K97))"),"") | L97: =IFERROR(__xludf.DUMMYFUNCTION("IF('Respuestas de formulario 1'!L97="""","""",TO_TEXT('Respuestas de formulario 1'!L97))"),"") | M97: =IFERROR(__xludf.DUMMYFUNCTION("IF('Respuestas de formulario 1'!M97="""","""",TO_TEXT('Respuestas de formulario 1'!M97))"),"") | N97: =IF(A97="","",IFERROR(YEAR(A97),"")) -> 2023 | O97: =IF(A97="","",IFERROR(TEXT(A97,"mmmm"),"")) -> marzo | P97: España luppo Emilia
A98: ='Respuestas de formulario 1'!A98 -> 45012.676 | B98: ='Respuestas de formulario 1'!B98 -> Caminoa | C98: ='Respuestas de formulario 1'!C98 -> Abril | D98: ='Respuestas de formulario 1'!D98 -> Abril.caminoa16@gmail.com | E98: ='Respuestas de formulario 1'!E98 -> 36516 | F98: ='Respuestas de formulario 1'!F98 -> 42208997 | G98: =IFERROR(__xludf.DUMMYFUNCTION("IF('Respuestas de formulario 1'!G98="""","""",IF(LEFT(REGEXREPLACE(TO_TEXT('Respuestas de formulario 1'!G98),""[^0-9]"",""""),2)=""54"",""+""&REGEXREPLACE(TO_TEXT('Respuestas de formulario 1'!G98),""[^0-9]"",""""),""+54""&REGEXREPLACE(TO_TEXT('Respuestas "&"de formulario 1'!G98),""[^0-9]"","""")))"),"+542235414440") -> +542235414440 | H98: ='Respuestas de formulario 1'!S98 -> 2023 | I98: =IFERROR(__xludf.DUMMYFUNCTION("IF('Respuestas de formulario 1'!I98="""","""",TO_TEXT('Respuestas de formulario 1'!I98))"),"Particular") -> Particular | J98: =IFERROR(__xludf.DUMMYFUNCTION("IF('Respuestas de formulario 1'!J98<>"""",UPPER(TRIM(TO_TEXT('Respuestas de formulario 1'!J98))),IF('Respuestas de formulario 1'!O98<>"""",UPPER(TRIM(TO_TEXT('Respuestas de formulario 1'!O98))),""""))"),"") | K98: =IFERROR(__xludf.DUMMYFUNCTION("IF('Respuestas de formulario 1'!K98="""","""",TO_TEXT('Respuestas de formulario 1'!K98))"),"") | L98: =IFERROR(__xludf.DUMMYFUNCTION("IF('Respuestas de formulario 1'!L98="""","""",TO_TEXT('Respuestas de formulario 1'!L98))"),"") | M98: =IFERROR(__xludf.DUMMYFUNCTION("IF('Respuestas de formulario 1'!M98="""","""",TO_TEXT('Respuestas de formulario 1'!M98))"),"") | N98: =IF(A98="","",IFERROR(YEAR(A98),"")) -> 2023 | O98: =IF(A98="","",IFERROR(TEXT(A98,"mmmm"),"")) -> marzo | P98: Caminoa Abril
